Workbook

Sheet Input sheet
C1: Input cell | E1: Calculated cell
A3: Date of valuation | B3: Mar 31, 2025 | C3: Important: Before you run this spreadsheet, go into preferences in Excel and check under Calculation options
A4: Company name | B4: Lenovo Group Limited | C4: There should be a check against the iteration box. If there is not, you will get circular reasoning errors.
A5: Numbers from your base year below ( in consistent units)
B6: This year | C6: Last year | E6: Updated on January 2023 with updated Industry averages and risk premiums
A7: Country of incorporation | B7: Hong Kong
A8: Industry (US) | B8: Computers/Peripherals
A9: Industry (Global) | B9: Computers/Peripherals | C9: Last 10K | D9: Years since last 10K
A10: Revenues | B10: 69076.968 | C10: 56863.784 | D10: 0
A11: Operating income or EBIT | B11: 2006.902 | C11: 1990.822 | D11: 0.75
A12: Interest expense | B12: 293.595 | C12: 275.203
A13: Book value of equity | B13: 6659.917 | C13: 6081.187
A14: Book value of debt | B14: 5732.958 | C14: 3961.689
A15: Do you have R&D expenses to capitalize? | B15: Yes | C15: If you want to capitalize R&D, you have to input the numbers into the R&D worksheet.
A16: Do you have operating lease commitments? | B16: No | C16: If you lease or other contractual commitments that have not been converteed to debt already, say yes to this option and do the conversion.
A17: Cash and Marketable Securities | B17: 4728.124 | C17: 3559.831
A18: Cross holdings and other non-operating assets | B18: 1825.47 | C18: 1768.442
A19: Minority interests | B19: 1138.283 | C19: 1045.947
A20: Number of shares outstanding = | B20: 12404.659
A21: Current stock price = | B21: 11.83 | E21: Computed numbers: Here is what your company's numbers look like, relative to industry.
A22: Effective tax rate = | B22: 0.2 | E22: If you are not working in US dollars, you should add the inflation differential to the industry averages.
A23: Marginal tax rate = | B23: 0.165 | J23: Industry (US) | K23: Industry (Global) | L23: Global Distribution Stats
A24: The value drivers below (non-AI) | I24: Company | J24: Average | K24: Average | L24: 1st Quartile | M24: Median | N24: 3rd Quartile
A25: Revenue growth rate for next year | B25: 0.1 | E25: Revenue growth in the most recent year = | I25: =IF(C10>0,(B10/C10)^(1/D10)-1, "NA") | J25: =VLOOKUP(B8,'Industry Averages(US)'!A2:S95,3) | K25: =VLOOKUP(B9,'Industry Average Beta (Global)'!A2:N95,3) | L25: =VLOOKUP($B$9,'Input Stat Distributioons'!$A$3:$R$96,3,FALSE) | M25: =VLOOKUP($B$9,'Input Stat Distributioons'!$A$3:$R$96,4,FALSE) | N25: =VLOOKUP($B$9,'Input Stat Distributioons'!$A$3:$R$96,5,FALSE)
A26: Operating Margin for next year | B26: 0.029053128 | E26: Pre-tax operating margin in the most recent year = | I26: ='Valuation output'!B4 | J26: =VLOOKUP(B8,'Industry Averages(US)'!A2:AA95,4) | K26: =VLOOKUP(B9,'Industry Average Beta (Global)'!A2:N95,4) | L26: =VLOOKUP($B$9,'Input Stat Distributioons'!$A$3:$R$96,6,FALSE) | M26: =VLOOKUP($B$9,'Input Stat Distributioons'!$A$3:$R$96,7,FALSE) | N26: =VLOOKUP($B$9,'Input Stat Distributioons'!$A$3:$R$96,8,FALSE)
A27: Compounded annual revenue growth rate - years 2-5 = | B27: 0.08 | C27: Growth Lever | E27: Sales to capital ratio in most recent year = | I27: =B10/'Valuation output'!B58 | J27: =VLOOKUP(B8,'Industry Averages(US)'!A2:S95,14) | K27: =VLOOKUP(B9,'Industry Average Beta (Global)'!A2:N95,14) | L27: =VLOOKUP($B$9,'Input Stat Distributioons'!$A$3:$R$96,9,FALSE) | M27: =VLOOKUP($B$9,'Input Stat Distributioons'!$A$3:$R$96,10,FALSE) | N27: =VLOOKUP($B$9,'Input Stat Distributioons'!$A$3:$R$96,11,FALSE)
A28: Target pre-tax operating margin = | B28: 0.22484875 | C28: Profitability Lever | E28: Marginal sales to capital ratio = | I28: =IF(('Input sheet'!B10-'Input sheet'!C10)/(('Input sheet'!B13+'Input sheet'!B14-'Input sheet'!B17)-('Input sheet'!C13+'Input sheet'!C14-'Input sheet'!C17))>0,('Input sheet'!B10-'Input sheet'!C10)/(('Input sheet'!B13+'Input sheet'!B14-'Input sheet'!B17)-('Input sheet'!C13+'Input sheet'!C14-'Input sheet'!C17)),"NA")
A29: Year of convergence for margin | B29: 5 | C29: Speed of convergence level | E29: Return on invested capital in most recent year= | I29: ='Valuation output'!B7/'Valuation output'!B58 | J29: =VLOOKUP(B8,'Industry Averages(US)'!A2:S95,5) | K29: =VLOOKUP(B9,'Industry Average Beta (Global)'!A2:N95,5)
A30: Sales to capital ratio (for years 1-5) | B30: 3.6197887 | C30: Efficency of Growth Lever | E30: Standard deviation in stock prices = | J30: =VLOOKUP(B8,'Industry Averages(US)'!A2:S95,10) | K30: =VLOOKUP(B8,'Industry Average Beta (Global)'!A2:Z95,10)
A31: Sales to capital ratio (for years 6-10) | B31: 3.6197887 | E31: Cost of capital = | J31: =VLOOKUP(B8,'Industry Averages(US)'!A2:S95,13) | K31: =VLOOKUP(B8,'Industry Average Beta (Global)'!A2:Z95,13) | L31: =VLOOKUP($B$9,'Input Stat Distributioons'!$A$3:$R$96,12,FALSE) | M31: =VLOOKUP($B$9,'Input Stat Distributioons'!$A$3:$R$96,13,FALSE) | N31: =VLOOKUP($B$9,'Input Stat Distributioons'!$A$3:$R$96,14,FALSE)
A32: Market numbers
A33: Riskfree rate | B33: 0.0425 | E33: Valuation Output Feedback (for you to use to fine tune your inputs, if you want)
A34: Initial cost of capital = | B34: ='Cost of capital worksheet'!B13 | C34: Do not input. Go to cost of capital sheet. | E34: Revenues in year 10, based on your revenue growth = | J34: ='Valuation output'!L3+'Valuation output'!L14+'Valuation output'!L23
A35: Other inputs | E35: Pre-tax Operating Income in year 10, based on your operating margin = | J35: ='Valuation output'!M5+'Valuation output'!M16+'Valuation output'!M25
A36: Do you have employee options outstanding? | B36: No | E36: Return on invested capital in year 10, based on your sales/capital ratio = | J36: ='Valuation output'!L59
A37: Number of options outstanding = | B37: 0 | E37: Check the Diagnostics worksheet for more details.
A38: Average strike price = | B38: 0
A39: Average maturity = | B39: 0
A40: Standard deviation on stock price = | B40: 0
A42: Value Drivers for AI Chip business
B43: Current | C43: Year 10
A44: Total Market | B44: 0 | C44: 0
A45: NVIDIA's Market Share | B45: 0 | C45: 0
A46: Operating margin | B46: 0 | C46: 0
A48: Value Drivers for Auto Chip business
B49: Current | C49: Year 10
A50: Total Market | B50: 0 | C50: 0
A51: NVIDIA's Market Share | B51: 0 | C51: 0
A52: Operating margin | B52: 0 | C52: 0
A54: Default assumptions.
A55: In stable growth, I will assume that your firm will have a cost of capital similar to that of typical mature companies (riskfree rate + 4.5%)
A56: Do you want to override this assumption = | B56: Yes | C56: Mature companies generally see their risk levels approach the average
A57: If yes, enter the cost of capital after year 10 = | B57: 0.085 | C57: Though some sectors, even in stable growth, may have higher risk. If you change your risk free rate after year 10 (see cell B57 & 58), you should incorporate the change into your stable cost of capital estimate.
A58: I will assume that your firm will earn a return on capital equal to its cost of capital after year 10. I am assuming that whatever competitive advantages you have today will fade over time.
A59: Do you want to override this assumption = | B59: Yes | C59: Mature companies find it difficult to generate returns that exceed the cost of capital
A60: If yes, enter the return on capital you expect after year 10 | B60: 0.12 | C60: But there are significant exceptions among companies with long-lasting competitive advantages.
A61: I will assume that your firm has no chance of failure over the foreseeable future.
A62: Do you want to override this assumption = | B62: No | C62: Many young, growth companies fail, especially if they have trouble raising cash. Many distressed companies fail, because they have trouble making debt payments.
A63: If yes, enter the probability of failure = | B63: 0 | C63: Tough to estimate but a key input. Use the failure rate worksheet, if necessary.
A64: What do you want to tie your proceeds in failure to? | B64: V | C64: B: Book value of capital, V= Estimated fair value for the company
A65: Enter the distress proceeds as percentage of book or fair value | B65: 0.5 | C65: This can be zero, if the assets will be worth nothing if the firm fails.
A66: I assume that reinvestment in a year translates into growth in the next year, i.e., there is a one year lag between reinvesting and generating growth from that reinvestment.
A67: Do you want override this assumption = | B67: Yes
A68: If yes, enter a different lag (0 = no lag to 3 = lag of 3 years) | B68: 1
A69: I will assume that your effective tax rate will adjust to your marginal tax rate by your terminal year. If you override this assumption, I will leave the tax rate at your effective tax rate.
A70: Do you want to override this assumption = | B70: No
A71: I will assume that you have no losses carried forward from prior years ( NOL) coming into the valuation. If you have a money losing company, you may want to override tis.
A72: Do you want to override this assumption = | B72: No | C72: Check the financial statements.
A73: If yes, enter the NOL that you are carrying over into year 1 | B73: 0 | C73: An NOL will shield your income from taxes, even after you start making money.
A74: I will asssume that today's risk free rate will prevail in perpetuity. If you override this assumption, I will change the riskfree rate after year 10.
A75: Do you want to override this assumption = | B75: No | C75: If yes, you will be asked to enter a normal risk free rate and your growth in perpetuity will be adjusted accordingly.
A76: If yes, enter the riskfree rate after year 10 | B76: 0.02 | C76: Enter your estimate of what the riskfree rate (in your currency of choice) will be after year 10
A77: I will assume that the growth rate in perpetuity will be equal to the risk free rate. This allows for both valuation consistency and prevents "impossible" growth rates.
A78: Do you want to override this assumption = | B78: No | C78: This is an option to let you use a negative growth rate in perpetuity or to even liquidate the firm.
A79: If yes, enter the growth rate in perpetuity | B79: -0.05 | C79: This can be negative, if you feel the company will decline (and disappear) after growth is done. If you let it exceed the risk free rate, you are on your own in uncharted territory.
A80: I have assumed that none of the cash is trapped (in foreign countries) and that there is no additional tax liability coming due and that cash is a neutral asset.
A81: Do you want to override this assumption | B81: No
A82: If yes, enter trapped cash (if taxes) or entire balance (if mistrust) | B82: 0 | C82: Cash that is trapped in foreign markets (and subject to additoinal tax) or cash that is being discounted by the market (because of management mistrust)
A83: & Average tax rate of the foreign markets where the cash is trapped | B83: 0.15 | C83: Additional tax rate due on trapped cash or discount being applied to cash balance because of mistrust.

Sheet Valuation output
B1: Base year | C1: 1 | D1: 2 | E1: 3 | F1: 4 | G1: 5 | H1: 6 | I1: 7 | J1: 8 | K1: 9 | L1: 10 | M1: Terminal year | N1: Terminal Value
A2: Rest Revenue growth rate | C2: ='Input sheet'!B25 | D2: ='Input sheet'!B27 | E2: =D2 | F2: =E2 | G2: =F2 | H2: =G2-((G2-$M$2)/5) | I2: =G2-((G2-$M$2)/5)*2 | J2: =G2-((G2-$M$2)/5)*3 | K2: =G2-((G2-$M$2)/5)*4 | L2: =G2-((G2-$M$2)/5)*5 | M2: =IF('Input sheet'!B78="Yes",'Input sheet'!B79,IF('Input sheet'!B75="Yes",'Input sheet'!B76,'Input sheet'!B33))
A3: Rest Revenues | B3: ='Input sheet'!B10-B14-B23 | C3: =B3*(1+C2) | D3: =C3*(1+D2) | E3: =D3*(1+E2) | F3: =E3*(1+F2) | G3: =F3*(1+G2) | H3: =G3*(1+H2) | I3: =H3*(1+I2) | J3: =I3*(1+J2) | ... M3: =L3*(1+M2)
A4: EBIT (Operating) margin | B4: =B5/B3 | C4: ='Input sheet'!B26 | D4: =IF(D1>'Input sheet'!$B$29,'Input sheet'!$B$28,'Input sheet'!$B$28-(('Input sheet'!$B$28-$C$15)/'Input sheet'!$B$29)*('Input sheet'!$B$29-D1)) | E4: =IF(E1>'Input sheet'!$B$29,'Input sheet'!$B$28,'Input sheet'!$B$28-(('Input sheet'!$B$28-$C$4)/'Input sheet'!$B$29)*('Input sheet'!$B$29-E1)) | F4: =IF(F1>'Input sheet'!$B$29,'Input sheet'!$B$28,'Input sheet'!$B$28-(('Input sheet'!$B$28-$C$4)/'Input sheet'!$B$29)*('Input sheet'!$B$29-F1)) | G4: =IF(G1>'Input sheet'!$B$29,'Input sheet'!$B$28,'Input sheet'!$B$28-(('Input sheet'!$B$28-$C$4)/'Input sheet'!$B$29)*('Input sheet'!$B$29-G1)) | H4: =IF(H1>'Input sheet'!$B$29,'Input sheet'!$B$28,'Input sheet'!$B$28-(('Input sheet'!$B$28-$C$4)/'Input sheet'!$B$29)*('Input sheet'!$B$29-H1)) | I4: =IF(I1>'Input sheet'!$B$29,'Input sheet'!$B$28,'Input sheet'!$B$28-(('Input sheet'!$B$28-$C$4)/'Input sheet'!$B$29)*('Input sheet'!$B$29-I1)) | J4: =IF(J1>'Input sheet'!$B$29,'Input sheet'!$B$28,'Input sheet'!$B$28-(('Input sheet'!$B$28-$C$4)/'Input sheet'!$B$29)*('Input sheet'!$B$29-J1)) | K4: =IF(K1>'Input sheet'!$B$29,'Input sheet'!$B$28,'Input sheet'!$B$28-(('Input sheet'!$B$28-$C$4)/'Input sheet'!$B$29)*('Input sheet'!$B$29-K1)) | L4: =IF(L1>'Input sheet'!$B$29,'Input sheet'!$B$28,'Input sheet'!$B$28-(('Input sheet'!$B$28-$C$4)/'Input sheet'!$B$29)*('Input sheet'!$B$29-L1)) | M4: =L4
A5: EBIT (Operating income) | B5: =IF('Input sheet'!B16="Yes",IF('Input sheet'!B15="Yes",'Input sheet'!B11+'Operating lease converter'!F32+'R& D converter'!D39,'Input sheet'!B11+'Operating lease converter'!F32),IF('Input sheet'!B15="Yes",'Input sheet'!B11+'R& D converter'!D39,'Input sheet'!B11))-B14*B15-B23*B24 | C5: =C4*C3 | D5: =D4*D3 | E5: =E4*E3 | F5: =F4*F3 | G5: =G4*G3 | H5: =H4*H3 | I5: =I4*I3 | J5: =J4*J3 | ... M5: =M4*M3
A6: Tax rate | B6: ='Input sheet'!B22 | C6: =B6 | D6: =C6 | E6: =D6 | F6: =E6 | G6: =F6 | H6: =G6+($M$6-$G$6)/5 | I6: =H6+($M$6-$G$6)/5 | J6: =I6+($M$6-$G$6)/5 | K6: =J6+($M$6-$G$6)/5 | L6: =K6+($M$6-$G$6)/5 | M6: =IF('Input sheet'!B70="Yes",'Input sheet'!B22,'Input sheet'!B23)
A7: EBIT(1-t) | B7: =IF(B5>0,B5*(1-B6),B5) | C7: =IF(C5>0,IF(C5<B10,C5,C5-(C5-B10)*C6),C5) | D7: =IF(D5>0,IF(D5<C10,D5,D5-(D5-C10)*D6),D5) | E7: =IF(E5>0,IF(E5<D10,E5,E5-(E5-D10)*E6),E5) | F7: =IF(F5>0,IF(F5<E10,F5,F5-(F5-E10)*F6),F5) | G7: =IF(G5>0,IF(G5<F10,G5,G5-(G5-F10)*G6),G5) | H7: =IF(H5>0,IF(H5<G10,H5,H5-(H5-G10)*H6),H5) | I7: =IF(I5>0,IF(I5<H10,I5,I5-(I5-H10)*I6),I5) | J7: =IF(J5>0,IF(J5<I10,J5,J5-(J5-I10)*J6),J5) | ... L7: =IF(L5>0,IF(L5<K10,L5,L5-(L5-K10)*L6),L5) | M7: =M5*(1-M6)
A8: - Reinvestment | C8: =IF('Input sheet'!$B$67="No",(D3-C3)/C57,IF('Input sheet'!$B$68=0,(C3-B3)/C57,IF('Input sheet'!$B$68=2,(E3-D3)/C57,IF('Input sheet'!$B$68=3,(F3-E3)/C57,(D3-C3)/C57)))) | D8: =IF('Input sheet'!$B$67="No",(E3-D3)/D57,IF('Input sheet'!$B$68=0,(D3-C3)/D57,IF('Input sheet'!$B$68=2,(F3-E3)/D57,IF('Input sheet'!$B$68=3,(G3-F3)/D57,(E3-D3)/D57)))) | E8: =IF('Input sheet'!$B$67="No",(F3-E3)/E57,IF('Input sheet'!$B$68=0,(E3-D3)/E57,IF('Input sheet'!$B$68=2,(G3-F3)/E57,IF('Input sheet'!$B$68=3,(H3-G3)/E57,(F3-E3)/E57)))) | F8: =IF('Input sheet'!$B$67="No",(G3-F3)/F57,IF('Input sheet'!$B$68=0,(F3-E3)/F57,IF('Input sheet'!$B$68=2,(H3-G3)/F57,IF('Input sheet'!$B$68=3,(I3-H3)/F57,(G3-F3)/F57)))) | G8: =IF('Input sheet'!$B$67="No",(H3-G3)/G57,IF('Input sheet'!$B$68=0,(G3-F3)/G57,IF('Input sheet'!$B$68=2,(I3-H3)/G57,IF('Input sheet'!$B$68=3,(J3-I3)/G57,(H3-G3)/G57)))) | H8: =IF('Input sheet'!$B$67="No",(I3-H3)/H57,IF('Input sheet'!$B$68=0,(H3-G3)/H57,IF('Input sheet'!$B$68=2,(J3-I3)/H57,IF('Input sheet'!$B$68=3,(K3-J3)/H57,(I3-H3)/H57)))) | I8: =IF('Input sheet'!$B$67="No",(J3-I3)/I57,IF('Input sheet'!$B$68=0,(I3-H3)/I57,IF('Input sheet'!$B$68=2,(K3-J3)/I57,IF('Input sheet'!$B$68=3,(L3-K3)/I57,(J3-I3)/I57)))) | J8: =IF('Input sheet'!$B$67="No",(K3-J3)/J57,IF('Input sheet'!$B$68=0,(J3-I3)/J57,IF('Input sheet'!$B$68=2,(L3-K3)/J57,IF('Input sheet'!$B$68=3,(M3-L3)/J57,(K3-J3)/J57)))) | K8: =IF('Input sheet'!$B$67="No",(L3-K3)/K57,IF('Input sheet'!$B$68=0,(K3-J3)/K57,IF('Input sheet'!$B$68=2,L3*L2/K57,IF('Input sheet'!$B$68=3,M3*M2/K57,(L3-K3)/K57)))) | L8: =IF('Input sheet'!$B$67="No",(M3-L3)/L57,IF('Input sheet'!$B$68=0,(L3-K3)/L57,IF('Input sheet'!$B$68=2,M3*M2/L57,IF('Input sheet'!$B$68=3,(M3*(1+M2)^2-M3*(1+M2))/L57,(M3-L3)/L57)))) | M8: =IF(M2>0,(M2/M59)*M7,0)
A9: FCFF | C9: =C7-C8 | D9: =D7-D8 | E9: =E7-E8 | F9: =F7-F8 | G9: =G7-G8 | H9: =H7-H8 | I9: =I7-I8 | J9: =J7-J8 | ... M9: =M7-M8 | N9: =M9/(M30-M2)
A10: NOL | B10: =IF('Input sheet'!B72="Yes",'Input sheet'!B73,0) | C10: =IF(C5<0,B10-C5,IF(B10>C5,B10-C5,0)) | D10: =IF(D5<0,C10-D5,IF(C10>D5,C10-D5,0)) | E10: =IF(E5<0,D10-E5,IF(D10>E5,D10-E5,0)) | F10: =IF(F5<0,E10-F5,IF(E10>F5,E10-F5,0)) | G10: =IF(G5<0,F10-G5,IF(F10>G5,F10-G5,0)) | H10: =IF(H5<0,G10-H5,IF(G10>H5,G10-H5,0)) | I10: =IF(I5<0,H10-I5,IF(H10>I5,H10-I5,0)) | J10: =IF(J5<0,I10-J5,IF(I10>J5,I10-J5,0)) | ... M10: =IF(M5<0,L10-M5,IF(L10>M5,L10-M5,0))
A12: Total Market (AI) | B12: ='Input sheet'!B44 | C12: =(G12-B12)/5+B12 | D12: =(G12-B12)/5+C12 | E12: =(G12-B12)/5+D12 | F12: =(G12-B12)/5+E12 | G12: =B12+3*(L12-B12)/5 | H12: =(L12-G12)/5+G12 | I12: =(L12-G12)/5+H12 | J12: =(L12-G12)/5+I12 | K12: =(L12-G12)/5+J12 | L12: ='Input sheet'!C44 | M12: =L12*(1+M2)
A13: Nvidia Market share (AI) | B13: ='Input sheet'!B45 | C13: =B13-($B$13-$L$13)/10 | D13: =C13-($B$13-$L$13)/10 | E13: =D13-($B$13-$L$13)/10 | F13: =E13-($B$13-$L$13)/10 | G13: =F13-($B$13-$L$13)/10 | H13: =G13-($B$13-$L$13)/10 | I13: =H13-($B$13-$L$13)/10 | J13: =I13-($B$13-$L$13)/10 | K13: =J13-($B$13-$L$13)/10 | L13: ='Input sheet'!C45 | M13: =L13
A14: Revenues from AI | B14: =B12*B13 | C14: =C12*C13 | D14: =D12*D13 | E14: =E12*E13 | F14: =F12*F13 | G14: =G12*G13 | H14: =H12*H13 | I14: =I12*I13 | ... M14: =M12*M13
A15: Operating Margin | B15: ='Input sheet'!B46 | C15: =B15 | D15: =IF(D1>'Input sheet'!$B$29,'Input sheet'!$C$46,'Input sheet'!$C$46-(('Input sheet'!$C$46-$C$15)/'Input sheet'!$B$29)*('Input sheet'!$B$29-D1)) | E15: =IF(E1>'Input sheet'!$B$29,'Input sheet'!$C$46,'Input sheet'!$C$46-(('Input sheet'!$C$46-$C$15)/'Input sheet'!$B$29)*('Input sheet'!$B$29-E1)) | F15: =IF(F1>'Input sheet'!$B$29,'Input sheet'!$C$46,'Input sheet'!$C$46-(('Input sheet'!$C$46-$C$15)/'Input sheet'!$B$29)*('Input sheet'!$B$29-F1)) | G15: =IF(G1>'Input sheet'!$B$29,'Input sheet'!$C$46,'Input sheet'!$C$46-(('Input sheet'!$C$46-$C$15)/'Input sheet'!$B$29)*('Input sheet'!$B$29-G1)) | H15: =IF(H1>'Input sheet'!$B$29,'Input sheet'!$C$46,'Input sheet'!$C$46-(('Input sheet'!$C$46-$C$15)/'Input sheet'!$B$29)*('Input sheet'!$B$29-H1)) | I15: =IF(I1>'Input sheet'!$B$29,'Input sheet'!$C$46,'Input sheet'!$C$46-(('Input sheet'!$C$46-$C$15)/'Input sheet'!$B$29)*('Input sheet'!$B$29-I1)) | J15: =IF(J1>'Input sheet'!$B$29,'Input sheet'!$C$46,'Input sheet'!$C$46-(('Input sheet'!$C$46-$C$15)/'Input sheet'!$B$29)*('Input sheet'!$B$29-J1)) | K15: =IF(K1>'Input sheet'!$B$29,'Input sheet'!$C$46,'Input sheet'!$C$46-(('Input sheet'!$C$46-$C$15)/'Input sheet'!$B$29)*('Input sheet'!$B$29-K1)) | L15: =IF(L1>'Input sheet'!$B$29,'Input sheet'!$C$46,'Input sheet'!$C$46-(('Input sheet'!$C$46-$C$15)/'Input sheet'!$B$29)*('Input sheet'!$B$29-L1)) | M15: =L15
A16: Operating Income | B16: =B14*B15 | C16: =C14*C15 | D16: =D14*D15 | E16: =E14*E15 | F16: =F14*F15 | G16: =G14*G15 | H16: =H14*H15 | I16: =I14*I15 | ... M16: =M14*M15
A17: EBIT (1-t) | B17: =B16*(1-B6) | C17: =C16*(1-C6) | D17: =D16*(1-D6) | E17: =E16*(1-E6) | F17: =F16*(1-F6) | G17: =G16*(1-G6) | H17: =H16*(1-H6) | I17: =I16*(1-I6) | ... M17: =M16*(1-M6)
A18: - Reinvestment | C18: =IF('Input sheet'!$B$67="No",(D14-C14)/C57,IF('Input sheet'!$B$68=0,(D14-B14)/C57,IF('Input sheet'!$B$68=2,(E14-D14)/C57,IF('Input sheet'!$B$68=3,(F14-E14)/C57,(D14-C14)/C57)))) | D18: =IF('Input sheet'!$B$67="No",(E14-D14)/D57,IF('Input sheet'!$B$68=0,(E14-C14)/D57,IF('Input sheet'!$B$68=2,(F14-E14)/D57,IF('Input sheet'!$B$68=3,(G14-F14)/D57,(E14-D14)/D57)))) | E18: =IF('Input sheet'!$B$67="No",(F14-E14)/E57,IF('Input sheet'!$B$68=0,(F14-D14)/E57,IF('Input sheet'!$B$68=2,(G14-F14)/E57,IF('Input sheet'!$B$68=3,(H14-G14)/E57,(F14-E14)/E57)))) | F18: =IF('Input sheet'!$B$67="No",(G14-F14)/F57,IF('Input sheet'!$B$68=0,(G14-E14)/F57,IF('Input sheet'!$B$68=2,(H14-G14)/F57,IF('Input sheet'!$B$68=3,(I14-H14)/F57,(G14-F14)/F57)))) | G18: =IF('Input sheet'!$B$67="No",(H14-G14)/G57,IF('Input sheet'!$B$68=0,(H14-F14)/G57,IF('Input sheet'!$B$68=2,(I14-H14)/G57,IF('Input sheet'!$B$68=3,(J14-I14)/G57,(H14-G14)/G57)))) | H18: =IF('Input sheet'!$B$67="No",(I14-H14)/H57,IF('Input sheet'!$B$68=0,(I14-G14)/H57,IF('Input sheet'!$B$68=2,(J14-I14)/H57,IF('Input sheet'!$B$68=3,(K14-J14)/H57,(I14-H14)/H57)))) | I18: =IF('Input sheet'!$B$67="No",(J14-I14)/I57,IF('Input sheet'!$B$68=0,(J14-H14)/I57,IF('Input sheet'!$B$68=2,(K14-J14)/I57,IF('Input sheet'!$B$68=3,(L14-K14)/I57,(J14-I14)/I57)))) | J18: =IF('Input sheet'!$B$67="No",(K14-J14)/J57,IF('Input sheet'!$B$68=0,(K14-I14)/J57,IF('Input sheet'!$B$68=2,(L14-K14)/J57,IF('Input sheet'!$B$68=3,(M14-L14)/J57,(K14-J14)/J57)))) | K18: =IF('Input sheet'!$B$67="No",(L14-K14)/K57,IF('Input sheet'!$B$68=0,(K14-J14)/K57,IF('Input sheet'!$B$68=2,L12*L2/K57,IF('Input sheet'!$B$68=3,M14*M2/K57,(L14-K14)/K57)))) | L18: =IF('Input sheet'!$B$67="No",(M14-L14)/L57,IF('Input sheet'!$B$68=0,(L14-K14)/L57,IF('Input sheet'!$B$68=2,M14*M2/L57,IF('Input sheet'!$B$68=3,(M14*(1+M2)*M2)/L57,(M14-L14)/L57)))) | M18: =IF(M2>0,(M2/M59)*M17,0)
A19: FCFF (AI) | C19: =C17-C18 | D19: =D17-D18 | E19: =E17-E18 | F19: =F17-F18 | G19: =G17-G18 | H19: =H17-H18 | I19: =I17-I18 | J19: =J17-J18 | ... M19: =M17-M18 | N19: =M19/(M30-M2)
A21: Total Market (Auto) | B21: ='Input sheet'!B50 | C21: =(G21-B21)/5+B21 | D21: =(G21-B21)/5+C21 | E21: =(G21-B21)/5+D21 | F21: =(G21-B21)/5+E21 | G21: =B21+2*(L21-B21)/3 | H21: =(L21-G21)/5+G21 | I21: =(L21-G21)/5+H21 | J21: =(L21-G21)/5+I21 | K21: =(L21-G21)/5+J21 | L21: ='Input sheet'!C50 | M21: =L21*(1+M2)
A22: Nvidia Market share (Auto) | B22: ='Input sheet'!B51 | C22: =B22-($B$22-$L$22)/10 | D22: =C22-($B$22-$L$22)/10 | E22: =D22-($B$22-$L$22)/10 | F22: =E22-($B$22-$L$22)/10 | G22: =F22-($B$22-$L$22)/10 | H22: =G22-($B$22-$L$22)/10 | I22: =H22-($B$22-$L$22)/10 | J22: =I22-($B$22-$L$22)/10 | K22: =J22-($B$22-$L$22)/10 | L22: ='Input sheet'!C51 | M22: =L22
A23: Revenues from Auto | B23: =B21*B22 | C23: =C21*C22 | D23: =D21*D22 | E23: =E21*E22 | F23: =F21*F22 | G23: =G21*G22 | H23: =H21*H22 | I23: =I21*I22 | ... M23: =M21*M22
A24: Operating Margin | B24: ='Input sheet'!B52 | C24: ='Input sheet'!B26 | D24: =IF(D1>'Input sheet'!$B$29,'Input sheet'!$C$52,'Input sheet'!$C$52-(('Input sheet'!$C$52-$C$24)/'Input sheet'!$B$29)*('Input sheet'!$B$29-D1)) | E24: =IF(E1>'Input sheet'!$B$29,'Input sheet'!$C$52,'Input sheet'!$C$52-(('Input sheet'!$C$52-$C$24)/'Input sheet'!$B$29)*('Input sheet'!$B$29-E1)) | F24: =IF(F1>'Input sheet'!$B$29,'Input sheet'!$C$52,'Input sheet'!$C$52-(('Input sheet'!$C$52-$C$24)/'Input sheet'!$B$29)*('Input sheet'!$B$29-F1)) | G24: =IF(G1>'Input sheet'!$B$29,'Input sheet'!$C$52,'Input sheet'!$C$52-(('Input sheet'!$C$52-$C$24)/'Input sheet'!$B$29)*('Input sheet'!$B$29-G1)) | H24: =IF(H1>'Input sheet'!$B$29,'Input sheet'!$C$52,'Input sheet'!$C$52-(('Input sheet'!$C$52-$C$24)/'Input sheet'!$B$29)*('Input sheet'!$B$29-H1)) | I24: =IF(I1>'Input sheet'!$B$29,'Input sheet'!$C$52,'Input sheet'!$C$52-(('Input sheet'!$C$52-$C$24)/'Input sheet'!$B$29)*('Input sheet'!$B$29-I1)) | J24: =IF(J1>'Input sheet'!$B$29,'Input sheet'!$C$52,'Input sheet'!$C$52-(('Input sheet'!$C$52-$C$24)/'Input sheet'!$B$29)*('Input sheet'!$B$29-J1)) | K24: =IF(K1>'Input sheet'!$B$29,'Input sheet'!$C$52,'Input sheet'!$C$52-(('Input sheet'!$C$52-$C$24)/'Input sheet'!$B$29)*('Input sheet'!$B$29-K1)) | L24: =IF(L1>'Input sheet'!$B$29,'Input sheet'!$C$52,'Input sheet'!$C$52-(('Input sheet'!$C$52-$C$24)/'Input sheet'!$B$29)*('Input sheet'!$B$29-L1)) | M24: =L24
A25: Operating Income | B25: =B23*B24 | C25: =C23*C24 | D25: =D23*D24 | E25: =E23*E24 | F25: =F23*F24 | G25: =G23*G24 | H25: =H23*H24 | I25: =I23*I24 | ... M25: =M23*M24
A26: EBIT (1-t) | B26: =B25*(1-B6) | C26: =C25*(1-C6) | D26: =D25*(1-D6) | E26: =E25*(1-E6) | F26: =F25*(1-F6) | G26: =G25*(1-G6) | H26: =H25*(1-H6) | I26: =I25*(1-I6) | ... M26: =M25*(1-M6)
A27: - Reinvestment | C27: =IF('Input sheet'!$B$67="No",(D23-C23)/C57,IF('Input sheet'!$B$68=0,(D23-B23)/C57,IF('Input sheet'!$B$68=2,(E23-D23)/C57,IF('Input sheet'!$B$68=3,(F23-E23)/C57,(D23-C23)/C57)))) | D27: =IF('Input sheet'!$B$67="No",(E23-D23)/D57,IF('Input sheet'!$B$68=0,(E23-C23)/D57,IF('Input sheet'!$B$68=2,(F23-E23)/D57,IF('Input sheet'!$B$68=3,(G23-F23)/D57,(E23-D23)/D57)))) | E27: =IF('Input sheet'!$B$67="No",(F23-E23)/E57,IF('Input sheet'!$B$68=0,(F23-D23)/E57,IF('Input sheet'!$B$68=2,(G23-F23)/E57,IF('Input sheet'!$B$68=3,(H23-G23)/E57,(F23-E23)/E57)))) | F27: =IF('Input sheet'!$B$67="No",(G23-F23)/F57,IF('Input sheet'!$B$68=0,(G23-E23)/F57,IF('Input sheet'!$B$68=2,(H23-G23)/F57,IF('Input sheet'!$B$68=3,(I23-H23)/F57,(G23-F23)/F57)))) | G27: =IF('Input sheet'!$B$67="No",(H23-G23)/G57,IF('Input sheet'!$B$68=0,(H23-F23)/G57,IF('Input sheet'!$B$68=2,(I23-H23)/G57,IF('Input sheet'!$B$68=3,(J23-I23)/G57,(H23-G23)/G57)))) | H27: =IF('Input sheet'!$B$67="No",(I23-H23)/H57,IF('Input sheet'!$B$68=0,(I23-G23)/H57,IF('Input sheet'!$B$68=2,(J23-I23)/H57,IF('Input sheet'!$B$68=3,(K23-J23)/H57,(I23-H23)/H57)))) | I27: =IF('Input sheet'!$B$67="No",(J23-I23)/I57,IF('Input sheet'!$B$68=0,(J23-H23)/I57,IF('Input sheet'!$B$68=2,(K23-J23)/I57,IF('Input sheet'!$B$68=3,(L23-K23)/I57,(J23-I23)/I57)))) | J27: =IF('Input sheet'!$B$67="No",(K23-J23)/J57,IF('Input sheet'!$B$68=0,(K23-I23)/J57,IF('Input sheet'!$B$68=2,(L23-K23)/J57,IF('Input sheet'!$B$68=3,(M23-L23)/J57,(K23-J23)/J57)))) | K27: =IF('Input sheet'!$B$67="No",(L23-K23)/K57,IF('Input sheet'!$B$68=0,(K23-J23)/K57,IF('Input sheet'!$B$68=2,L12*L2/K57,IF('Input sheet'!$B$68=3,M23*M2/K57,(L23-K23)/K57)))) | L27: =IF('Input sheet'!$B$67="No",(M23-L23)/L57,IF('Input sheet'!$B$68=0,(L23-K23)/L57,IF('Input sheet'!$B$68=2,M23*M2/L57,IF('Input sheet'!$B$68=3,(M23*(1+M2)*M2)/L57,(M23-L23)/L57)))) | M27: =IF(M2>0,(M2/M59)*M26,0)
A28: FCFF (AI) | C28: =C26-C27 | D28: =D26-D27 | E28: =E26-E27 | F28: =F26-F27 | G28: =G26-G27 | H28: =H26-H27 | I28: =I26-I27 | J28: =J26-J27 | ... M28: =M26-M27 | N28: =M28/(M30-M2)
A30: Cost of capital | C30: ='Input sheet'!B34 | D30: =C30 | E30: =D30 | F30: =E30 | G30: =F30 | H30: =G30-($G$30-$M$30)/5 | I30: =H30-($G$30-$M$30)/5 | J30: =I30-($G$30-$M$30)/5 | K30: =J30-($G$30-$M$30)/5 | L30: =K30-($G$30-$M$30)/5 | M30: =IF('Input sheet'!B56="Yes",'Input sheet'!B57,IF('Input sheet'!B75="Yes",'Input sheet'!B76+'Country equity risk premiums'!B1,'Input sheet'!B33+'Country equity risk premiums'!B1))
A31: Cumulated discount factor | C31: =1/(1+C30) | D31: =C31*(1/(1+D30)) | E31: =D31*(1/(1+E30)) | F31: =E31*(1/(1+F30)) | G31: =F31*(1/(1+G30)) | H31: =G31*(1/(1+H30)) | I31: =H31*(1/(1+I30)) | J31: =I31*(1/(1+J30)) | K31: =J31*(1/(1+K30)) | L31: =K31*(1/(1+L30))
A32: PV(FCFF from rest) | C32: =C9*C31 | D32: =D9*D31 | E32: =E9*E31 | F32: =F9*F31 | G32: =G9*G31 | H32: =H9*H31 | I32: =I9*I31 | J32: =J9*J31 | ... L32: =L9*L31
A33: PV (FCFF frrom AI) | C33: =C19*C31 | D33: =D19*D31 | E33: =E19*E31 | F33: =F19*F31 | G33: =G19*G31 | H33: =H19*H31 | I33: =I19*I31 | J33: =J19*J31 | ... L33: =L19*L31
A34: PV(FCFF from Auto) | C34: =C28*C31 | D34: =D28*D31 | E34: =E28*E31 | F34: =F28*F31 | G34: =G28*G31 | H34: =H28*H31 | I34: =I28*I31 | J34: =J28*J31 | ... L34: =L28*L31
A37: Value of Rest | B37: =SUM(C32:L32)+N9*L31
A38: Value of AI | B38: =SUM(C33:L33)+N19*L31
A39: Value of Auto | B39: =SUM(C34:L34)+N28*L31
A40: Value as Going Concern = | B40: =SUM(B37:B39)
A41: Probability of failure = | B41: =IF('Input sheet'!B62="Yes",'Input sheet'!B63,0)
A42: Proceeds if firm fails = | B42: =IF('Input sheet'!B64="B",('Input sheet'!B13+'Input sheet'!B14)*'Input sheet'!B65,'Valuation output'!B40*'Input sheet'!B65)
A43: Value of operating assets = | B43: =B40*(1-B41)+B42*B41
A44: - Debt | B44: =IF('Input sheet'!B16="Yes",'Input sheet'!B14+'Operating lease converter'!C28,'Input sheet'!B14)
A45: - Minority interests | B45: ='Input sheet'!B19
A46: + Cash | B46: =IF('Input sheet'!B81="YES",'Input sheet'!B17-'Input sheet'!B82*('Input sheet'!B23-'Input sheet'!B83),'Input sheet'!B17)
A47: + Non-operating assets | B47: ='Input sheet'!B18
A48: Value of equity | B48: =B43-B44-B45+B46+B47
A49: - Value of options | B49: =IF('Input sheet'!B36="No",0,'Option value'!B29)
A50: Value of equity in common stock | B50: =B48-B49
A51: Number of shares | B51: ='Input sheet'!B20
A52: Estimated value /share | B52: =B50/B51
A53: Price | B53: ='Input sheet'!B21
A54: Price as % of value | B54: =B53/B52
A56: Implied variables | M56: After year 10
A57: Sales to capital ratio | C57: ='Input sheet'!B30 | D57: ='Input sheet'!B30 | E57: =D57 | F57: =E57 | G57: ='Input sheet'!B31 | H57: =G57 | I57: =H57 | J57: =I57 | K57: =J57 | L57: =K57
A58: Invested capital | B58: =IF('Input sheet'!B16="Yes",IF('Input sheet'!B15="Yes",'Input sheet'!B13+'Input sheet'!B14-'Input sheet'!B17+'Operating lease converter'!F33+'R& D converter'!D35,'Input sheet'!B13+'Input sheet'!B14-'Input sheet'!B17+'Operating lease converter'!F33),IF('Input sheet'!B15="Yes",'Input sheet'!B13+'Input sheet'!B14-'Input sheet'!B17+'R& D converter'!D35,'Input sheet'!B13+'Input sheet'!B14-'Input sheet'!B17)) | C58: =B58+C8+C18+C27 | D58: =C58+D8+D18+D27 | E58: =D58+E8+E18+E27 | F58: =E58+F8+F18+F27 | G58: =F58+G8+G18+G27 | H58: =G58+H8+H18+H27 | I58: =H58+I8+I18+I27 | J58: =I58+J8+J18+J27 | ... L58: =K58+L8+L18+L27
A59: ROIC | B59: =((B3*B4+B14*B15+B23*B24)*(1-B6))/B58 | C59: =(C7+C17+C26)/B58 | D59: =(D7+D17+D26)/C58 | E59: =(E7+E17+E26)/D58 | F59: =(F7+F17+F26)/E58 | G59: =(G7+G17+G26)/F58 | H59: =(H7+H17+H26)/G58 | I59: =(I7+I17+I26)/H58 | J59: =(J7+J17+J26)/I58 | ... L59: =(L7+L17+L26)/K58 | M59: =IF('Input sheet'!B59="Yes",'Input sheet'!B60,'Valuation output'!#REF!)

Sheet Stories to Numbers
A1: ='Input sheet'!B4 | G1: ='Input sheet'!B3
A2: The Opportunistic Chip Maker, after a DeepSeek Disruption
A3: NVIDIA has a history of innovation and opportunism in the chip business, often investing ahead of large trends in demand in crypto and gaming and now in AI and auto. Its early entry into the AI chip business will allow it to dominate this business, but the DeepSeek entry has disrupted the market, creating a two tier market - one commoditized and the other premier; Nvidia will dominate teh latter.. In the auto chip business, NVidia will grow to gain a significant, albeit not dominant, market share as that market grows. Across all of its busineses, NVIDIA will see sustained high operating margins, though the makers of Nvidia chips (especially TSMC) and TSMC's big customers (big tech) will push back, causing margins to drop from 2024 levels. | H3: Tell your story about the company. Keep it focuses on the company's businesses and tie it into the three key levers of value: cash flows, growth and risk
A7: The Assumptions
B8: Base year | C8: Next year | D8: Years 2-5 | E8: Years 6-10 | F8: After year 10 | G8: Link to story
A9: Revenues (a) | B9: ='Valuation output'!B3 | C9: ='Input sheet'!B25 | D9: ='Input sheet'!B27 | F9: ='Valuation output'!M2 | G9: The AI business will be big, but the DeepSeek entry has bifurcated it, into commoditized and premium, and Nvidia will continue to maintain its dominance of the latter. | H9: Tie each assumption to the part of your story that relates to it.
A10: Operating margin (b) | B10: ='Valuation output'!B4 | C10: ='Input sheet'!B26 | F10: ='Valuation output'!M4 | G10: Nvidia will continue to have high margins in its core businesses, and while the AI chip market will be smaller than it was pre-DeepSeek, but some of Nvidia's current competitors may shift to the other AI market.
A11: Tax rate | B11: ='Valuation output'!B6 | D11: =B11 | F11: ='Valuation output'!M6 | G11: Global/US marginal tax rate over time
A12: Reinvestment (c ) | C12: ='Input sheet'!B30 | D12: ='Input sheet'!B30 | E12: ='Input sheet'!B31 | F12: ='Valuation output'!M2/'Valuation output'!M59 | G12: Sales to capital stays higher than industry aveage, as company continues to get growth off past R&D, and focuses research on new AI and auto chips.
A13: Return on capital | B13: ='Valuation output'!B59 | C13: Marginal ROIC = | D13: =Diagnostics!C27 | F13: ='Valuation output'!M59 | G13: Strong competitive edges allow NVIDIA to earn well above its cost of capital for the next decade and beyond.
A14: Cost of capital (d) | D14: ='Valuation output'!C30 | F14: ='Valuation output'!M30 | G14: Initial cost of capital computed based upon industry( (semiconductors) and Nvidia's low debt mix and geographic exposure. Over time, Nvidia's cost of capital will drift down but will remain higher (third quartile) of all companies in market.
A15: The Cash Flows
B16: Revenues | C16: Operating Margin | D16: EBIT | E16: EBIT (1-t) | F16: Reinvestment | G16: FCFF | H16: These are the numbers that come from your assumptions. The revenues over time reflect your revenue growth, the operating margins evolve towards your target margin and your tax rate will change, if you have set it to. The reinvestment is estimated using the sales to capital ratio for the first 10 years and based on a reinvestment rate in stable growth (g/ ROC).
A17: 1 | B17: ='Valuation output'!C3+'Valuation output'!C14+'Valuation output'!C23 | C17: ='Valuation output'!C4 | D17: =B17*C17 | E17: ='Valuation output'!C7 | F17: ='Valuation output'!C8 | G17: =E17-F17
A18: 2 | B18: ='Valuation output'!D3+'Valuation output'!D14+'Valuation output'!D23 | C18: ='Valuation output'!D4 | D18: =B18*C18 | E18: ='Valuation output'!D7 | F18: ='Valuation output'!D8 | G18: =E18-F18
A19: 3 | B19: ='Valuation output'!E3+'Valuation output'!E14+'Valuation output'!E23 | C19: ='Valuation output'!E4 | D19: =B19*C19 | E19: ='Valuation output'!E7 | F19: ='Valuation output'!E8 | G19: =E19-F19
A20: 4 | B20: ='Valuation output'!F3+'Valuation output'!F14+'Valuation output'!F23 | C20: ='Valuation output'!F4 | D20: =B20*C20 | E20: ='Valuation output'!F7 | F20: ='Valuation output'!F8 | G20: =E20-F20
A21: 5 | B21: ='Valuation output'!G3+'Valuation output'!G14+'Valuation output'!G23 | C21: ='Valuation output'!G4 | D21: =B21*C21 | E21: ='Valuation output'!G7 | F21: ='Valuation output'!G8 | G21: =E21-F21
A22: 6 | B22: ='Valuation output'!H3+'Valuation output'!H14+'Valuation output'!H23 | C22: ='Valuation output'!H4 | D22: =B22*C22 | E22: ='Valuation output'!H7 | F22: ='Valuation output'!H8 | G22: =E22-F22
A23: 7 | B23: ='Valuation output'!I3+'Valuation output'!I14+'Valuation output'!I23 | C23: ='Valuation output'!I4 | D23: =B23*C23 | E23: ='Valuation output'!I7 | F23: ='Valuation output'!I8 | G23: =E23-F23
A24: 8 | B24: ='Valuation output'!J3+'Valuation output'!J14+'Valuation output'!J23 | C24: ='Valuation output'!J4 | D24: =B24*C24 | E24: ='Valuation output'!J7 | F24: ='Valuation output'!J8 | G24: =E24-F24
A25: 9 | B25: ='Valuation output'!K3+'Valuation output'!K14+'Valuation output'!K23 | C25: ='Valuation output'!K4 | D25: =B25*C25 | E25: ='Valuation output'!K7 | F25: ='Valuation output'!K8 | G25: =E25-F25
A26: 10 | B26: ='Valuation output'!L3+'Valuation output'!L14+'Valuation output'!L23 | C26: ='Valuation output'!L4 | D26: =B26*C26 | E26: ='Valuation output'!L7 | F26: ='Valuation output'!L8 | G26: =E26-F26
A27: Terminal year | B27: ='Valuation output'!M3+'Valuation output'!M14+'Valuation output'!M23 | C27: ='Valuation output'!M4 | D27: =B27*C27 | E27: ='Valuation output'!M7 | F27: ='Valuation output'!M8 | G27: =E27-F27
A28: The Value
A29: Value of Gaming & Other | D29: ='Valuation output'!B37
A30: Value of AI | D30: ='Valuation output'!B38
A31: Value of Auto | D31: ='Valuation output'!B39
A32: Value of operating assets = | D32: ='Valuation output'!B40
A33: Adjustment for distress | D33: =D32-'Valuation output'!B43 | E33: Probability of failure = | G33: ='Valuation output'!B41
A34: - Debt & Minority Interests | D34: ='Valuation output'!B44+'Valuation output'!B45
A35: + Cash & Other Non-operating assets | D35: ='Valuation output'!B46+'Valuation output'!B47
A36: Value of equity | D36: =D32-D33-D34+D35
A37: - Value of equity options | D37: ='Valuation output'!B49
A38: Number of shares | D38: ='Valuation output'!B51
A39: Value per share | D39: =(D36-D37)/D38 | E39: Stock was trading at = | G39: ='Input sheet'!B21

Sheet Valuation as picture
A1: You can modify this picture and bring in relevant details to back up your cost of capital and other details that you think flesh out your company's valuation story.
A3: ='Input sheet'!B4 | O3: ='Input sheet'!B3
A5: Base Year and Comparison | E5: Growth Story (Revenue) | H5: Profitability Story (Margin) | K5: Growth Efficiency Story
B6: Company | C6: Industry | E6: ='Stories to Numbers'!G9 | H6: ='Stories to Numbers'!G10 | K6: ='Stories to Numbers'!G12 | O6: Terminal Value
A7: Revenue Growth | B7: ='Input sheet'!I25 | C7: ='Input sheet'!K25 | O7: Growth Rate | P7: ='Valuation output'!M2
A8: Revenue | B8: ='Valuation output'!B3+'Valuation output'!B14+'Valuation output'!B23 | O8: Cost of capital | P8: ='Valuation output'!M30
A9: Operating Margin | B9: =B10/B8 | C9: ='Input sheet'!K26 | O9: Return on capital | P9: ='Valuation output'!M59
A10: Operating Income | B10: ='Valuation output'!B5+'Valuation output'!B16+'Valuation output'!B25 | O10: Reinvestment Rate | P10: =P7/P9
A11: EBIT (1-t) | B11: ='Valuation output'!B7
A15: ='Valuation output'!A37 | B15: ='Valuation output'!B37 | E15: ='Valuation output'!C1 | F15: ='Valuation output'!D1 | G15: ='Valuation output'!E1 | H15: ='Valuation output'!F1 | I15: ='Valuation output'!G1 | J15: ='Valuation output'!H1 | K15: ='Valuation output'!I1 | L15: ='Valuation output'!J1 | ... O15: ='Valuation output'!M1
A16: ='Valuation output'!A38 | B16: ='Valuation output'!B38 | D16: Revenue (Gaming/Other) | E16: ='Valuation output'!C3 | F16: ='Valuation output'!D3 | G16: ='Valuation output'!E3 | H16: ='Valuation output'!F3 | I16: ='Valuation output'!G3 | J16: ='Valuation output'!H3 | K16: ='Valuation output'!I3 | L16: ='Valuation output'!J3 | ... O16: ='Valuation output'!M3
A17: ='Valuation output'!A39 | B17: ='Valuation output'!B39 | D17: Revenue (AI) | E17: ='Valuation output'!C14 | F17: ='Valuation output'!D14 | G17: ='Valuation output'!E14 | H17: ='Valuation output'!F14 | I17: ='Valuation output'!G14 | J17: ='Valuation output'!H14 | K17: ='Valuation output'!I14 | L17: ='Valuation output'!J14 | ... O17: ='Valuation output'!M14
A18: ='Valuation output'!A41 | B18: ='Valuation output'!B41 | D18: Revenue (Auto) | E18: ='Valuation output'!C23 | F18: ='Valuation output'!D23 | G18: ='Valuation output'!E23 | H18: ='Valuation output'!F23 | I18: ='Valuation output'!G23 | J18: ='Valuation output'!H23 | K18: ='Valuation output'!I23 | L18: ='Valuation output'!J23 | ... O18: ='Valuation output'!M23
A19: ='Valuation output'!A43 | B19: ='Valuation output'!B43 | D19: Revenues (Total) | E19: =E16+E17+E18 | F19: =F16+F17+F18 | G19: =G16+G17+G18 | H19: =H16+H17+H18 | I19: =I16+I17+I18 | J19: =J16+J17+J18 | K19: =K16+K17+K18 | L19: =L16+L17+L18 | ... O19: =O16+O17+O18
A20: ='Valuation output'!A44 | B20: ='Valuation output'!B44 | D20: R&D Adj Operating Margin | E20: ='Valuation output'!C4 | F20: ='Valuation output'!D4 | G20: ='Valuation output'!E4 | H20: ='Valuation output'!F4 | I20: ='Valuation output'!G4 | J20: ='Valuation output'!H4 | K20: ='Valuation output'!I4 | L20: ='Valuation output'!J4 | ... O20: ='Valuation output'!M4
A21: ='Valuation output'!A45 | B21: ='Valuation output'!B45 | D21: Operating Income | E21: ='Valuation output'!C5+'Valuation output'!C16+'Valuation output'!C25 | F21: ='Valuation output'!D5+'Valuation output'!D16+'Valuation output'!D25 | G21: ='Valuation output'!E5+'Valuation output'!E16+'Valuation output'!E25 | H21: ='Valuation output'!F5+'Valuation output'!F16+'Valuation output'!F25 | I21: ='Valuation output'!G5+'Valuation output'!G16+'Valuation output'!G25 | J21: ='Valuation output'!H5+'Valuation output'!H16+'Valuation output'!H25 | K21: ='Valuation output'!I5+'Valuation output'!I16+'Valuation output'!I25 | L21: ='Valuation output'!J5+'Valuation output'!J16+'Valuation output'!J25 | ... O21: ='Valuation output'!M5+'Valuation output'!M16+'Valuation output'!M25
A22: ='Valuation output'!A46 | B22: ='Valuation output'!B46 | D22: EBIT (1-t) | E22: ='Valuation output'!C7+'Valuation output'!C17+'Valuation output'!C26 | F22: ='Valuation output'!D7+'Valuation output'!D17+'Valuation output'!D26 | G22: ='Valuation output'!E7+'Valuation output'!E17+'Valuation output'!E26 | H22: ='Valuation output'!F7+'Valuation output'!F17+'Valuation output'!F26 | I22: ='Valuation output'!G7+'Valuation output'!G17+'Valuation output'!G26 | J22: ='Valuation output'!H7+'Valuation output'!H17+'Valuation output'!H26 | K22: ='Valuation output'!I7+'Valuation output'!I17+'Valuation output'!I26 | L22: ='Valuation output'!J7+'Valuation output'!J17+'Valuation output'!J26 | ... O22: ='Valuation output'!M7+'Valuation output'!M17+'Valuation output'!M26
A23: ='Valuation output'!A47 | B23: ='Valuation output'!B47 | D23: Reinvestment | E23: ='Valuation output'!C8+'Valuation output'!C18+'Valuation output'!C27 | F23: ='Valuation output'!D8+'Valuation output'!D18+'Valuation output'!D27 | G23: ='Valuation output'!E8+'Valuation output'!E18+'Valuation output'!E27 | H23: ='Valuation output'!F8+'Valuation output'!F18+'Valuation output'!F27 | I23: ='Valuation output'!G8+'Valuation output'!G18+'Valuation output'!G27 | J23: ='Valuation output'!H8+'Valuation output'!H18+'Valuation output'!H27 | K23: ='Valuation output'!I8+'Valuation output'!I18+'Valuation output'!I27 | L23: ='Valuation output'!J8+'Valuation output'!J18+'Valuation output'!J27 | ... O23: ='Valuation output'!M8+'Valuation output'!M18+'Valuation output'!M27
A24: ='Valuation output'!A48 | B24: ='Valuation output'!B48 | D24: FCFF | E24: ='Valuation output'!C9+'Valuation output'!C19+'Valuation output'!C28 | F24: ='Valuation output'!D9+'Valuation output'!D19+'Valuation output'!D28 | G24: ='Valuation output'!E9+'Valuation output'!E19+'Valuation output'!E28 | H24: ='Valuation output'!F9+'Valuation output'!F19+'Valuation output'!F28 | I24: ='Valuation output'!G9+'Valuation output'!G19+'Valuation output'!G28 | J24: ='Valuation output'!H9+'Valuation output'!H19+'Valuation output'!H28 | K24: ='Valuation output'!I9+'Valuation output'!I19+'Valuation output'!I28 | L24: ='Valuation output'!J9+'Valuation output'!J19+'Valuation output'!J28 | ... O24: ='Valuation output'!M9+'Valuation output'!M19+'Valuation output'!M28
A25: ='Valuation output'!A49 | B25: ='Valuation output'!B49 | N25: ='Valuation output'!N9+'Valuation output'!N19+'Valuation output'!N28
A26: ='Valuation output'!A50 | B26: ='Valuation output'!B50
A27: ='Valuation output'!A51 | B27: ='Valuation output'!B51 | D27: Cost of Capital | E27: ='Valuation output'!C30 | F27: ='Valuation output'!D30 | G27: ='Valuation output'!E30 | H27: ='Valuation output'!F30 | I27: ='Valuation output'!G30 | J27: ='Valuation output'!H30 | K27: ='Valuation output'!I30 | L27: ='Valuation output'!J30 | ... N27: ='Valuation output'!L30
A28: ='Valuation output'!A52 | B28: ='Valuation output'!B52 | D28: Cumulated WACC | E28: ='Valuation output'!C31 | F28: ='Valuation output'!D31 | G28: ='Valuation output'!E31 | H28: ='Valuation output'!F31 | I28: ='Valuation output'!G31 | J28: ='Valuation output'!H31 | K28: ='Valuation output'!I31 | L28: ='Valuation output'!J31 | ... N28: ='Valuation output'!L31
A30: Price per share | B30: ='Stories to Numbers'!G39 | D30: Sales to Capital | E30: ='Valuation output'!C57 | F30: ='Valuation output'!D57 | G30: ='Valuation output'!E57 | H30: ='Valuation output'!F57 | I30: ='Valuation output'!G57 | J30: ='Valuation output'!H57 | K30: ='Valuation output'!I57 | L30: ='Valuation output'!J57 | ... N30: ='Valuation output'!L57
A31: % Under or Over Valued | B31: =B30/B28-1 | D31: ROIC | E31: ='Valuation output'!C59 | F31: ='Valuation output'!D59 | G31: ='Valuation output'!E59 | H31: ='Valuation output'!F59 | I31: ='Valuation output'!G59 | J31: ='Valuation output'!H59 | K31: ='Valuation output'!I59 | L31: ='Valuation output'!J59 | ... O31: ='Valuation output'!M59
D34: Risk Story | G34: Competitive Advantages | L34: AI and Auto Business: Market Size and Market Share
D35: ='Stories to Numbers'!G14 | G35: ='Stories to Numbers'!G13 | M35: AI | O35: Auto
M36: Current | N36: In 2034 | O36: Current | P36: In 2034
L37: Total Market ($ M) | M37: ='Input sheet'!B44 | N37: ='Input sheet'!C44 | O37: ='Input sheet'!B50 | P37: ='Input sheet'!C50
L38: Market Share | M38: ='Input sheet'!B45 | N38: ='Input sheet'!C45 | O38: ='Input sheet'!B51 | P38: ='Input sheet'!C51
L39: NVIDIA revenues | M39: =M37*M38 | N39: =N37*N38 | O39: =O37*O38 | P39: =P37*P38

Sheet Diagnostics
A1: Step 1: Check revenue growth rate | D1: Your forecasts | G1: Questions to ask
B2: Industry Average | C2: Most Recent year | D2: Next year | E2: Years 2-5 | G2: 1. If you are forecasting a revenue growth rate > industry average, is your company small?
A3: Annual Revenue Growth Rate | B3: ='Input sheet'!J25 | C3: ='Input sheet'!I25 | D3: =C7/B7-1 | E3: =(D7/B7)^(1/5)-1 | G3: 2. If your forecasted revenue growth rate is very different from your company's most recent year of growth, what is the reason?
A5: Step 2: Check dollar revenues
B6: Most Recent year | C6: Next year | D6: Year 5 | E6: Year 10 | G6: 1. How big is the total market today?
A7: Revenues | B7: ='Valuation output'!B3+'Valuation output'!B14+'Valuation output'!B23 | C7: ='Valuation output'!C3+'Valuation output'!C14+'Valuation output'!C23 | D7: ='Valuation output'!G3+'Valuation output'!G14+'Valuation output'!G23 | E7: ='Valuation output'!L3+'Valuation output'!L14+'Valuation output'!L23 | G7: 2. How much revenues do the biggest companies in that market make today?
G8: 3. How much growth is there in the total market?
G9: 4. What type of market share are you forecasting for your company in year 10?
A11: Step 3: Check your margins | B11: Most Recent year | C11: Next year | D11: Year 5 | E11: Year 10 | G11: 1. What are the margins of the industry that the company is in?
A12: Operating Margin | B12: ='Valuation output'!B4 | C12: ='Valuation output'!C4 | D12: ='Valuation output'!G4 | E12: ='Valuation output'!M4 | G12: 2. What are the unit economics of the business? (How much does it cost you to make the extra unit that you sell?
G13: 3. What does the competition in this business look like?
A15: Step 4: Check how much you are reinvesting
B16: Most Recent year | C16: Next year | D16: Year 5 | E16: Year 10 | G16: 1. is the growth that you are forecasting bounce-back growth or new growth?
A17: Sales to Capital | B17: ='Input sheet'!I27 | C17: ='Valuation output'!C57 | D17: ='Valuation output'!G57 | E17: ='Valuation output'!L57 | G17: 2. How much excess capacity do you have to service near term growth?
G18: 3. Does investment efficiency in this business change as companies get bigger?
A19: Reinvestment effect on cash flows
B20: $ Value | C20: As % of value
A21: PV of after-tax operating income for next 10 years | B21: =('Valuation output'!C7+'Valuation output'!C17+'Valuation output'!C26)*'Valuation output'!C31+('Valuation output'!D7+'Valuation output'!D17+'Valuation output'!D26)*'Valuation output'!D31+('Valuation output'!E7+'Valuation output'!E17+'Valuation output'!E26)*'Valuation output'!E31+('Valuation output'!F7+'Valuation output'!F17+'Valuation output'!F26)*'Valuation output'!F31+('Valuation output'!G7+'Valuation output'!G17+'Valuation output'!G26)*'Valuation output'!G31+('Valuation output'!H7+'Valuation output'!H17+'Valuation output'!H26)*'Valuation output'!H31+('Valuation output'!I7+'Valuation output'!I17+'Valuation output'!I26)*'Valuation output'!I31+('Valuation output'!J7+'Valuation output'!J17+'Valuation output'!J26)*'Valuation output'!J31+('Valuation output'!K7+'Valuation output'!K17+'Valuation output'!K26)*'Valuation output'!K31+('Valuation output'!L7+'Valuation output'!L17+'Valuation output'!L26)*'Valuation output'!C31+('Valuation output'!M7+'Valuation output'!M17+'Valuation output'!M26)*'Valuation output'!M31 | C21: =B21/B21 | G21: 1. Is your reinvestment consitent with your revenue growth forecast?
A22: Value effect of reinvestment for next 10 years | B22: =B21-B23 | C22: =B22/B21 | G22: 2. Are you comfortable with your return on capital in year 10?
A23: PV of FCFF for next ten years | B23: =SUM('Valuation output'!C32:L32)+SUM('Valuation output'!C33:L33)+SUM('Valuation output'!C34:L34) | C23: =C21-C22
A25: Return on capital effects
B26: Most recent year | C26: Marginal (1-10) | D26: ROC in year 10 | E26: Stable ROC
A27: Return on capital | B27: ='Valuation output'!B59 | C27: =('Valuation output'!L7-'Valuation output'!B7+'Valuation output'!L17-'Valuation output'!B17+'Valuation output'!L26-'Valuation output'!B26-'Valuation output'!B26)/('Valuation output'!L58-'Valuation output'!B58) | D27: ='Valuation output'!L59 | E27: ='Valuation output'!M59
A29: Step 5: Risk Metrics
B30: Industry Average | C30: Compounded | D30: Year 1-5 | E30: Stable Growth | G30: 1. How does your cost of capital compare to the industry average?
A31: Cost of capital | B31: ='Input sheet'!J31 | C31: =(1/'Valuation output'!L31)^(1/10)-1 | D31: ='Valuation output'!C30 | E31: ='Valuation output'!M30 | G31: 2. What is happenign to your cost of capital over time? Why?
G32: 3. Is your failure rate consistent with your company's characteristics?
A33: Failure Rate | B33: ='Valuation output'!B41
A35: Step 6: Price versus Value
A36: Your calculated value as a percent of current price | B36: ='Valuation output'!B52/'Valuation output'!B53
B37: =IF(B36="NA","Value is negative. See below",IF(B36>2,"Value seems high. See below",IF(B36<0.5,"Value seems low. See below"," ")))
A38: Inputs | B38: If calculated value is negative or looks too low | C38: If calculated value looks too high
A39: Revenue growth rate (input cell B25, B27) | B39: Increase revenue growth rate | C39: Decrease revenue growth rate
A40: Operating margin (B26, B28) | B40: Increase the target pre-tax operating margin | C40: Decrease the target pre-tax operating margin
A41: Sales to Capital (B30-B32) | B41: Increase the sales/capital ratio | C41: Decrease the sales/capital ratio
A42: Return on capital in perpetuity (B48, B49) | B42: Increase relative to your cost of capital | C42: If higher than your cost of capital, lower towards your cost of capital

Sheet Option value
A1: Note: This worksheet is the most finicky of all of the worksheets in this spreadsheet. If you start to get errors, here is a quick fix. Go into cell B12 and replace the contents with a number (say 5), and then undo your action. The spreadsheet will fix itself magically.
A3: Valuing Options or Warrants
A4: Enter the current stock price = | B4: ='Input sheet'!B21
A5: Enter the strike price on the option = | B5: ='Input sheet'!B38
A6: Enter the expiration of the option = | B6: ='Input sheet'!B39
A7: Enter the standard deviation in stock prices = | B7: ='Input sheet'!B40 | C7: (volatility)
A8: Enter the annualized dividend yield on stock = | B8: 0
A9: Enter the treasury bond rate = | B9: ='Input sheet'!B33
A10: Enter the number of warrants (options) outstanding = | B10: ='Input sheet'!B37
A11: Enter the number of shares outstanding = | B11: ='Input sheet'!B20
A13: Do not input any numbers below this line
A14: Dilution-adjusted Black-Scholes
A15: Stock Price= | B15: =B4 | C15: # Warrants issued= | D15: =B10
A16: Strike Price= | B16: =B5 | C16: # Shares outstanding= | D16: =B11
A17: Adjusted S = | B17: =(B15*D16+B28*D15)/(D16+D15) | C17: T.Bond rate= | D17: =B9
A18: Adjusted K = | B18: =B16 | C18: Variance= | D18: =B7^2
A19: Expiration (in years) = | B19: =B6 | C19: Annualized dividend yield= | D19: =B8
C20: Div. Adj. interest rate= | D20: =D17-D19
A22: d1 = | B22: =(LN(B17/B18)+(D20+(D18/2))*B19)/(((D18)^(0.5))*(B19^0.5))
A23: N (d1) = | B23: =NORMSDIST(B22)
A25: d2 = | B25: =B22-((D18^0.5)*(B19^(0.5)))
A26: N (d2) = | B26: =NORMSDIST(B25)
A28: Value per option = | B28: =((EXP((0-D19)*B19))*B17*B23-B18*(EXP((0-D17)*B19))*B26)
A29: Value of all options outstanding = | B29: =B28*B10

Sheet Operating lease converter
A1: Operating Lease Converter
A2: The yellow cells are input cells. Please enter them.
A3: Inputs | H3: Until 2019, this worksheet had to be used for every firm with operating lease commitments, since accountants treated operating lease expenses as operating expenses. In 2019, IFRS and GAAP made the long-overdue change to treat leases as debt, and for firms that follow these standards, the conversion that I am doing on this spreadsheet is being done by accountants, with lease debt and operating income already adjusted. If that is the case, and you showed the lease debt as part of debt in the input page, please do not use this spreadsheet, since you will be double counting.
A4: Operating lease expense in current year = | E4: 295
A5: Operating Lease Commitments (From footnote to financials)
A6: Year | B6: Commitment | C6: ! Year 1 is next year, ….
A7: 1 | B7: 287
A8: 2 | B8: 235
A9: 3 | B9: 194
A10: 4 | B10: 151
A11: 5 | B11: 98
A12: 6 and beyond | B12: 605
A14: Output
A15: Pre-tax Cost of Debt = | C15: ='Cost of capital worksheet'!B37 | D15: ! If you do not have a cost of debt, use the synthetic rating estimator
A18: Number of years embedded in yr 6 estimate = | D18: =IF(B12>0,ROUND(B12/AVERAGE(B7:B11),0),0) | E18: ! I use the average lease expense over the first five years
E19: to estimate the number of years of expenses in yr 6
A20: Converting Operating Leases into debt
A21: Year | B21: Commitment | C21: Present Value
A22: =A7 | B22: =B7 | C22: =B22/(1+$C$15)^A22
A23: =A8 | B23: =B8 | C23: =B23/(1+$C$15)^A23
A24: =A9 | B24: =B9 | C24: =B24/(1+$C$15)^A24
A25: =A10 | B25: =B10 | C25: =B25/(1+$C$15)^A25
A26: =A11 | B26: =B11 | C26: =B26/(1+$C$15)^A26
A27: =A12 | B27: =IF(B12>0,IF(D18>0,B12/D18,B12),0) | C27: =IF(D18>0,(B27*(1-(1+C15)^(-D18))/C15)/(1+$C$15)^5,B27/(1+C15)^6) | D27: ! Commitment beyond year 6 converted into an annuity for ten years
A28: Debt Value of leases = | C28: =SUM(C22:C27)
A30: Restated Financials
A31: Depreciation on Operating Lease Asset = | F31: =C28/(5+D18) | G31: ! I use straight line depreciation
A32: Adjustment to Operating Earnings = | F32: =E4-F31 | G32: ! Add this amount to pre-tax operating income
A33: Adjustment to Total Debt outstanding = | F33: =C28 | G33: ! Add this amount to debt
A34: Adjustment to Depreciation = | F34: =C28/(5+D18)

Sheet Synthetic rating
A1: If you have negative operating income, this spreadsheet will offer you a D rating. Do not use that rating as your cost of debt for a going concern. Insread give your company a low, but going concern rating like BB and use that cost of debt.
A4: Inputs for synthetic rating estimation
A5: Please read the special cases worksheet (see below) before you use this spreadsheet.
A6: Before you use this spreadsheet, make sure that the iteration box (under calculation options in excel) is checked.
A7: Enter the type of firm = | C7: ='Cost of capital worksheet'!B36
A8: Enter current Earnings before interest and taxes (EBIT) = | F8: =IF('Input sheet'!B16="Yes",'Input sheet'!B11+'Operating lease converter'!F32,'Input sheet'!B11) | G8: (Add back only long term interest expense for financial firms)
A9: Enter current interest expenses = | F9: =IF('Input sheet'!B16="Yes",'Cost of capital worksheet'!B31+'Operating lease converter'!C28*'Operating lease converter'!C15,'Cost of capital worksheet'!B31) | G9: (Use only long term interest expense for financial firms)
A10: Enter long term risk free rate = | F10: ='Input sheet'!B33
A11: Output
A12: Interest coverage ratio = | D12: =IF(F9=0,1000000,IF(F8<0,-100000,F8/F9))
A13: Estimated Bond Rating = | D13: =IF(C7=1,VLOOKUP(D12,A22:D36,3),(IF(C7=2,VLOOKUP(D12,A41:D55,3),VLOOKUP(D12,F22:I36,3)))) | F13: Note: If you get REF! All over the place, set the operating lease commitment question in cell F5
A14: Estimated Company Default Spread = | D14: =IF(C7=1,VLOOKUP(D12,A22:D36,4),(IF(C7=2,VLOOKUP(D12,A41:D55,4),VLOOKUP(D12,F22:I36,4)))) | F14: to No, and then reset it to Yes. It should work.
A15: Estimated County Default Spread (if any) = | D15: =VLOOKUP('Input sheet'!B7,'Country equity risk premiums'!A5:C196,3)
A16: Estimated Cost of Debt = | D16: =F10+D14+D15
A18: If you want to update the spreads listed below, please visit http://www.bondsonline.com
A19: For large manufacturing firms | J19: Default Probabilities over time (1 - 10 year time horizons)
A20: If interest coverage ratio is | J20: Rating | K20: 1 | L20: 2 | M20: 3 | N20: 4 | O20: 5 | P20: 6 | Q20: 7 | R20: 8 | S20: 9 | T20: 10
A21: > | B21: ≤ to | C21: Rating is | D21: Spread is | J21: AAA | K21: 0 | L21: 0.0003 | M21: 0.0013 | N21: 0.0024 | O21: 0.0035 | P21: 0.0045 | Q21: 0.0051 | R21: 0.0059 | S21: 0.0064 | T21: 0.007
A22: -100000 | B22: 0.199999 | C22: D2/D | D22: 0.2 | J22: AA | K22: 0.0002 | L22: 0.0006 | M22: 0.0012 | N22: 0.0021 | O22: 0.0031 | P22: 0.0042 | Q22: 0.005 | R22: 0.0058 | S22: 0.0065 | T22: 0.0072
A23: 0.2 | B23: 0.649999 | C23: C2/C | D23: 0.175 | J23: A | K23: 0.0005 | L23: 0.0014 | M23: 0.0023 | N23: 0.0035 | O23: 0.0047 | P23: 0.0062 | Q23: 0.0079 | R23: 0.0093 | S23: 0.0108 | T23: 0.0124
A24: 0.65 | B24: 0.799999 | C24: Ca2/CC | D24: 0.1578 | J24: BBB | K24: 0.0016 | L24: 0.0045 | M24: 0.0078 | N24: 0.0117 | O24: 0.0158 | P24: 0.0198 | Q24: 0.0233 | R24: 0.0267 | S24: 0.03 | T24: 0.0332
A25: 0.8 | B25: 1.249999 | C25: Caa/CCC | D25: 0.1157 | J25: BB | K25: 0.0061 | L25: 0.0192 | M25: 0.0348 | N25: 0.0505 | O25: 0.0652 | P25: 0.0785 | Q25: 0.0901 | R25: 0.1004 | S25: 0.1097 | T25: 0.1178
A26: 1.25 | B26: 1.499999 | C26: B3/B- | D26: 0.0737 | J26: B | K26: 0.0333 | L26: 0.0771 | M26: 0.1155 | N26: 0.1458 | O26: 0.1693 | P26: 0.1883 | Q26: 0.2036 | R26: 0.216 | S26: 0.227 | T26: 0.2374
A27: 1.5 | B27: 1.749999 | C27: B2/B | D27: 0.0526 | J27: CCC/C | K27: 0.2708 | L27: 0.3664 | M27: 0.4141 | N27: 0.441 | O27: 0.4619 | P27: 0.4709 | Q27: 0.4826 | R27: 0.4905 | S27: 0.4976 | T27: 0.5038
A28: 1.75 | B28: 1.999999 | C28: B1/B+ | D28: 0.0455
A29: 2 | B29: 2.2499999 | C29: Ba2/BB | D29: 0.0313
A30: 2.25 | B30: 2.49999 | C30: Ba1/BB+ | D30: 0.0242
A31: 2.5 | B31: 2.999999 | C31: Baa2/BBB | D31: 0.02
A32: 3 | B32: 4.249999 | C32: A3/A- | D32: 0.0162
A33: 4.25 | B33: 5.499999 | C33: A2/A | D33: 0.0142
A34: 5.5 | B34: 6.499999 | C34: A1/A+ | D34: 0.0123
A35: 6.5 | B35: 8.499999 | C35: Aa2/AA | D35: 0.0085
A36: 8.5 | B36: 100000 | C36: Aaa/AAA | D36: 0.0069
A38: For smaller and riskier firms
A39: If interest coverage ratio is
A40: greater than | B40: ≤ to | C40: Rating is | D40: Spread is
A41: -100000 | B41: 0.499999 | C41: D2/D | D41: 0.2 | G41: Rating is | H41: Spread is
A42: 0.5 | B42: 0.799999 | C42: C2/C | D42: 0.175 | G42: A1/A+ | H42: 0.0123
A43: 0.8 | B43: 1.249999 | C43: Ca2/CC | D43: 0.1578 | G43: A2/A | H43: 0.0142
A44: 1.25 | B44: 1.499999 | C44: Caa/CCC | D44: 0.1157 | G44: A3/A- | H44: 0.0162
A45: 1.5 | B45: 1.999999 | C45: B3/B- | D45: 0.0737 | G45: Aa2/AA | H45: 0.0085
A46: 2 | B46: 2.499999 | C46: B2/B | D46: 0.0526 | G46: Aaa/AAA | H46: 0.0069
A47: 2.5 | B47: 2.999999 | C47: B1/B+ | D47: 0.0455 | G47: B1/B+ | H47: 0.0455
A48: 3 | B48: 3.499999 | C48: Ba2/BB | D48: 0.0313 | G48: B2/B | H48: 0.0526
A49: 3.5 | B49: 3.9999999 | C49: Ba1/BB+ | D49: 0.0242 | G49: B3/B- | H49: 0.0737
A50: 4 | B50: 4.499999 | C50: Baa2/BBB | D50: 0.02 | G50: Ba1/BB+ | H50: 0.0242
A51: 4.5 | B51: 5.999999 | C51: A3/A- | D51: 0.0162 | G51: Ba2/BB | H51: 0.0313
A52: 6 | B52: 7.499999 | C52: A2/A | D52: 0.0142 | G52: Baa2/BBB | H52: 0.02
A53: 7.5 | B53: 9.499999 | C53: A1/A+ | D53: 0.0123 | G53: C2/C | H53: 0.175
... A55: 12.5 | B55: 100000 | C55: Aaa/AAA | D55: 0.0069 | G55: Caa/CCC | H55: 0.1157
G56: D2/D | H56: 0.2

Sheet R& D converter
A1: R & D Converter
A2: This spreadsheet converts R&D expenses from operating to capital expenses. It makes the appropriate adjustments to operating income, net
A3: income, the book value of assets and the book value of equity.
A5: Inputs
A6: Over how many years do you want to amortize R&D expenses | B6: 5 | F6: 5 | G6: ! If in doubt, use the lookup table below
A7: Enter the current year's R&D expense = | B7: 2288.204 | F7: 11665 | G7: The maximum allowed is ten years
A8: Enter R& D expenses for past years: the number of years that you will need to enter will be determined by the amortization period
A9: Do not input numbers in the first column (Year). It will get automatically updated based on the input above.
A10: Year | B10: R& D Expenses
A11: -1 | B11: 2027.532 | C11: ! Year -1 is the year prior to the current year
A12: =IF((0-A11)<$F$6,IF(A11>-1,,A11-1),) | B12: 2195.329 | C12: ! Year -2 is the two years prior to the current year
A13: =IF((0-A12)<$F$6,IF(A12>-1,,A12-1),) | B13: 2073.461
A14: =IF((0-A13)<$F$6,IF(A13>-1,,A13-1),) | B14: 1453.912
A15: =IF((0-A14)<$F$6,IF(A14>-1,,A14-1),) | B15: 1335.744
A16: =IF((0-A15)<$F$6,IF(A15>-1,,A15-1),) | B16: 1266.341
A17: =IF((0-A16)<$F$6,IF(A16>-1,,A16-1),) | B17: 1273.729
A18: =IF((0-A17)<$F$6,IF(A17>-1,,A17-1),) | B18: 1361.691
A19: =IF((0-A18)<$F$6,IF(A18>-1,,A18-1),) | B19: 1491.37
A20: =IF((0-A19)<$F$6,IF(A19>-1,,A19-1),) | B20: 1220.919
A22: Output
A23: Year | B23: R&D Expense | C23: Unamortized portion | E23: Amortization this year
A24: Current | B24: =F7 | C24: =1 | D24: =B24*C24
A25: =A11 | B25: =B11 | C25: =IF(A25<0,($F$6+A25)/$F$6,0) | D25: =B25*C25 | E25: =IF(A25<0,B25/$F$6,0)
A26: =A12 | B26: =B12 | C26: =IF(A26<0,($F$6+A26)/$F$6,0) | D26: =B26*C26 | E26: =IF(A26<0,B26/$F$6,0)
A27: =A13 | B27: =B13 | C27: =IF(A27<0,($F$6+A27)/$F$6,0) | D27: =B27*C27 | E27: =IF(A27<0,B27/$F$6,0)
A28: =A14 | B28: =B14 | C28: =IF(A28<0,($F$6+A28)/$F$6,0) | D28: =B28*C28 | E28: =IF(A28<0,B28/$F$6,0)
A29: =A15 | B29: =B15 | C29: =IF(A29<0,($F$6+A29)/$F$6,0) | D29: =B29*C29 | E29: =IF(A29<0,B29/$F$6,0)
A30: =A16 | B30: =B16 | C30: =IF(A30<0,($F$6+A30)/$F$6,0) | D30: =B30*C30 | E30: =IF(A30<0,B30/$F$6,0)
A31: =A17 | B31: =B17 | C31: =IF(A31<0,($F$6+A31)/$F$6,0) | D31: =B31*C31 | E31: =IF(A31<0,B31/$F$6,0)
A32: =A18 | B32: =B18 | C32: =IF(A32<0,($F$6+A32)/$F$6,0) | D32: =B32*C32 | E32: =IF(A32<0,B32/$F$6,0)
A33: =A19 | B33: =B19 | C33: =IF(A33<0,($F$6+A33)/$F$6,0) | D33: =B33*C33 | E33: =IF(A33<0,B33/$F$6,0)
A34: =A20 | B34: =B20 | C34: =IF(A34<0,($F$6+A34)/$F$6,0) | D34: =B34*C34 | E34: =IF(A34<0,B34/$F$6,0)
A35: Value of Research Asset = | D35: =SUM(D24:D34) | E35: =SUM(E25:E34)
A37: Amortization of asset for current year = | D37: =E35
A39: Adjustment to Operating Income = | D39: =F7-D37 | E39: ! A positive number indicates an increase in operating income (add to reported EBIT)
A40: Tax Effect of R&D Expensing | D40: =D39*'Input sheet'!B23

Sheet Cost of capital worksheet
A1: You can use this spreadsheet to compute your cost of capital. You can either use the built-in data to compute key inputs (beta, equity risk premium, default spread) or enter them directly. If you choose to use the built in ERP data, you can update the ERP numbers to reflect a more current mature market premuum (since the spreadsheet uses the start of the year numbers).
A3: Estimation of Current Cost of Capital | G3: Operating Countries ERP calculator
A4: There are four ways in whch you can estimate your cost of capital. In the first, you can directly input a cost of captial. In the second, you can work through your company's cost of capital inputs in detail, entering business, geogaphical mix and debt, and I will help you estimate a cost of capital. In the third, you can look up the cost of capital for the industry your firm belongs to and in the fourth, you can use a crosssectoinal distribution of costs of capital for companies at the start of the year to make your estimate. | G4: Country | H4: Revenues | I4: ERP | J4: Weight | K4: Weighted ERP
G5: United States | H5: 26966 | I5: =IF(H5=0,0,VLOOKUP(G5,'Country equity risk premiums'!$A$5:$D$196,4)) | J5: =IF(H5>0,H5/$H$18,) | K5: =IF(J5=0,0,I5*J5) | M5: The last two rows in each of country/region risk premium tables is set aside for your input to provide you with flexibility to enter some numbers directly. For instance, assume that you have a company that breaks its revenues down into three countries and then puts the rest into "Rest of the World". You can enter the "Rest of the World" in one of these two rows and enter an equity risk premium for the rest of the world. The easiest way to do that is to go into the country equity risk premium worksheet and change the GDP for the three countries that you have data for to zero and compute the global weighted average ERP for the remaining countries. With the regional worksheet, you can use the last two rows to enter the data for an individual country (usually the domestic country) that might be broken out though the rest of the revenues are broken down by region. You can look up the ERP for the country in the country ERP worksheet. | S5: United States | T5: 26966
G6: China | H6: 10306 | I6: =IF(H6=0,0,VLOOKUP(G6,'Country equity risk premiums'!$A$5:$D$196,4)) | J6: =IF(H6>0,H6/$H$18,) | K6: =IF(J6=0,0,I6*J6) | S6: Taiwan | T6: 13405
G7: Taiwan | H7: 13405 | I7: =IF(H7=0,0,VLOOKUP(G7,'Country equity risk premiums'!$A$5:$D$196,4)) | J7: =IF(H7>0,H7/$H$18,) | K7: =IF(J7=0,0,I7*J7) | S7: China (Including Hong Kong) | T7: 10306
I8: =IF(H8=0,0,VLOOKUP(G8,'Country equity risk premiums'!$A$5:$D$196,4)) | J8: =IF(H8>0,H8/$H$18,) | K8: =IF(J8=0,0,I8*J8) | S8: Other Countries | T8: 10245
I9: =IF(H9=0,0,VLOOKUP(G9,'Country equity risk premiums'!$A$5:$D$196,4)) | J9: =IF(H9>0,H9/$H$18,) | K9: =IF(J9=0,0,I9*J9)
I10: =IF(H10=0,0,VLOOKUP(G10,'Country equity risk premiums'!$A$5:$D$196,4)) | J10: =IF(H10>0,H10/$H$18,) | K10: =IF(J10=0,0,I10*J10)
A11: Which approach will you be using? | B11: Detailed | I11: =IF(H11=0,0,VLOOKUP(G11,'Country equity risk premiums'!$A$5:$D$196,4)) | J11: =IF(H11>0,H11/$H$18,) | K11: =IF(J11=0,0,I11*J11)
A12: If direct input, enter cost of capital to use | B12: 0.09 | I12: =IF(H12=0,0,VLOOKUP(G12,'Country equity risk premiums'!$A$5:$D$196,4)) | J12: =IF(H12>0,H12/$H$18,) | K12: =IF(J12=0,0,I12*J12)
A13: Cost of capital based upon approach = | B13: =IF(B11="I will input",B12,IF(B11="Detailed",E62,IF(B11="Industry Average",B67,B72))) | I13: =IF(H13=0,0,VLOOKUP(G13,'Country equity risk premiums'!$A$5:$D$196,4)) | J13: =IF(H13>0,H13/$H$18,) | K13: =IF(J13=0,0,I13*J13)
I14: =IF(H14=0,0,VLOOKUP(G14,'Country equity risk premiums'!$A$5:$D$196,4)) | J14: =IF(H14>0,H14/$H$18,) | K14: =IF(J14=0,0,I14*J14)
A15: Approach 1: Detailed Cost of Capital | I15: =IF(H15=0,0,VLOOKUP(G15,'Country equity risk premiums'!$A$5:$D$196,4)) | J15: =IF(H15>0,H15/$H$18,) | K15: =IF(J15=0,0,I15*J15)
A16: Inputs | G16: Rest of the World | H16: 10245 | I16: 0.055 | J16: =IF(H16>0,H16/$H$18,) | K16: =IF(J16=0,0,I16*J16)
A17: Equity | J17: =IF(H17>0,H17/$H$18,) | K17: =IF(J17=0,0,I17*J17)
A18: Number of Shares outstanding = | B18: ='Input sheet'!B20 | G18: Total | H18: =SUM(H5:H17) | J18: =SUM(J5:J17) | K18: =SUM(K5:K17)
A19: Current Market Price per share = | B19: ='Input sheet'!B21 | G19: Operating Regions ERP calculator
G20: Region | H20: Revenues | I20: ERP | J20: Weight | K20: Weighted ERP
A21: Approach for estimating beta | B21: Single Business(US) | G21: ='Country equity risk premiums'!A201 | I21: ='Country equity risk premiums'!B201 | J21: =H21/$H$32 | K21: =I21*J21
A22: If direct input, enter levered beta (or regression beta) | B22: 1.2 | G22: ='Country equity risk premiums'!A202 | H22: 27899 | I22: ='Country equity risk premiums'!B202 | J22: =H22/$H$32 | K22: =I22*J22
A23: Unlevered beta = | B23: =IF(B21="Single Business(US)",VLOOKUP('Input sheet'!B8,'Industry Averages(US)'!A2:G95,7),IF(B21="Multibusiness(US)",K48,IF(B21="Single Business(Global)",VLOOKUP('Input sheet'!B9,'Industry Average Beta (Global)'!A2:G95,7),'Cost of capital worksheet'!K64))) | G23: ='Country equity risk premiums'!A203 | I23: ='Country equity risk premiums'!B203 | J23: =H23/$H$32 | K23: =I23*J23
A24: Riskfree Rate = | B24: ='Input sheet'!B33 | G24: ='Country equity risk premiums'!A204 | I24: ='Country equity risk premiums'!B204 | J24: =H24/$H$32 | K24: =I24*J24
A25: What approach do you want to use to input ERP? | B25: Operating countries | G25: ='Country equity risk premiums'!A205 | I25: ='Country equity risk premiums'!B205 | J25: =H25/$H$32 | K25: =I25*J25
A26: Direct input for ERP (if you choose "will input" | B26: 0.06 | G26: ='Country equity risk premiums'!A206 | I26: ='Country equity risk premiums'!B206 | J26: =H26/$H$32 | K26: =I26*J26
A27: Equity Risk Premium used in cost of equity = | B27: =IF(B25="Will Input",B26,IF(B25="Country of Incorporation",VLOOKUP('Input sheet'!B7,'Country equity risk premiums'!A5:E195,4),IF(B25="Operating regions",'Cost of capital worksheet'!K32,'Cost of capital worksheet'!K18))) | G27: ='Country equity risk premiums'!A207 | I27: ='Country equity risk premiums'!B207 | J27: =H27/$H$32 | K27: =I27*J27
G28: ='Country equity risk premiums'!A208 | H28: 8292 | I28: ='Country equity risk premiums'!B208 | J28: =H28/$H$32 | K28: =I28*J28
A29: Debt | G29: ='Country equity risk premiums'!A193 | H29: 5389 | I29: ='Country equity risk premiums'!B209 | J29: =H29/$H$32 | K29: =I29*J29
A30: Book Value of Straight Debt = | B30: ='Input sheet'!B14 | J30: =H30/$H$32 | K30: =I30*J30
A31: Interest Expense on Debt = | B31: ='Input sheet'!B12 | G31: South Korea | H31: 66423 | I31: 0.052 | J31: =H31/$H$32 | K31: =I31*J31
A32: Average Maturity = | B32: 3 | G32: Total | H32: =SUM(H21:H31) | J32: =SUM(J21:J31) | K32: =SUM(K21:K31)
A33: Approach for estimating pre-tax cost of debt | B33: Actual rating
A34: If direct input, input the pre-tax cost of debt | B34: 0.04 | G34: Multi Business (US Industry Averages)
A35: If actual rating, input the rating | B35: A2/A | G35: Business | H35: Revenues | I35: EV/Sales | J35: Estimated Value | K35: Unlevered Beta | L35: Cost of capital
A36: If synethetic rating, input the type of company | B36: 2 | G36: Semiconductor | H36: 25878 | I36: =IF(G36=0,,VLOOKUP(G36,'Industry Averages(US)'!$A$2:$S$95,15)) | J36: =H36*I36 | K36: =IF(I36=0,0,VLOOKUP(G36,'Industry Averages(US)'!$A$2:$S$95,7)) | L36: =IF(I36=0,0,VLOOKUP(G36,'Industry Averages(US)'!$A$2:$S$95,13))
A37: Pre-tax Cost of Debt = | B37: =IF(B33="Direct Input",B34,IF(B33="Synthetic Rating",'Synthetic rating'!D16,B24+VLOOKUP('Cost of capital worksheet'!B35,'Synthetic rating'!G42:H56,2))) | I37: =IF(G37=0,,VLOOKUP(G37,'Industry Averages(US)'!$A$2:$S$95,15)) | J37: =H37*I37 | K37: =IF(I37=0,0,VLOOKUP(G37,'Industry Averages(US)'!$A$2:$S$95,7)) | L37: =IF(I37=0,0,VLOOKUP(G37,'Industry Averages(US)'!$A$2:$S$95,13))
A38: Tax Rate = | B38: ='Input sheet'!B23 | I38: =IF(G38=0,,VLOOKUP(G38,'Industry Averages(US)'!$A$2:$S$95,15)) | J38: =H38*I38 | K38: =IF(I38=0,0,VLOOKUP(G38,'Industry Averages(US)'!$A$2:$S$95,7)) | L38: =IF(I38=0,0,VLOOKUP(G38,'Industry Averages(US)'!$A$2:$S$95,13))
I39: =IF(G39=0,,VLOOKUP(G39,'Industry Averages(US)'!$A$2:$S$95,15)) | J39: =H39*I39 | K39: =IF(I39=0,0,VLOOKUP(G39,'Industry Averages(US)'!$A$2:$S$95,7)) | L39: =IF(I39=0,0,VLOOKUP(G39,'Industry Averages(US)'!$A$2:$S$95,13))
A40: Book Value of Convertible Debt = | B40: 0 | I40: =IF(G40=0,,VLOOKUP(G40,'Industry Averages(US)'!$A$2:$S$95,15)) | J40: =H40*I40 | K40: =IF(I40=0,0,VLOOKUP(G40,'Industry Averages(US)'!$A$2:$S$95,7)) | L40: =IF(I40=0,0,VLOOKUP(G40,'Industry Averages(US)'!$A$2:$S$95,13))
A41: Interest Expense on Convertible = | B41: 0 | I41: =IF(G41=0,,VLOOKUP(G41,'Industry Averages(US)'!$A$2:$S$95,15)) | J41: =H41*I41 | K41: =IF(I41=0,0,VLOOKUP(G41,'Industry Averages(US)'!$A$2:$S$95,7)) | L41: =IF(I41=0,0,VLOOKUP(G41,'Industry Averages(US)'!$A$2:$S$95,13))
A42: Maturity of Convertible Bond = | B42: 0 | I42: =IF(G42=0,,VLOOKUP(G42,'Industry Averages(US)'!$A$2:$S$95,15)) | J42: =H42*I42 | K42: =IF(I42=0,0,VLOOKUP(G42,'Industry Averages(US)'!$A$2:$S$95,7)) | L42: =IF(I42=0,0,VLOOKUP(G42,'Industry Averages(US)'!$A$2:$S$95,13))
A43: Market Value of Convertible = | B43: 0 | I43: =IF(G43=0,,VLOOKUP(G43,'Industry Averages(US)'!$A$2:$S$95,15)) | J43: =H43*I43 | K43: =IF(I43=0,0,VLOOKUP(G43,'Industry Averages(US)'!$A$2:$S$95,7)) | L43: =IF(I43=0,0,VLOOKUP(G43,'Industry Averages(US)'!$A$2:$S$95,13))
I44: =IF(G44=0,,VLOOKUP(G44,'Industry Averages(US)'!$A$2:$S$95,15)) | J44: =H44*I44 | K44: =IF(I44=0,0,VLOOKUP(G44,'Industry Averages(US)'!$A$2:$S$95,7)) | L44: =IF(I44=0,0,VLOOKUP(G44,'Industry Averages(US)'!$A$2:$S$95,13)) | M44: The cost of capital is in US dollars, using the riskfree rate at the start of the year. It will be adjusted for the difference in riskfree rates to make it more current and to change currencies.
A45: Debt value of operating leases = | B45: =IF('Input sheet'!B16="Yes",'Operating lease converter'!F33,0) | I45: =IF(G45=0,,VLOOKUP(G45,'Industry Averages(US)'!$A$2:$S$95,15)) | J45: =H45*I45 | K45: =IF(I45=0,0,VLOOKUP(G45,'Industry Averages(US)'!$A$2:$S$95,7)) | L45: =IF(I45=0,0,VLOOKUP(G45,'Industry Averages(US)'!$A$2:$S$95,13))
I46: =IF(G46=0,,VLOOKUP(G46,'Industry Averages(US)'!$A$2:$S$95,15)) | J46: =H46*I46 | K46: =IF(I46=0,0,VLOOKUP(G46,'Industry Averages(US)'!$A$2:$S$95,7)) | L46: =IF(I46=0,0,VLOOKUP(G46,'Industry Averages(US)'!$A$2:$S$95,13))
A47: Preferred Stock | I47: =IF(G47=0,,VLOOKUP(G47,'Industry Averages(US)'!$A$2:$S$95,15)) | J47: =H47*I47 | K47: =IF(I47=0,0,VLOOKUP(G47,'Industry Averages(US)'!$A$2:$S$95,7)) | L47: =IF(I47=0,0,VLOOKUP(G47,'Industry Averages(US)'!$A$2:$S$95,13))
A48: Number of Preferred Shares = | B48: 0 | G48: Company | H48: =SUM(H36:H47) | J48: =SUM(J36:J47) | K48: =K36*(J36/J48)+K37*J37/J48+K38*J38/J48+K39*J39/J48+K40*J40/J48+K41*J41/J48+K42*J42/J48+K43*J43/J48+K44*J44/J48+K45*J45/J48+K46*J46/J48+K47*J47/J48 | L48: =L36*(J36/J48)+L37*J37/J48+L38*J38/J48+L39*J39/J48+L40*J40/J48+L41*J41/J48+L42*J42/J48+L43*J43/J48+L44*J44/J48+L45*J45/J48+L46*J46/J48+L47*J47/J48
A49: Current Market Price per Share= | B49: 70
A50: Annual Dividend per Share = | B50: 5 | G50: Multi Business (Global Industry Averages)
G51: Business | H51: Revenues | I51: EV/Sales | J51: Estimated Value | K51: Unlevered Beta | L51: Cost of capital
A52: Output | G52: Semiconductor | H52: 25878 | I52: =IF(G52=0,,VLOOKUP(G52,'Industry Average Beta (Global)'!$A$2:$O$95,15)) | J52: =H52*I52 | K52: =IF(G52=0,,VLOOKUP(G52,'Industry Average Beta (Global)'!$A$2:$O$95,7)) | L52: =IF(I52=0,0,VLOOKUP(G52,'Industry Average Beta (Global)'!$A$2:$M$95,13))
A53: Estimating Market Value of Straight Debt = | C53: =B31*(1-(1+B37)^(-B32))/B37+B30/(1+B37)^B32 | I53: =IF(G53=0,,VLOOKUP(G53,'Industry Average Beta (Global)'!$A$2:$O$95,15)) | J53: =H53*I53 | K53: =IF(G53=0,,VLOOKUP(G53,'Industry Average Beta (Global)'!$A$2:$O$95,7)) | L53: =IF(I53=0,0,VLOOKUP(G53,'Industry Average Beta (Global)'!$A$2:$M$95,13))
A54: Estimated Value of Straight Debt in Convertible = | C54: =B41*(1-(1+B37)^(-B42))/B37+B40/(1+B37)^B42 | I54: =IF(G54=0,,VLOOKUP(G54,'Industry Average Beta (Global)'!$A$2:$O$95,15)) | J54: =H54*I54 | K54: =IF(G54=0,,VLOOKUP(G54,'Industry Average Beta (Global)'!$A$2:$O$95,7)) | L54: =IF(I54=0,0,VLOOKUP(G54,'Industry Average Beta (Global)'!$A$2:$M$95,13))
A55: Value of Debt in Operating leases = | C55: =B45 | I55: =IF(G55=0,,VLOOKUP(G55,'Industry Average Beta (Global)'!$A$2:$O$95,15)) | J55: =H55*I55 | K55: =IF(G55=0,,VLOOKUP(G55,'Industry Average Beta (Global)'!$A$2:$O$95,7)) | L55: =IF(I55=0,0,VLOOKUP(G55,'Industry Average Beta (Global)'!$A$2:$M$95,13))
A56: Estimated Value of Equity in Convertible = | C56: =B43-C54 | I56: =IF(G56=0,,VLOOKUP(G56,'Industry Average Beta (Global)'!$A$2:$O$95,15)) | J56: =H56*I56 | K56: =IF(G56=0,,VLOOKUP(G56,'Industry Average Beta (Global)'!$A$2:$O$95,7)) | L56: =IF(I56=0,0,VLOOKUP(G56,'Industry Average Beta (Global)'!$A$2:$M$95,13))
A57: Levered Beta for equity = | C57: =IF(B21="Direct Input",B22,B23*(1+(1-B38)*(C60/B60))) | I57: =IF(G57=0,,VLOOKUP(G57,'Industry Average Beta (Global)'!$A$2:$O$95,15)) | J57: =H57*I57 | K57: =IF(G57=0,,VLOOKUP(G57,'Industry Average Beta (Global)'!$A$2:$O$95,7)) | L57: =IF(I57=0,0,VLOOKUP(G57,'Industry Average Beta (Global)'!$A$2:$M$95,13))
I58: =IF(G58=0,,VLOOKUP(G58,'Industry Average Beta (Global)'!$A$2:$O$95,15)) | J58: =H58*I58 | K58: =IF(G58=0,,VLOOKUP(G58,'Industry Average Beta (Global)'!$A$2:$O$95,7)) | L58: =IF(I58=0,0,VLOOKUP(G58,'Industry Average Beta (Global)'!$A$2:$M$95,13))
B59: Equity | C59: Debt | D59: Preferred Stock | E59: Capital | I59: =IF(G59=0,,VLOOKUP(G59,'Industry Average Beta (Global)'!$A$2:$O$95,15)) | J59: =H59*I59 | K59: =IF(G59=0,,VLOOKUP(G59,'Industry Average Beta (Global)'!$A$2:$O$95,7)) | L59: =IF(I59=0,0,VLOOKUP(G59,'Industry Average Beta (Global)'!$A$2:$M$95,13))
A60: Market Value | B60: =B18*B19 | C60: =C53+C54+C55 | D60: =B48*B49 | E60: =SUM(B60:D60) | I60: =IF(G60=0,,VLOOKUP(G60,'Industry Average Beta (Global)'!$A$2:$O$95,15)) | J60: =H60*I60 | K60: =IF(G60=0,,VLOOKUP(G60,'Industry Average Beta (Global)'!$A$2:$O$95,7)) | L60: =IF(I60=0,0,VLOOKUP(G60,'Industry Average Beta (Global)'!$A$2:$M$95,13)) | M60: The cost of capital is in US dollars, using the riskfree rate at the start of the year. It will be adjusted for the difference in riskfree rates to make it more current and to change currencies.
A61: Weight in Cost of Capital | B61: =B60/$E$60 | C61: =C60/$E$60 | D61: =D60/$E$60 | E61: =SUM(B61:D61) | I61: =IF(G61=0,,VLOOKUP(G61,'Industry Average Beta (Global)'!$A$2:$O$95,15)) | J61: =H61*I61 | K61: =IF(G61=0,,VLOOKUP(G61,'Industry Average Beta (Global)'!$A$2:$O$95,7)) | L61: =IF(I61=0,0,VLOOKUP(G61,'Industry Average Beta (Global)'!$A$2:$M$95,13))
A62: Cost of Component | B62: =B24+C57*B27 | C62: =B37*(1-B38) | D62: =B50/B49 | E62: =B61*B62+C61*C62+D61*D62 | I62: =IF(G62=0,,VLOOKUP(G62,'Industry Average Beta (Global)'!$A$2:$O$95,15)) | J62: =H62*I62 | K62: =IF(G62=0,,VLOOKUP(G62,'Industry Average Beta (Global)'!$A$2:$O$95,7)) | L62: =IF(I62=0,0,VLOOKUP(G62,'Industry Average Beta (Global)'!$A$2:$M$95,13))
I63: =IF(G63=0,,VLOOKUP(G63,'Industry Average Beta (Global)'!$A$2:$O$95,15)) | J63: =H63*I63 | K63: =IF(G63=0,,VLOOKUP(G63,'Industry Average Beta (Global)'!$A$2:$O$95,7)) | L63: =IF(I63=0,0,VLOOKUP(G63,'Industry Average Beta (Global)'!$A$2:$M$95,13))
G64: Company | H64: =SUM(H52:H63) | J64: =SUM(J52:J63) | K64: =K52*(J52/J64)+K53*J53/J64+K54*J54/J64+K55*J55/J64+K56*J56/J64+K57*J57/J64+K58*J58/J64+K59*J59/J64+K60*J60/J64+K61*J61/J64+K62*J62/J64+K63*J63/J64 | L64: =L52*(J52/J64)+L53*J53/J64+L54*J54/J64+L55*J55/J64+L56*J56/J64+L57*J57/J64+L58*J58/J64+L59*J59/J64+L60*J60/J64+L61*J61/J64+L62*J62/J64+L63*J63/J64
A65: Approach 2: industry average cost of capital, adjusted for riskfre rate differences
A66: Industry | B66: Multibusiness(US)
A67: Cost of capital, adjusted for riskfree rate difference | B67: =IF(B66="Single Business(US)",(VLOOKUP('Input sheet'!B8,'Industry Averages(US)'!A2:M95,13)+('Input sheet'!B33-3.88%)),IF(B66="Multibusiness(US)",L48+('Input sheet'!B33-3.88%),IF(B66="Single Business(Global)",(VLOOKUP('Input sheet'!B8,'Industry Average Beta (Global)'!A2:M95,13)+('Input sheet'!B33-3.88%)),L64+('Input sheet'!B33-3.88%))))
A69: Approach 3: Uae histogram of costs of capital of all publicly traded firms
A70: Which grouping (US, Emerging Markets, Global) | B70: Global
A71: Which risk grouping does your company fall in? | B71: Third Quartile
A72: Cost of capital based upon decile/group chosen | B72: =VLOOKUP(B70,A75:F79,IF(B71="First Decile",2,IF(B71="First Quartile",3,IF(B71="Median",4,IF(B71="Third Quartile",5,6)))))
A74: Region | B74: First Decile | C74: First Quartile | D74: Median | E74: Third Quartile | F74: Ninth Decile
A75: Emerging | B75: 0.0741 | C75: 0.0844 | D75: 0.0961 | E75: 0.1099 | F75: 0.1281
A76: Europe | B76: 0.0678 | C76: 0.0765 | D76: 0.0897 | E76: 0.1011 | F76: 0.1152
A77: Global | B77: 0.0689 | C77: 0.0803 | D77: 0.0906 | E77: 0.1031 | F77: 0.1175
A78: Japan | B78: 0.0686 | C78: 0.0783 | D78: 0.0891 | E78: 0.0977 | F78: 0.1091
A79: US | B79: 0.0578 | C79: 0.0687 | D79: 0.0835 | E79: 0.0931 | F79: 0.1005
A80: These costs of capital are all in US dollars and reflect the US dollar riskfree rate at the start of the year. Once you make your choice, though, I will adjust the rate by the difference in riskfree rates, effectively converting currency and bringing it up to date.

Sheet Failure Rate worksheet
A1: Estimating the likelihood of failure
A2: Approach 1: Using a corporate bond rating
A4: Default Probabilities over time (1 - 10 year time horizons)
A5: Rating | B5: 1 | C5: 2 | D5: 3 | E5: 4 | F5: 5 | G5: 6 | H5: 7 | I5: 8 | J5: 9 | K5: 10
A6: AAA | B6: 0 | C6: 0.0003 | D6: 0.0013 | E6: 0.0024 | F6: 0.0035 | G6: 0.0045 | H6: 0.0051 | I6: 0.0059 | J6: 0.0064 | K6: 0.007
A7: AA | B7: 0.0002 | C7: 0.0006 | D7: 0.0012 | E7: 0.0021 | F7: 0.0031 | G7: 0.0042 | H7: 0.005 | I7: 0.0058 | J7: 0.0065 | K7: 0.0072
A8: A | B8: 0.0005 | C8: 0.0014 | D8: 0.0023 | E8: 0.0035 | F8: 0.0047 | G8: 0.0062 | H8: 0.0079 | I8: 0.0093 | J8: 0.0108 | K8: 0.0124
A9: BBB | B9: 0.0016 | C9: 0.0045 | D9: 0.0078 | E9: 0.0117 | F9: 0.0158 | G9: 0.0198 | H9: 0.0233 | I9: 0.0267 | J9: 0.03 | K9: 0.0332
A10: BB | B10: 0.0061 | C10: 0.0192 | D10: 0.0348 | E10: 0.0505 | F10: 0.0652 | G10: 0.0785 | H10: 0.0901 | I10: 0.1004 | J10: 0.1097 | K10: 0.1178
A11: B | B11: 0.0333 | C11: 0.0771 | D11: 0.1155 | E11: 0.1458 | F11: 0.1693 | G11: 0.1883 | H11: 0.2036 | I11: 0.216 | J11: 0.227 | K11: 0.2374
A12: CCC/C | B12: 0.2708 | C12: 0.3664 | D12: 0.4141 | E12: 0.441 | F12: 0.4619 | G12: 0.4709 | H12: 0.4826 | I12: 0.4905 | J12: 0.4976 | K12: 0.5038
A14: Thus, if you use the 10-year likelihood of failure, the chance of failure for a BB rated firm is 11.78%.
A16: Approach 2: Using corporate age (for young companies)
O17: Survial Rate Data from Bureau of Labor Statistics (2022)
C18: Agriculture | D18: Mining | E18: Utilities | F18: Construction | G18: Manufacturing | H18: Retail | I18: Transportation | J18: Information | K18: Health Care | L18: All Sectors | O18: Agriculture | P18: Mining | Q18: Utilities | R18: Construction | S18: Manufacturing | T18: Retail | U18: Transportation | V18: Information | W18: Health Care | X18: All Sectors
A19: Failure Rate given age | B19: 0 | C19: =1-O28 | D19: =1-P28 | E19: =1-Q28 | F19: =1-R28 | G19: =1-S28 | H19: =1-T28 | I19: =1-U28 | J19: =1-V28 | ... L19: =1-X28 | N19: 1 | O19: 0.823 | P19: 0.818 | Q19: 0.84 | R19: 0.743 | S19: 0.828 | T19: 0.831 | U19: 0.769 | V19: 0.752 | W19: 0.814 | X19: 0.783
B20: 1 | C20: =O19-O$28 | D20: =P19-P$28 | E20: =Q19-Q$28 | F20: =R19-R$28 | G20: =S19-S$28 | H20: =T19-T$28 | I20: =U19-U$28 | J20: =V19-V$28 | ... L20: =X19-X$28 | N20: 2 | O20: 0.748 | P20: 0.712 | Q20: 0.735 | R20: 0.598 | S20: 0.724 | T20: 0.724 | U20: 0.636 | V20: 0.627 | W20: 0.722 | X20: 0.662
B21: 2 | C21: =O20-O$28 | D21: =P20-P$28 | E21: =Q20-Q$28 | F21: =R20-R$28 | G21: =S20-S$28 | H21: =T20-T$28 | I21: =U20-U$28 | J21: =V20-V$28 | ... L21: =X20-X$28 | N21: 3 | O21: 0.661 | P21: 0.629 | Q21: 0.67 | R21: 0.456 | S21: 0.622 | T21: 0.631 | U21: 0.523 | V21: 0.533 | W21: 0.674 | X21: 0.566
B22: 3 | C22: =O21-O$28 | D22: =P21-P$28 | E22: =Q21-Q$28 | F22: =R21-R$28 | G22: =S21-S$28 | H22: =T21-T$28 | I22: =U21-U$28 | J22: =V21-V$28 | ... L22: =X21-X$28 | N22: 4 | O22: 0.612 | P22: 0.538 | Q22: 0.629 | R22: 0.371 | S22: 0.541 | T22: 0.565 | U22: 0.45 | V22: 0.464 | W22: 0.613 | X22: 0.498
B23: 4 | C23: =O22-O$28 | D23: =P22-P$28 | E23: =Q22-Q$28 | F23: =R22-R$28 | G23: =S22-S$28 | H23: =T22-T$28 | I23: =U22-U$28 | J23: =V22-V$28 | ... L23: =X22-X$28 | N23: 5 | O23: 0.574 | P23: 0.512 | Q23: 0.565 | R23: 0.332 | S23: 0.494 | T23: 0.521 | U23: 0.411 | V23: 0.419 | W23: 0.559 | X23: 0.454
B24: 5 | C24: =O23-O$28 | D24: =P23-P$28 | E24: =Q23-Q$28 | F24: =R23-R$28 | G24: =S23-S$28 | H24: =T23-T$28 | I24: =U23-U$28 | J24: =V23-V$28 | ... L24: =X23-X$28 | N24: 6 | O24: 0.541 | P24: 0.472 | Q24: 0.556 | R24: 0.306 | S24: 0.463 | T24: 0.485 | U24: 0.377 | V24: 0.372 | W24: 0.548 | X24: 0.423
B25: 6 | C25: =O24-O$28 | D25: =P24-P$28 | E25: =Q24-Q$28 | F25: =R24-R$28 | G25: =S24-S$28 | H25: =T24-T$28 | I25: =U24-U$28 | J25: =V24-V$28 | ... L25: =X24-X$28 | N25: 7 | O25: 0.516 | P25: 0.429 | Q25: 0.516 | R25: 0.284 | S25: 0.438 | T25: 0.457 | U25: 0.349 | V25: 0.34 | W25: 0.529 | X25: 0.396
B26: 7 | C26: =O25-O$28 | D26: =P25-P$28 | E26: =Q25-Q$28 | F26: =R25-R$28 | G26: =S25-S$28 | H26: =T25-T$28 | I26: =U25-U$28 | J26: =V25-V$28 | ... L26: =X25-X$28 | N26: 8 | O26: 0.495 | P26: 0.405 | Q26: 0.503 | R26: 0.271 | S26: 0.415 | T26: 0.433 | U26: 0.324 | V26: 0.314 | W26: 0.484 | X26: 0.371
B27: 8 | C27: =O26-O$28 | D27: =P26-P$28 | E27: =Q26-Q$28 | F27: =R26-R$28 | G27: =S26-S$28 | H27: =T26-T$28 | I27: =U26-U$28 | J27: =V26-V$28 | ... L27: =X26-X$28 | N27: 9 | O27: 0.465 | P27: 0.371 | Q27: 0.476 | R27: 0.258 | S27: 0.4 | T27: 0.41 | U27: 0.305 | V27: 0.274 | W27: 0.455 | X27: 0.348
B28: 9 | C28: =O27-O$28 | D28: =P27-P$28 | E28: =Q27-Q$28 | F28: =R27-R$28 | G28: =S27-S$28 | H28: =T27-T$28 | I28: =U27-U$28 | J28: =V27-V$28 | ... L28: =X27-X$28 | N28: 10 | O28: 0.449 | P28: 0.323 | Q28: 0.449 | R28: 0.247 | S28: 0.381 | T28: 0.39 | U28: 0.284 | V28: 0.255 | W28: 0.425 | X28: 0.328
B29: 10 | C29: =O28-O$28 | D29: =P28-P$28 | E29: =Q28-Q$28 | F29: =R28-R$28 | G29: =S28-S$28 | H29: =T28-T$28 | I29: =U28-U$28 | J29: =V28-V$28 | ... L29: =X28-X$28
A30: Source; Bureau of Labor Statistics
A31: Thus, if you are valuing a technology firm that is 6 years old, the chance of failure is 11.70%.
A33: Factors to consider
A34: 1. The likelihood of failure decreases for larger firms.
A35: 2. The likelihood of failure decreases with access to capital, and is thus lower for publicly traded firms or firms with multiple high profile VCs
A36: 3. The likelihood of failure decreases as revenue growth increases, since hope for future growth will sustain the firm.
A37: 4. The likelihood of failure decreases with better unit economics, higher gross margins on the additional units sold

Sheet Summary Sheet
A1: Year | B1: Revenues | C1: Revenue Growth Rate | D1: Pre-Tax Operating Margin | E1: Pre-Tax Operating Income | F1: NOL | G1: Taxes | H1: After-Tax Operating Income
A2: Traling 12 month | B2: ='Valuation output'!B3 | D2: ='Valuation output'!B4 | E2: =B2*D2 | F2: ='Valuation output'!B10 | G2: =E2-H2 | H2: ='Valuation output'!B7
A3: 1 | B3: ='Valuation output'!C3 | C3: ='Valuation output'!C2 | D3: ='Valuation output'!C4 | E3: =B3*D3 | F3: ='Valuation output'!C10 | G3: =E3-H3 | H3: ='Valuation output'!C7
A4: 2 | B4: ='Valuation output'!D3 | C4: =B4/B3-1 | D4: ='Valuation output'!D4 | E4: =B4*D4 | F4: ='Valuation output'!D10 | G4: =E4-H4 | H4: ='Valuation output'!D7
A5: 3 | B5: ='Valuation output'!E3 | C5: =B5/B4-1 | D5: ='Valuation output'!E4 | E5: =B5*D5 | F5: ='Valuation output'!E10 | G5: =E5-H5 | H5: ='Valuation output'!E7
A6: 4 | B6: ='Valuation output'!F3 | C6: =B6/B5-1 | D6: ='Valuation output'!F4 | E6: =B6*D6 | F6: ='Valuation output'!F10 | G6: =E6-H6 | H6: ='Valuation output'!F7
A7: 5 | B7: ='Valuation output'!G3 | C7: =B7/B6-1 | D7: ='Valuation output'!G4 | E7: =B7*D7 | F7: ='Valuation output'!G10 | G7: =E7-H7 | H7: ='Valuation output'!G7
A8: 6 | B8: ='Valuation output'!H3 | C8: =B8/B7-1 | D8: ='Valuation output'!H4 | E8: =B8*D8 | F8: ='Valuation output'!H10 | G8: =E8-H8 | H8: ='Valuation output'!H7
A9: 7 | B9: ='Valuation output'!I3 | C9: =B9/B8-1 | D9: ='Valuation output'!I4 | E9: =B9*D9 | F9: ='Valuation output'!I10 | G9: =E9-H9 | H9: ='Valuation output'!I7
A10: 8 | B10: ='Valuation output'!J3 | C10: =B10/B9-1 | D10: ='Valuation output'!J4 | E10: =B10*D10 | F10: ='Valuation output'!J10 | G10: =E10-H10 | H10: ='Valuation output'!J7
A11: 9 | B11: ='Valuation output'!K3 | C11: =B11/B10-1 | D11: ='Valuation output'!K4 | E11: =B11*D11 | F11: ='Valuation output'!K10 | G11: =E11-H11 | H11: ='Valuation output'!K7
A12: 10 | B12: ='Valuation output'!L3 | C12: =B12/B11-1 | D12: ='Valuation output'!L4 | E12: =B12*D12 | F12: ='Valuation output'!L10 | G12: =E12-H12 | H12: ='Valuation output'!L7
A14: Year | B14: After-Tax Operating Income | C14: Change in Revenues | D14: Sales to Capital | E14: Reinvestment | F14: FCFF | G14: Capital Invested | H14: Implied ROC
A15: =A2 | B15: =H2 | G15: ='Valuation output'!B58 | H15: =B15/G15
A16: =A3 | B16: =H3 | C16: =B3-B2 | D16: ='Valuation output'!C57 | E16: =C16/D16 | F16: =B16-E16 | G16: =G15+E16 | H16: =B16/G16
A17: =A4 | B17: =H4 | C17: =B4-B3 | D17: ='Valuation output'!D57 | E17: =C17/D17 | F17: =B17-E17 | G17: =G16+E17 | H17: =B17/G17
A18: =A5 | B18: =H5 | C18: =B5-B4 | D18: ='Valuation output'!E57 | E18: =C18/D18 | F18: =B18-E18 | G18: =G17+E18 | H18: =B18/G18
A19: =A6 | B19: =H6 | C19: =B6-B5 | D19: ='Valuation output'!F57 | E19: =C19/D19 | F19: =B19-E19 | G19: =G18+E19 | H19: =B19/G19
A20: =A7 | B20: =H7 | C20: =B7-B6 | D20: ='Valuation output'!G57 | E20: =C20/D20 | F20: =B20-E20 | G20: =G19+E20 | H20: =B20/G20
A21: =A8 | B21: =H8 | C21: =B8-B7 | D21: ='Valuation output'!H57 | E21: =C21/D21 | F21: =B21-E21 | G21: =G20+E21 | H21: =B21/G21
A22: =A9 | B22: =H9 | C22: =B9-B8 | D22: ='Valuation output'!I57 | E22: =C22/D22 | F22: =B22-E22 | G22: =G21+E22 | H22: =B22/G22
A23: =A10 | B23: =H10 | C23: =B10-B9 | D23: ='Valuation output'!J57 | E23: =C23/D23 | F23: =B23-E23 | G23: =G22+E23 | H23: =B23/G23
A24: =A11 | B24: =H11 | C24: =B11-B10 | D24: ='Valuation output'!K57 | E24: =C24/D24 | F24: =B24-E24 | G24: =G23+E24 | H24: =B24/G24
A25: =A12 | B25: =H12 | C25: =B12-B11 | D25: ='Valuation output'!L57 | E25: =C25/D25 | F25: =B25-E25 | G25: =G24+E25 | H25: =B25/G25
A27: Year | B27: Beta | C27: Cost of Equity | D27: Pre-Tax Cost of Debt | E27: Tax Savings | F27: After-Tax Cost of Debt | G27: Debt Ratio | H27: Cost of Capital
A28: =A16 | H28: ='Valuation output'!#REF!
A29: =A17 | H29: ='Valuation output'!#REF!
A30: =A18 | H30: ='Valuation output'!#REF!
A31: =A19 | H31: ='Valuation output'!#REF!
A32: =A20 | H32: ='Valuation output'!#REF!
A33: =A21 | H33: ='Valuation output'!#REF!
A34: =A22 | H34: ='Valuation output'!#REF!
A35: =A23 | H35: ='Valuation output'!#REF!
A36: =A24 | H36: ='Valuation output'!#REF!
A37: =A25 | H37: ='Valuation output'!#REF!
A39: Year | B39: Cost of Capital | C39: Cumulated Cost of Capital | D39: FCFF | E39: Terminal Value | F39: Present Value
A40: =A28 | B40: =H28 | C40: =(1+'Summary Sheet'!B40) | D40: =F16 | F40: =D40/C40
A41: =A29 | B41: =H29 | C41: =C40*(1+B41) | D41: =F17 | F41: =D41/C41
A42: =A30 | B42: =H30 | C42: =C41*(1+B42) | D42: =F18 | F42: =D42/C42
A43: =A31 | B43: =H31 | C43: =C42*(1+B43) | D43: =F19 | F43: =D43/C43
A44: =A32 | B44: =H32 | C44: =C43*(1+B44) | D44: =F20 | F44: =D44/C44
A45: =A33 | B45: =H33 | C45: =C44*(1+B45) | D45: =F21 | F45: =D45/C45
A46: =A34 | B46: =H34 | C46: =C45*(1+B46) | D46: =F22 | F46: =D46/C46
A47: =A35 | B47: =H35 | C47: =C46*(1+B47) | D47: =F23 | F47: =D47/C47
A48: =A36 | B48: =H36 | C48: =C47*(1+B48) | D48: =F24 | F48: =D48/C48
A49: =A37 | B49: =H37 | C49: =C48*(1+B49) | D49: =F25 | E49: ='Valuation output'!B39 | F49: =(D49+E49)/C49
A50: Value of operating assets = | F50: =SUM(F40:F49)

Sheet Country equity risk premiums
A1: Mature Market ERP + | B1: 0.0433 | C1: Updated anuary 1, 2025
A2: Changing this number will update all your country equity risk premiums.
A4: Country | B4: Moody's rating | C4: Adj. Default Spread | D4: Equity Risk Premium | E4: Country Risk Premium | F4: Corporate Tax Rate
A5: Abu Dhabi | B5: Aa2 | C5: 0.0048889784 | D5: =$B$1+E5 | E5: 0.0065910878 | F5: 0.15
A6: Albania | B6: Ba3 | C6: 0.0356197 | D6: =$B$1+E6 | E6: 0.048020783 | F6: 0.15
A7: Algeria | B7: NR | C7: 0.029799488 | D7: =$B$1+E7 | E7: 0.04017425 | F7: 0.15
A8: Andorra (Principality of) | B8: Baa1 | C8: 0.015830978 | D8: =$B$1+E8 | E8: 0.02134257 | F8: 0.1898
A9: Angola | B9: B3 | C9: 0.064371549 | D9: =$B$1+E9 | E9: 0.086782656 | F9: 0.25
A10: Anguilla | B10: NR | C10: 0.060122636 | D10: =$B$1+E10 | E10: 0.081054474 | F10: 0.25228019
A11: Antigua & Barbuda | B11: NR | C11: 0.0601 | D11: =$B$1+E11 | E11: 0.081012248 | F11: 0.2523
A12: Argentina | B12: Ca | C12: 0.11884874 | D12: =$B$1+E12 | E12: 0.16022621 | F12: 0.35
A13: Armenia | B13: Ba3 | C13: 0.0356197 | D13: =$B$1+E13 | E13: 0.048020783 | F13: 0.18
A14: Aruba | B14: Baa3 | C14: 0.021767594 | D14: =$B$1+E14 | E14: 0.029346034 | F14: 0.25
A15: Australia | B15: Aaa | C15: 0 | D15: =$B$1+E15 | E15: 0 | F15: 0.3
A16: Austria | B16: Aa1 | C16: 0.0039577444 | D16: =$B$1+E16 | E16: 0.0053356425 | F16: 0.24
... A196: Zimbabwe | B196: NR | C196: 0.089165654 | D196: =$B$1+E196 | E196: 0.12020889 | F196: 0.35
A200: Region | B200: ERP | C200: Default Spread | D200: Weighted Average: Default Spreads | E200: Tax Rate | F200: Weighted Average: CRP | G200: Total GDP (in $ millions)
A201: Africa | B201: =$B$1+D201 | C201: 0.058347166 | D201: 0.061639737 | E201: 0.27421915 | F201: 0.083065163 | G201: 2508220.7
A202: Asia | B202: =$B$1+D202 | C202: 0.010802217 | D202: 0.010708616 | E202: 0.25344179 | F202: 0.0154 | G202: 32948678
A203: Australia & New Zealand | B203: =$B$1+D203 | C203: 3.0266287e-05 | D203: 3.185925e-05 | E203: 0.29743621 | F203: 4.2933242e-05 | G203: 1942472.4
A204: Caribbean | B204: =$B$1+D204 | C204: 0.057116504 | D204: 0.060122636 | E204: 0.25228019 | F204: 0.081020731 | G204: 869389.48
A205: Central and South America | B205: =$B$1+D205 | C205: 0.035961225 | D205: 0.035769377 | E205: 0.31553953 | F205: 0.048202495 | G205: 5601817.8
A206: Eastern Europe | B206: =$B$1+D206 | C206: 0.025972276 | D206: 0.025213163 | E206: 0.17230578 | F206: 0.033977035 | G206: 5010073.3
A207: Middle East | B207: =$B$1+D207 | C207: 0.014034486 | D207: 0.015572785 | E207: 0.18937683 | F207: 0.020985747 | G207: 3382577.7
A208: North America | B208: =$B$1+D208 | C208: 0 | D208: 0 | E208: 0.25108814 | F208: 0 | G208: 27577639
A209: Western Europe | B209: =$B$1+D209 | C209: 0.0086832261 | D209: 0.0082741051 | E209: 0.2477522 | F209: 0.011150111 | G209: 20250229
A210: Global | B210: =$B$1+D210 | C210: 0.010700412 | D210: 0.010377276 | E210: 0.25221031 | F210: 0.0143 | G210: 1.000911e+08

Sheet Industry Averages(US)
A1: Industry Name | B1: Number of firms | C1: Annual Average Revenue growth - Last 5 years | D1: Pre-tax Operating Margin (Unadjusted) | E1: After-tax ROC | F1: Average effective tax rate | G1: Unlevered Beta | H1: Equity (Levered) Beta | I1: Cost of equity | J1: Std deviation in stock prices | K1: Pre-tax cost of debt | L1: Market Debt/Capital | M1: Cost of capital | N1: Sales/Capital | O1: EV/Sales | P1: EV/EBITDA | Q1: EV/EBIT | R1: Price/Book | S1: Trailing PE | T1: Non-cash WC as % of Revenues | U1: Cap Ex as % of Revenues | V1: Net Cap Ex as % of Revenues | W1: Reinvestment Rate | X1: ROE | Y1: Dividend Payout Ratio | Z1: Equity Reinvestment Rate | AA1: Pre-tax Operating Margin (Lease & R&D adjusted)
A2: Advertising | B2: 54 | C2: -0.016176667 | D2: 0.10900602 | E2: 0.34913077 | F2: 0.29273675 | G2: 1.196157 | H2: 1.3372941 | I2: 0.10370483 | J2: 0.67185667 | K2: 0.0641 | L2: 0.20758669 | M2: 0.09215682 | N2: 4.1947709 | O2: 2.7530321 | P2: 15.557573 | Q2: 24.270405 | R2: 6.976657 | S2: 291.27018 | T2: 0.032307738 | U2: 0.018063081 | V2: 0.0070344212 | W2: 0.16148109 | X2: 0.11852694 | Y2: 0.83363167 | Z2: 0.83363167 | AA2: 0.11395905
A3: Aerospace/Defense | B3: 67 | C3: 0.082055366 | D3: 0.075864631 | E3: 0.14025351 | F3: 0.16478876 | G3: 0.80089258 | H3: 0.90155313 | I3: 0.08483725 | J3: 0.42742401 | K3: 0.0553 | L3: 0.18562455 | M3: 0.076788152 | N3: 2.6209632 | O3: 2.6041799 | P3: 17.237956 | Q3: 28.387133 | R3: 6.825577 | S3: 87.417779 | T3: 0.38696212 | U3: 0.027915932 | V3: 0.0076674729 | W3: 0.65008606 | X3: 0.11941015 | Y3: 0.51504927 | Z3: 0.51504927 | AA3: 0.078696976
A4: Air Transport | B4: 24 | C4: 0.026369231 | D4: 0.055360162 | E4: 0.084763986 | F4: 0.22111636 | G4: 0.76485375 | H4: 1.2360067 | I4: 0.099319092 | J4: 0.65271639 | K4: 0.0641 | L4: 0.51650226 | M4: 0.072851403 | N4: 1.7451652 | O4: 1.0222121 | P4: 7.4650274 | Q4: 17.630171 | R4: 2.9413236 | S4: 17.981924 | T4: 0.010803799 | U4: 0.087934044 | V4: 0.043650452 | W4: 0.99545339 | X4: 0.13271934 | Y4: 0.14499244 | Z4: 0.14499244 | AA4: 0.055046004
A5: Apparel | B5: 37 | C5: 0.0696692 | D5: 0.087262866 | E5: 0.15256209 | F5: 0.18412185 | G5: 0.82670219 | H5: 0.99056805 | I5: 0.088691596 | J5: 0.50926388 | K5: 0.0578 | L5: 0.3145444 | M5: 0.074429651 | N5: 1.7344818 | O5: 1.4137614 | P5: 9.2153762 | Q5: 14.635936 | R5: 3.1369627 | S5: 28.054987 | T5: 0.24009395 | U5: 0.020011292 | V5: 0.001315238 | W5: -0.33753473 | X5: 0.084666289 | Y5: 0.62837259 | Z5: 0.62837259 | AA5: 0.096195175
A6: Auto & Truck | B6: 34 | C6: 0.10895222 | D6: 0.031316364 | E6: 0.031538761 | F6: 0.062980714 | G6: 1.4333545 | H6: 1.6154126 | I6: 0.11574737 | J6: 0.77591112 | K6: 0.0641 | L6: 0.18297971 | M6: 0.1033647 | N6: 1.1507771 | O6: 3.4699548 | P6: 37.443235 | Q6: 106.52228 | R6: 6.8543516 | S6: 27.282768 | T6: -0.019121502 | U6: 0.068059464 | V6: 0.029960463 | W6: 0.31341819 | X6: 0.092658993 | Y6: 0.069260275 | Z6: 0.069260275 | AA6: 0.033115493
A7: Auto Parts | B7: 33 | C7: 0.064891667 | D7: 0.050968432 | E7: 0.08659675 | F7: 0.21438279 | G7: 0.98664427 | H7: 1.2251238 | I7: 0.09884786 | J7: 0.52623749 | K7: 0.0578 | L7: 0.32356185 | M7: 0.080890869 | N7: 2.4258769 | O7: 0.74586437 | P7: 6.5271706 | Q7: 13.574321 | R7: 1.645472 | S7: 24.802889 | T7: 0.16214141 | U7: 0.033703735 | V7: 0.029796679 | W7: 0.98724784 | X7: 0.070868492 | Y7: 0.32661617 | Z7: 0.32661617 | AA7: 0.054112155
A8: Bank (Money Center) | B8: 15 | C8: 0.059959231 | D8: NA | E8: NA | F8: 0.18536212 | G8: 0.52502035 | H8: 0.87525288 | I8: 0.08369845 | J8: 0.30469401 | K8: 0.0553 | L8: 0.64687718 | M8: 0.056385063 | N8: 0 | O8: NA | P8: NA | Q8: NA | R8: 1.3220448 | S8: 28.041917 | T8: NA | U8: NA | V8: NA | W8: NA | X8: 0.1151632 | Y8: 0.31247661 | Z8: 0.31247661 | AA8: NA
A9: Banks (Regional) | B9: 591 | C9: 0.065430418 | D9: NA | E9: NA | F9: 0.21077505 | G9: 0.47508893 | H9: 0.51926094 | I9: 0.068283999 | J9: 0.29959993 | K9: 0.0508 | L9: 0.37623619 | M9: 0.056927686 | N9: 0 | O9: NA | P9: NA | Q9: NA | R9: 1.1291008 | S9: 18.412354 | T9: NA | U9: NA | V9: NA | W9: NA | X9: 0.068001195 | Y9: 0.55482977 | Z9: 0.55482977 | AA9: NA
A10: Beverage (Alcoholic) | B10: 18 | C10: 0.0508625 | D10: 0.22851541 | E10: 0.17863486 | F10: 0.21589979 | G10: 0.50620702 | H10: 0.61029786 | I10: 0.072225897 | J10: 0.63076376 | K10: 0.0578 | L10: 0.23351097 | M10: 0.065483059 | N10: 0.85107422 | O10: 3.3006471 | P10: 11.630381 | Q10: 14.398388 | R10: 2.6964073 | S10: 44.431034 | T10: 0.16418832 | U10: 0.086525687 | V10: 0.062082137 | W10: 0.35708516 | X10: 0.094907137 | Y10: 0.55497307 | Z10: 0.55497307 | AA10: 0.22883891
A11: Beverage (Soft) | B11: 29 | C11: 0.16750833 | D11: 0.20008555 | E11: 0.30609597 | F11: 0.19713421 | G11: 0.51288797 | H11: 0.5677661 | I11: 0.070384272 | J11: 0.47670268 | K11: 0.0578 | L11: 0.16479515 | M11: 0.065929155 | N11: 1.6739558 | O11: 4.0010981 | P11: 16.763124 | Q11: 19.866728 | R11: 7.4839161 | S11: 25.66698 | T11: -0.10319965 | U11: 0.053396374 | V11: 0.028297226 | W11: 0.26994041 | X11: 0.3060583 | Y11: 0.68694704 | Z11: 0.68694704 | AA11: 0.20137096
A12: Broadcasting | B12: 22 | C12: 0.018948125 | D12: 0.12511923 | E12: 0.12676647 | F12: 0.26794959 | G12: 0.47767444 | H12: 0.91752363 | I12: 0.085528773 | J12: 0.52595168 | K12: 0.0578 | L12: 0.59929947 | M12: 0.060251057 | N12: 1.1351345 | O12: 1.2871012 | P12: 7.2056458 | Q12: 10.263125 | R12: 1.0157799 | S12: 45.02352 | T12: 0.10428461 | U12: 0.018909044 | V12: -0.023811838 | W12: 2.0277458 | X12: -0.091235946 | Y12: 0.0062531244 | Z12: 0.0062531244 | AA12: 0.12512541
A13: Brokerage & Investment Banking | B13: 30 | C13: 0.22187095 | D13: NA | E13: NA | F13: 0.21118585 | G13: 0.47017758 | H13: 0.9522674 | I13: 0.087033179 | J13: 0.40490891 | K13: 0.0553 | L13: 0.65106515 | M13: 0.057371836 | N13: 0 | O13: NA | P13: NA | Q13: NA | R13: 2.1075534 | S13: 29.867932 | T13: NA | U13: NA | V13: NA | W13: NA | X13: 0.13110869 | Y13: 0.3715976 | Z13: 0.3715976 | AA13: NA
A14: Building Materials | B14: 39 | C14: 0.040569355 | D14: 0.13339808 | E14: 0.26836667 | F14: 0.23721141 | G14: 1.2345816 | H14: 1.3598827 | I14: 0.10468292 | J14: 0.34747493 | K14: 0.0553 | L14: 0.15947308 | M14: 0.09460296 | N14: 2.6563018 | O14: 2.3330553 | P14: 13.144109 | Q14: 17.280609 | R14: 4.2673352 | S14: 22.983758 | T14: 0.17589732 | U14: 0.033813891 | V14: 0.14426832 | W14: 1.357634 | X14: 0.27358512 | Y14: 0.16632376 | Z14: 0.16632376 | AA14: 0.13659536
A15: Business & Consumer Services | B15: 152 | C15: 0.052418068 | D15: 0.1210671 | E15: 0.26832207 | F15: 0.23839859 | G15: 0.92174211 | H15: 1.00385 | I15: 0.089266703 | J15: 0.45393206 | K15: 0.0578 | L15: 0.14369516 | M15: 0.082668695 | N15: 2.6612038 | O15: 2.9329096 | P15: 16.754385 | Q15: 23.770575 | R15: 5.9406153 | S15: 49.988354 | T15: 0.14466691 | U15: 0.028368194 | V15: -0.0011791142 | W15: 0.046745076 | X15: 0.1826562 | Y15: 0.41282665 | Z15: 0.41282665 | AA15: 0.12434266
A16: Cable TV | B16: 9 | C16: 0.24145 | D16: 0.18459798 | E16: 0.13752245 | F16: 0.24595154 | G16: 0.50420605 | H16: 0.96051074 | I16: 0.087390115 | J16: 0.49732784 | K16: 0.0578 | L16: 0.55821494 | M16: 0.062806265 | N16: 0.8503768 | O16: 2.2740102 | P16: 7.0399595 | Q16: 12.515126 | R16: 1.5110125 | S16: 10.7412 | T16: 0.01466126 | U16: 0.12745669 | V16: -0.0021867097 | W16: 0.04818005 | X16: 0.15502629 | Y16: 0.32245541 | Z16: 0.32245541 | AA16: 0.18156022
A17: Chemical (Basic) | B17: 31 | C17: 0.086697778 | D17: 0.060486894 | E17: 0.087115256 | F17: 0.17651352 | G17: 0.86036855 | H17: 1.1476869 | I17: 0.095494844 | J17: 0.5002162 | K17: 0.0578 | L17: 0.36810088 | M17: 0.076300281 | N17: 1.5856092 | O17: 1.0328956 | P17: 7.9670584 | Q17: 16.210396 | R17: 1.6112248 | S17: 25.808373 | T17: 0.15608311 | U17: 0.060077957 | V17: 0.037466858 | W17: 0.69395624 | X17: 0.063698091 | Y17: 1.2817897 | Z17: 1.2817897 | AA17: 0.062465659
A18: Chemical (Diversified) | B18: 4 | C18: 0.016685 | D18: 0.043609561 | E18: 0.053536736 | F18: 0 | G18: 0.58046503 | H18: 0.99413866 | I18: 0.088846204 | J18: 0.46970419 | K18: 0.0578 | L18: 0.53078499 | M18: 0.064697502 | N18: 1.3096091 | O18: 0.99834666 | P18: 9.2737113 | Q18: 22.259387 | R18: 1.3756962 | S18: 33.223684 | T18: 0.19024416 | U18: 0.056483491 | V18: 0.0030959738 | W18: 0.2143221 | X18: -0.013011807 | Y18: 0.019605263 | Z18: 0.019605263 | AA18: 0.043824309
A19: Chemical (Specialty) | B19: 60 | C19: 0.091944222 | D19: 0.11934945 | E19: 0.11308896 | F19: 0.20545318 | G19: 0.79421458 | H19: 0.92154891 | I19: 0.085703068 | J19: 0.48149355 | K19: 0.0578 | L19: 0.21336957 | M19: 0.076666212 | N19: 1.134432 | O19: 2.7705093 | P19: 13.305677 | Q19: 22.129731 | R19: 2.5680733 | S19: 43.856679 | T19: 0.22293596 | U19: 0.08817628 | V19: 0.052027276 | W19: 0.54297215 | X19: 0.077759098 | Y19: 0.59231875 | Z19: 0.59231875 | AA19: 0.1212337
A20: Coal & Related Energy | B20: 16 | C20: 0.0065125 | D20: 0.10974054 | E20: 0.13136099 | F20: 0.17764285 | G20: 1.266679 | H20: 1.182063 | I20: 0.096983328 | J20: 0.53778223 | K20: 0.0578 | L20: 0.086500148 | M20: 0.092344037 | N20: 1.2410015 | O20: 1.5677608 | P20: 3.8937525 | Q20: 7.9798441 | R20: 1.6524339 | S20: 8.928954 | T20: 0.10744364 | U20: 0.10056739 | V20: 0.04181844 | W20: 0.7841825 | X20: 0.11335307 | Y20: 0.06849833 | Z20: 0.06849833 | AA20: 0.11036163
A21: Computer Services | B21: 63 | C21: 0.093410571 | D21: 0.060552453 | E21: 0.2051186 | F21: 0.15828324 | G21: 1.091807 | H21: 1.2344606 | I21: 0.099252145 | J21: 0.44396279 | K21: 0.0553 | L21: 0.20842271 | M21: 0.087210076 | N21: 4.7139988 | O21: 1.3841287 | P21: 14.291252 | Q21: 21.794178 | R21: 4.5486513 | S21: 56.19389 | T21: 0.13791056 | U21: 0.0099162488 | V21: 0.0013792624 | W21: -0.1352498 | X21: 0.174426 | Y21: 0.55313082 | Z21: 0.55313082 | AA21: 0.06447428
A22: Computers/Peripherals | B22: 35 | C22: 0.035478846 | D22: 0.22650657 | E22: 0.41408712 | F22: 0.22873507 | G22: 1.1182873 | H22: 1.1422456 | I22: 0.095259236 | J22: 0.52621968 | K22: 0.0578 | L22: 0.045958193 | M22: 0.092873582 | N22: 3.3449301 | O22: 6.6791419 | P22: 25.359132 | Q22: 29.389549 | R22: 38.955771 | S22: 610.14732 | T22: -0.07992706 | U22: 0.025816046 | V22: 0.0033470275 | W22: 0.021789697 | X22: 0.00020232635 | Y22: 0.17968918 | Z22: 0.17968918 | AA22: 0.22950815
A23: Construction Supplies | B23: 46 | C23: 0.037463548 | D23: 0.15132789 | E23: 0.18411663 | F23: 0.2173442 | G23: 1.1527822 | H23: 1.2936372 | I23: 0.10181449 | J23: 0.47524839 | K23: 0.0578 | L23: 0.17739375 | M23: 0.091443256 | N23: 1.5644348 | O23: 2.4608868 | P23: 12.622658 | Q23: 16.105371 | R23: 4.3882268 | S23: 18.967552 | T23: 0.18587441 | U23: 0.048192359 | V23: 0.038508067 | W23: 0.4233188 | X23: 0.2562598 | Y23: 0.29216332 | Z23: 0.29216332 | AA23: 0.1520683
A24: Diversified | B24: 21 | C24: 0.11620111 | D24: 0.32847329 | E24: 0.24653408 | F24: 0.19221263 | G24: 1.0140268 | H24: 1.0899964 | I24: 0.092996845 | J24: 0.59349661 | K24: 0.0578 | L24: 0.13859853 | M24: 0.086115865 | N24: 0.79974779 | O24: 2.9071161 | P24: 7.8569258 | Q24: 8.8072144 | R24: 1.806285 | S24: 13.032909 | T24: 0.01489651 | U24: 0.048625329 | V24: 0.030015662 | W24: 0.10870946 | X24: 0.208988 | Y24: 0.050332683 | Z24: 0.050332683 | AA24: 0.33000089
A25: Drugs (Biotechnology) | B25: 535 | C25: 0.23766171 | D25: 0.014221273 | E25: 0.030814784 | F25: 0.19482955 | G25: 1.1689512 | H25: 1.2519481 | I25: 0.10000935 | J25: 0.86827812 | K25: 0.0758 | L25: 0.1459806 | M25: 0.093708925 | N25: 0.93339464 | O25: 6.7917911 | P25: 15.186565 | Q25: NA | R25: 6.0170977 | S25: 84.994302 | T25: 0.1364562 | U25: 0.033607871 | V25: 0.24938462 | W25: NA | X25: -0.14115598 | Y25: 0.009746278 | Z25: 0.009746278 | AA25: 0.074882658
A26: Drugs (Pharmaceutical) | B26: 231 | C26: 0.24784957 | D26: 0.22807562 | E26: 0.1407987 | F26: 0.13582709 | G26: 0.98336094 | H26: 1.0737971 | I26: 0.092295416 | J26: 0.80048454 | K26: 0.0758 | L26: 0.14449997 | M26: 0.087173554 | N26: 1.014858 | O26: 5.4837121 | P26: 15.368863 | Q26: 23.367949 | R26: 5.699401 | S26: 20.88293 | T26: 0.25087194 | U26: 0.053594365 | V26: 0.23936247 | W26: 1.1762437 | X26: 0.10492983 | Y26: 1.2549442 | Z26: 1.2549442 | AA26: 0.25591612
A27: Education | B27: 29 | C27: 0.04766 | D27: 0.092405384 | E27: 0.11855547 | F27: 0.2561145 | G27: 0.92211126 | H27: 0.98317228 | I27: 0.08837136 | J27: 0.55822687 | K27: 0.0578 | L27: 0.16279108 | M27: 0.081042284 | N27: 1.8590089 | O27: 2.4903032 | P27: 14.254584 | Q27: 28.470503 | R27: 3.3561827 | S27: 33.921511 | T27: 0.079872593 | U27: 0.031075975 | V27: 0.0089103062 | W27: 0.30448849 | X27: 0.042221737 | Y27: 0.71873518 | Z27: 0.71873518 | AA27: 0.085465634
A28: Electrical Equipment | B28: 101 | C28: 0.13288854 | D28: 0.071521814 | E28: 0.12226468 | F28: 0.20188534 | G28: 1.2010769 | H28: 1.2697511 | I28: 0.10078022 | J28: 0.7211567 | K28: 0.0641 | L28: 0.1292534 | M28: 0.093967892 | N28: 2.0875372 | O28: 3.3071963 | P28: 19.60583 | Q28: 41.435042 | R28: 4.0692398 | S28: 55.433924 | T28: 0.28872735 | U28: 0.050657052 | V28: 0.10742964 | W28: 2.0270788 | X28: 0.047772955 | Y28: 0.80268485 | Z28: 0.80268485 | AA28: 0.076432655
A29: Electronics (Consumer & Office) | B29: 11 | C29: -0.069977143 | D29: -0.05297232 | E29: -0.058115332 | F29: #DIV/0! | G29: 0.95363638 | H29: 0.9196352 | I29: 0.085620204 | J29: 0.73198977 | K29: 0.0641 | L29: 0.11745374 | M29: 0.081210379 | N29: 2.7373985 | O29: 0.72469459 | P29: 44.48899 | Q29: NA | R29: 2.2193726 | S29: #DIV/0! | T29: 0.12810473 | U29: 0.020722079 | V29: 0.0021872119 | W29: NA | X29: -0.30964018 | Y29: #DIV/0! | Z29: #DIV/0! | AA29: -0.048685426
A30: Electronics (General) | B30: 122 | C30: 0.10585198 | D30: 0.081549817 | E30: 0.13112418 | F30: 0.19228955 | G30: 1.0112706 | H30: 1.0582316 | I30: 0.091621429 | J30: 0.6160856 | K30: 0.0578 | L30: 0.12603197 | M30: 0.085537686 | N30: 2.1729518 | O30: 2.4557309 | P30: 17.283481 | Q30: 28.93182 | R30: 3.752862 | S30: 74.938248 | T30: 0.22928356 | U30: 0.033053712 | V30: 0.047231928 | W30: 0.54226763 | X30: 0.10193122 | Y30: 0.2222524 | Z30: 0.2222524 | AA30: 0.083700233
A31: Engineering/Construction | B31: 42 | C31: 0.086511481 | D31: 0.055676522 | E31: 0.19158079 | F31: 0.26452669 | G31: 0.91716412 | H31: 0.98791529 | I31: 0.088576732 | J31: 0.47331966 | K31: 0.0578 | L31: 0.15199106 | M31: 0.081702673 | N31: 3.8629621 | O31: 1.4093069 | P31: 15.646991 | Q31: 24.03091 | R31: 4.8115469 | S31: 44.734075 | T31: 0.18589283 | U31: 0.023582468 | V31: 0.038518529 | W31: 0.84197589 | X31: 0.130824 | Y31: 0.082519842 | Z31: 0.082519842 | AA31: 0.05839409
A32: Entertainment | B32: 96 | C32: 0.13250966 | D32: 0.083399915 | E32: 0.099413466 | F32: 0.18832506 | G32: 0.93752432 | H32: 1.0409093 | I32: 0.090871371 | J32: 0.62697912 | K32: 0.0578 | L32: 0.16899577 | M32: 0.08284046 | N32: 1.4069695 | O32: 3.9046945 | P32: 19.610967 | Q32: 45.584062 | R32: 4.0679111 | S32: 84.243189 | T32: 0.015271226 | U32: 0.036993536 | V32: -0.039181988 | W32: -0.71185667 | X32: -0.039027958 | Y32: 0.00081707032 | Z32: 0.00081707032 | AA32: 0.082564197
A33: Environmental & Waste Services | B33: 50 | C33: 0.19639524 | D33: 0.14893093 | E33: 0.31722931 | F33: 0.22539063 | G33: 0.81543659 | H33: 0.92047027 | I33: 0.085656363 | J33: 0.54475822 | K33: 0.0578 | L33: 0.1619422 | M33: 0.078805177 | N33: 2.3193891 | O33: 3.6831618 | P33: 15.816654 | Q33: 24.291419 | R33: 6.6546338 | S33: 86.590526 | T33: 0.10122787 | U33: 0.086852736 | V33: 0.064171995 | W33: 0.5897644 | X33: 0.22316956 | Y33: 0.36332109 | Z33: 0.36332109 | AA33: 0.15120144
A34: Farming/Agriculture | B34: 35 | C34: 0.22231053 | D34: 0.072528629 | E34: 0.099660979 | F34: 0.23425644 | G34: 0.73179853 | H34: 0.98238816 | I34: 0.088337407 | J34: 0.69591326 | K34: 0.0641 | L34: 0.34780956 | M34: 0.074333757 | N34: 1.5671727 | O34: 1.1820782 | P34: 11.764312 | Q34: 15.776928 | R34: 2.5034534 | S34: 35.002915 | T34: 0.14866693 | U34: 0.039422639 | V34: 0.033604203 | W34: 0.44796407 | X34: 0.15326132 | Y34: 0.30570616 | Z34: 0.30570616 | AA34: 0.074664801
A35: Financial Svcs. (Non-bank & Insurance) | B35: 166 | C35: 0.1479327 | D35: 0.16330572 | E35: NA | F35: 0.1861937 | G35: 0.35059353 | H35: 1.0734899 | I35: 0.092282113 | J35: 0.4195847 | K35: 0.0553 | L35: 0.74137337 | M35: 0.054615072 | N35: 0.068100315 | O35: 19.303479 | P35: 62.824401 | Q35: 79.267753 | R35: 3.797378 | S35: 30.211083 | T35: 12.499751 | U35: 0.026661394 | V35: 0.01791866 | W35: 0.14977712 | X35: 0.31548808 | Y35: 0.18129346 | Z35: 0.18129346 | AA35: 0.16436087
A36: Food Processing | B36: 77 | C36: 0.1001784 | D36: 0.11969899 | E36: 0.17900874 | F36: 0.24155911 | G36: 0.38277696 | H36: 0.47424024 | I36: 0.066334602 | J36: 0.46269573 | K36: 0.0578 | L36: 0.26751649 | M36: 0.060185842 | N36: 1.6975231 | O36: 1.7945613 | P36: 11.167311 | Q36: 14.755007 | R36: 2.1753859 | S36: 27.673229 | T36: 0.056479431 | U36: 0.03988083 | V36: 0.04355998 | W36: 0.41589524 | X36: 0.09802418 | Y36: 0.67956385 | Z36: 0.67956385 | AA36: 0.12132969
A37: Food Wholesalers | B37: 14 | C37: 0.11898 | D37: 0.026683235 | E37: 0.1730373 | F37: 0.23847854 | G37: 0.55477746 | H37: 0.72463223 | I37: 0.077176576 | J37: 0.39167026 | K37: 0.0553 | L37: 0.30206832 | M37: 0.066392261 | N37: 7.7773251 | O37: 0.44417811 | P37: 10.770682 | Q37: 16.860431 | R37: 4.5141609 | S37: 29.303463 | T37: 0.057112801 | U37: 0.0099436103 | V37: 0.014365743 | W37: 0.72301944 | X37: 0.20052924 | Y37: 0.34499482 | Z37: 0.34499482 | AA37: 0.026340676
A38: Furn/Home Furnishings | B38: 28 | C38: -0.0028295238 | D38: 0.065064335 | E38: 0.10653951 | F38: 0.21164393 | G38: 0.69019058 | H38: 0.86624269 | I38: 0.083308309 | J38: 0.54801472 | K38: 0.0578 | L38: 0.29543892 | M38: 0.071503069 | N38: 1.9591798 | O38: 1.1838951 | P38: 10.179237 | Q38: 17.216244 | R38: 2.3694623 | S38: 30.847498 | T38: 0.15734604 | U38: 0.029978651 | V38: 0.011233595 | W38: 0.11503778 | X38: 0.058499602 | Y38: 0.84338214 | Z38: 0.84338214 | AA38: 0.068585729
A39: Green & Renewable Energy | B39: 18 | C39: 0.1573 | D39: 0.21598234 | E39: 0.036682308 | F39: 0.057241379 | G39: 0.50052545 | H39: 1.1304253 | I39: 0.094747414 | J39: 0.71930257 | K39: 0.0641 | L39: 0.63791864 | M39: 0.064974211 | N39: 0.18825826 | O39: 6.3834981 | P39: 11.304546 | Q39: 31.905381 | R39: 0.76045811 | S39: 25.511222 | T39: -0.37543127 | U39: 0.49500959 | V39: 0.38159403 | W39: 1.5993934 | X39: -0.11574517 | Y39: 0.00081832444 | Z39: 0.00081832444 | AA39: 0.19738797
A40: Healthcare Products | B40: 218 | C40: 0.14605857 | D40: 0.14812122 | E40: 0.14710426 | F40: 0.15966033 | G40: 0.9580877 | H40: 1.0145167 | I40: 0.089728573 | J40: 0.67405286 | K40: 0.0641 | L40: 0.11340903 | M40: 0.085004682 | N40: 1.3345093 | O40: 5.2006861 | P40: 21.197595 | Q40: 33.633725 | R40: 4.7566126 | S40: 45.251638 | T40: 0.2669413 | U40: 0.047980861 | V40: 0.045760403 | W40: 0.55462868 | X40: 0.088810773 | Y40: 0.35807522 | Z40: 0.35807522 | AA40: 0.15146904
A41: Healthcare Support Services | B41: 113 | C41: 0.11339571 | D41: 0.03436937 | E41: 0.44602956 | F41: 0.23085871 | G41: 0.81535001 | H41: 0.94121293 | I41: 0.08655452 | J41: 0.53996782 | K41: 0.0578 | L41: 0.24357689 | M41: 0.076030897 | N41: 14.649504 | O41: 0.52599305 | P41: 11.315758 | Q41: 15.14891 | R41: 2.8942972 | S41: 38.829719 | T41: -0.069306453 | U41: 0.0063339834 | V41: 0.0074326016 | W41: 0.45953028 | X41: 0.11660456 | Y41: 0.42183665 | Z41: 0.42183665 | AA41: 0.03427554
A42: Heathcare Information and Technology | B42: 116 | C42: 0.14728 | D42: 0.13352299 | E42: 0.12742981 | F42: 0.1651096 | G42: 1.1234094 | H42: 1.2229237 | I42: 0.098752597 | J42: 0.64543812 | K42: 0.0578 | L42: 0.13938046 | M42: 0.091030558 | N42: 1.2215733 | O42: 5.3118895 | P42: 22.011352 | Q42: 38.61752 | R42: 3.9295596 | S42: 54.467381 | T42: 0.23103515 | U42: 0.040037161 | V42: 0.053782455 | W42: 0.3802678 | X42: 0.039337638 | Y42: 0.25671826 | Z42: 0.25671826 | AA42: 0.13495449
A43: Homebuilding | B43: 30 | C43: 0.090010909 | D43: 0.15524694 | E43: 0.21045793 | F43: 0.23178301 | G43: 1.3762359 | H43: 1.4274867 | I43: 0.10761017 | J43: 0.41432025 | K43: 0.0553 | L43: 0.1489459 | M43: 0.097759611 | N43: 1.6411184 | O43: 1.243097 | P43: 7.6474289 | Q43: 7.9742937 | R43: 1.7480276 | S43: 10.852486 | T43: 0.63170581 | U43: 0.0057858923 | V43: 0.0072897974 | W43: 0.51379466 | X43: 0.20149423 | Y43: 0.072972851 | Z43: 0.072972851 | AA43: 0.15587403
A44: Hospitals/Healthcare Facilities | B44: 33 | C44: 0.015660526 | D44: 0.12448735 | E44: 0.21189862 | F44: 0.22234896 | G44: 0.56526134 | H44: 0.85708161 | I44: 0.082911634 | J44: 0.50809906 | K44: 0.0578 | L44: 0.4355154 | M44: 0.065681933 | N44: 1.9243115 | O44: 1.4840223 | P44: 8.1121465 | Q44: 12.210147 | R44: 4.281727 | S44: 19.90376 | T44: 0.10773433 | U44: 0.05840346 | V44: 0.029405358 | W44: 0.33957034 | X44: 0.76100912 | Y44: 0.23156762 | Z44: 0.23156762 | AA44: 0.12143679
A45: Hotel/Gaming | B45: 65 | C45: 0.11904537 | D45: 0.1814697 | E45: 0.12172347 | F45: 0.14872131 | G45: 0.95072145 | H45: 1.1937608 | I45: 0.097489842 | J45: 0.45095329 | K45: 0.0578 | L45: 0.30173037 | M45: 0.081154207 | N45: 0.9762978 | O45: 4.2829604 | P45: 15.417626 | Q45: 28.231253 | R45: 14.590953 | S45: 33.744808 | T45: 0.02288365 | U45: 0.077795835 | V45: 0.02025023 | W45: 0.25417209 | X45: 0.42051077 | Y45: 0.15158277 | Z45: 0.15158277 | AA45: 0.14904859
A46: Household Products | B46: 101 | C46: 0.031504091 | D46: 0.18381525 | E46: 0.33557668 | F46: 0.22492009 | G46: 0.82892968 | H46: 0.89526498 | I46: 0.084564974 | J46: 0.56670354 | K46: 0.0578 | L46: 0.1321202 | M46: 0.079119643 | N46: 2.2174325 | O46: 3.5277078 | P46: 15.311706 | Q46: 18.971627 | R46: 7.3313556 | S46: 32.173838 | T46: 0.068959791 | U46: 0.035264087 | V46: 0.0021758105 | W46: 0.012952165 | X46: 0.26244956 | Y46: 0.73878638 | Z46: 0.73878638 | AA46: 0.18562429
A47: Information Services | B47: 16 | C47: 0.02525 | D47: 0.11538317 | E47: 0.24548991 | F47: 0.23243236 | G47: 0.80315905 | H47: 0.98448932 | I47: 0.088428388 | J47: 0.39658065 | K47: 0.0553 | L47: 0.26126942 | M47: 0.076160904 | N47: 2.7320131 | O47: 2.2692123 | P47: 11.74754 | Q47: 18.678482 | R47: 3.7266775 | S47: 21.277616 | T47: 0.1687025 | U47: 0.020095381 | V47: 0.037257759 | W47: 0.44710104 | X47: 0.15903367 | Y47: 0.34174988 | Z47: 0.34174988 | AA47: 0.1224416
... A50: Insurance (Prop/Cas.) | B50: 53 | C50: 0.091218667 | D50: 0.13631717 | E50: 0.21986027 | F50: 0.20317549 | G50: 0.56901977 | H50: 0.60566358 | I50: 0.072025233 | J50: 0.33688355 | K50: 0.0553 | L50: 0.13391402 | M50: 0.067934128 | N50: 1.911339 | O50: 1.5092145 | P50: 10.216278 | Q50: 10.963946 | R50: 2.33233 | S50: 16.589026 | T50: -0.38805051 | U50: 0.0076276048 | V50: 0.0061452887 | W50: 0.22655292 | X50: 0.22604897 | Y50: 0.16875745 | Z50: 0.16875745 | AA50: 0.13702141
A51: Investments & Asset Management | B51: 231 | C51: 0.083659455 | D51: 0.14487822 | E51: 0.06797686 | F51: 0.18718662 | G51: 0.49932623 | H51: 0.56713616 | I51: 0.070356996 | J51: 0.22941033 | K51: 0.0508 | L51: 0.25950158 | M51: 0.061986254 | N51: 0.516545 | O51: 6.0123897 | P51: 41.404367 | Q51: 41.450814 | R51: 2.5278122 | S51: 56.097872 | T51: NA | U51: 0.024697761 | V51: 0.054996962 | W51: 0.48858293 | X51: 0.13317232 | Y51: 0.59629399 | Z51: 0.59629399 | AA51: 0.14125835
A52: Machinery | B52: 109 | C52: 0.062251029 | D52: 0.15789971 | E52: 0.24758723 | F52: 0.21009486 | G52: 0.98352421 | H52: 1.0672423 | I52: 0.092011591 | J52: 0.4607333 | K52: 0.0578 | L52: 0.13568778 | M52: 0.085408807 | N52: 1.9682598 | O52: 3.2279049 | P52: 15.350424 | Q52: 20.022926 | R52: 4.2734116 | S52: 33.326767 | T52: 0.25444087 | U52: 0.023858725 | V52: 0.050323075 | W52: 0.35902578 | X52: 0.16564121 | Y52: 0.34237039 | Z52: 0.34237039 | AA52: 0.15989799
A53: Metals & Mining | B53: 64 | C53: 0.018413846 | D53: 0.22622928 | E53: 0.27131917 | F53: 0.36243196 | G53: 0.96159827 | H53: 1.0222506 | I53: 0.090063449 | J53: 0.72372346 | K53: 0.0641 | L53: 0.14354307 | M53: 0.084036298 | N53: 1.2286157 | O53: 2.8868181 | P53: 8.6804332 | Q53: 12.272595 | R53: 3.1156411 | S53: 74.863844 | T53: 0.16545695 | U53: 0.13377771 | V53: 0.058526634 | W53: 0.57078146 | X53: 0.12502994 | Y53: 0.69063201 | Z53: 0.69063201 | AA53: 0.22647118
A54: Office Equipment & Services | B54: 14 | C54: 0.14147667 | D54: 0.081660455 | E54: 0.15003947 | F54: 0.2164797 | G54: 0.9638144 | H54: 1.2004956 | I54: 0.097781459 | J54: 0.49892004 | K54: 0.0578 | L54: 0.3174372 | M54: 0.080502889 | N54: 2.3287715 | O54: 1.2000345 | P54: 8.7653945 | Q54: 14.162062 | R54: 2.856526 | S54: 14.811538 | T54: 0.065899804 | U54: 0.021693865 | V54: -0.0022258744 | W54: -0.22156951 | X54: 0.033707708 | Y54: 2.012592 | Z54: 2.012592 | AA54: 0.084755858
A55: Oil/Gas (Integrated) | B55: 4 | C55: 0.00195 | D55: 0.13434037 | E55: 0.129034 | F55: 0.30257395 | G55: 0.45577993 | H55: 0.483682 | I55: 0.066743431 | J55: 0.2555953 | K55: 0.0508 | L55: 0.12058732 | M55: 0.063289396 | N55: 1.2679675 | O55: 1.5157082 | P55: 6.6954772 | Q55: 11.055015 | R55: 1.6638982 | S55: 10.82669 | T55: 0.036147155 | U55: 0.083827163 | V55: 0.019303911 | W55: 0.28275164 | X55: 0.14204315 | Y55: 0.52371706 | Z55: 0.52371706 | AA55: 0.13718198
A56: Oil/Gas (Production and Exploration) | B56: 147 | C56: 0.053528533 | D56: 0.29540458 | E56: 0.18619989 | F56: 0.23663745 | G56: 0.7545351 | H56: 0.87592934 | I56: 0.083727741 | J56: 0.47658851 | K56: 0.0578 | L56: 0.21040224 | M56: 0.075232173 | N56: 0.66742412 | O56: 3.077234 | P56: 5.6022673 | Q56: 10.139033 | R56: 1.739888 | S56: 19.102466 | T56: 0.015250158 | U56: 0.36742825 | V56: 0.17944803 | W56: 0.74392646 | X56: 0.17604363 | Y56: 0.3763251 | Z56: 0.3763251 | AA56: 0.3006389
A57: Oil/Gas Distribution | B57: 24 | C57: 0.19872067 | D57: 0.28061579 | E57: 0.12176139 | F57: 0.19723763 | G57: 0.55077587 | H57: 0.7547075 | I57: 0.078478835 | J57: 0.3817415 | K57: 0.0553 | L57: 0.34010076 | M57: 0.065893802 | N57: 0.48899531 | O57: 4.9810847 | P57: 12.164142 | Q57: 17.299809 | R57: 3.2118746 | S57: 27.817917 | T57: 0.02868263 | U57: 0.22848825 | V57: 0.15403105 | W57: 0.64754026 | X57: 0.19746513 | Y57: 0.60725117 | Z57: 0.60725117 | AA57: 0.28455532
A58: Oilfield Svcs/Equip. | B58: 97 | C58: 0.052465846 | D58: 0.049926821 | E58: 0.14367132 | F58: 0.19763426 | G58: 0.77777933 | H58: 0.93760052 | I58: 0.086398103 | J58: 0.49488387 | K58: 0.0578 | L58: 0.27810053 | M58: 0.074426402 | N58: 3.1319386 | O58: 0.6072836 | P58: 7.3500173 | Q58: 11.69672 | R58: 1.746243 | S58: 29.325088 | T58: 0.075072931 | U58: 0.023850467 | V58: 0.002021968 | W58: -0.014857775 | X58: 0.13265562 | Y58: 0.38724444 | Z58: 0.38724444 | AA58: 0.051850059
A59: Packaging & Container | B59: 22 | C59: 0.040221667 | D59: 0.097903437 | E59: 0.14486486 | F59: 0.21399991 | G59: 0.73835419 | H59: 0.97636341 | I59: 0.088076536 | J59: 0.33975428 | K59: 0.0553 | L59: 0.34603581 | M59: 0.071950735 | N59: 1.7435135 | O59: 1.5409264 | P59: 9.457927 | Q59: 15.428794 | R59: 2.8490477 | S59: 26.09845 | T59: 0.10248735 | U59: 0.056274025 | V59: 0.016203867 | W59: 0.14127571 | X59: 0.20757288 | Y59: 0.32348788 | Z59: 0.32348788 | AA59: 0.099785231
A60: Paper/Forest Products | B60: 6 | C60: 0.04535 | D60: 0.10131944 | E60: 0.1941948 | F60: 0.25599916 | G60: 0.95888221 | H60: 1.071741 | I60: 0.092206387 | J60: 0.60657458 | K60: 0.0578 | L60: 0.1841133 | M60: 0.083211276 | N60: 2.4742493 | O60: 1.2326955 | P60: 7.8733524 | Q60: 11.956088 | R60: 3.5653256 | S60: 23.336023 | T60: 0.081604638 | U60: 0.053265179 | V60: 0.078687607 | W60: 0.82134475 | X60: 0.24202243 | Y60: 0.19507471 | Z60: 0.19507471 | AA60: 0.10331067
A61: Power | B61: 48 | C61: 0.050618571 | D61: 0.19751183 | E61: 0.065649115 | F61: 0.13258131 | G61: 0.34271383 | H61: 0.54234863 | I61: 0.069283696 | J61: 0.27314273 | K61: 0.0508 | L61: 0.44547962 | M61: 0.055391995 | N61: 0.38012046 | O61: 4.3250131 | P61: 11.873307 | Q61: 21.89016 | R61: 2.073413 | S61: 23.267833 | T61: 0.080326096 | U61: 0.36491878 | V61: 0.23573285 | W61: 1.4296025 | X61: 0.11130193 | Y61: 0.55463775 | Z61: 0.55463775 | AA61: 0.19673168
A62: Precious Metals | B62: 60 | C62: 0.0447 | D62: 0.18829184 | E62: 0.12926868 | F62: 0.42903313 | G62: 1.1452183 | H62: 1.2283148 | I62: 0.09898603 | J62: 0.70971952 | K62: 0.0641 | L62: 0.15894995 | M62: 0.090893724 | N62: 0.709283 | O62: 3.061824 | P62: 8.1677222 | Q62: 15.627358 | R62: 1.6107918 | S62: 28.220425 | T62: 0.20137848 | U62: 0.20150782 | V62: 0.030208703 | W62: 0.58808355 | X62: -0.038158326 | Y62: 0.015321367 | Z62: 0.015321367 | AA62: 0.18924617
A63: Publishing & Newspapers | B63: 19 | C63: 0.015013333 | D63: 0.083015686 | E63: 0.15529614 | F63: 0.32131794 | G63: 0.55734329 | H63: 0.63735309 | I63: 0.073397389 | J63: 0.41000492 | K63: 0.0553 | L63: 0.22296848 | M63: 0.066279702 | N63: 2.2554076 | O63: 1.5926717 | P63: 11.093234 | Q63: 19.220258 | R63: 2.257678 | S63: 25.084097 | T63: 0.10880574 | U63: 0.034925471 | V63: -0.0063874491 | W63: -0.032337086 | X63: 0.041853468 | Y63: 0.72755742 | Z63: 0.72755742 | AA63: 0.082827709
... A69: Reinsurance | B69: 1 | C69: 0.0966 | D69: 0.05513647 | E69: 0.098903244 | F69: 0.20130577 | G69: 0.57788296 | H69: 0.53732987 | I69: 0.069066383 | J69: 0.19865813 | K69: 0.0508 | L69: 0.26780363 | M69: 0.060773473 | N69: 2.2382479 | O69: 0.64106323 | P69: 11.047015 | Q69: 11.587215 | R69: 1.2543996 | S69: 19.354333 | T69: 0.041100901 | U69: 0 | V69: -0.0019796096 | W69: 0.5108018 | X69: 0.090164951 | Y69: 0.31224209 | Z69: 0.31224209 | AA69: 0.055325049
A70: Restaurant/Dining | B70: 62 | C70: 0.085973077 | D70: 0.15960255 | E70: 0.20394892 | F70: 0.20465304 | G70: 0.87497392 | H70: 1.0090401 | I70: 0.089491435 | J70: 0.41504325 | K70: 0.0553 | L70: 0.18789373 | M70: 0.080469448 | N70: 1.6556715 | O70: 4.4691845 | P70: 18.667677 | Q70: 32.106777 | R70: NA | S70: 56.604438 | T70: -0.0039480913 | U70: 0.062746239 | V70: 0.041463066 | W70: 0.38719269 | X70: NA | Y70: 0.55122729 | Z70: 0.55122729 | AA70: 0.13959271
A71: Retail (Automotive) | B71: 29 | C71: 0.10321762 | D71: 0.060132518 | E71: 0.1211501 | F71: 0.22578359 | G71: 0.9917642 | H71: 1.3530744 | I71: 0.10438812 | J71: 0.47394512 | K71: 0.0578 | L71: 0.33510224 | M71: 0.083934111 | N71: 2.4663966 | O71: 1.2220459 | P71: 14.419928 | Q71: 21.681946 | R71: 7.7770146 | S71: 123.07047 | T71: 0.12188532 | U71: 0.020009322 | V71: 0.024936385 | W71: 0.82898584 | X71: 0.35699249 | Y71: 0.059615562 | Z71: 0.059615562 | AA71: 0.05586664
A72: Retail (Building Supply) | B72: 13 | C72: 0.051490833 | D72: 0.12124631 | E72: 0.36284597 | F72: 0.23817453 | G72: 1.5745466 | H72: 1.7927744 | I72: 0.12342713 | J72: 0.52125982 | K72: 0.0578 | L72: 0.16797788 | M72: 0.10997594 | N72: 3.5706348 | O72: 2.5168841 | P72: 15.746684 | Q72: 20.75233 | R72: NA | S72: 42.963604 | T72: 0.083527571 | U72: 0.02420335 | V72: 0.071570385 | W72: 0.71689216 | X72: NA | Y72: 0.53225823 | Z72: 0.53225823 | AA72: 0.1197749
A73: Retail (Distributors) | B73: 66 | C73: 0.070734146 | D73: 0.10559724 | E73: 0.17536862 | F73: 0.24372011 | G73: 0.92546452 | H73: 1.1171559 | I73: 0.094172851 | J73: 0.43888604 | K73: 0.0553 | L73: 0.23820734 | M73: 0.081619836 | N73: 1.8806345 | O73: 1.8141684 | P73: 12.874163 | Q73: 15.744116 | R73: 4.3031974 | S73: 51.902157 | T73: 0.17020866 | U73: 0.058357263 | V73: 0.076716912 | W73: 1.0195444 | X73: 0.21635699 | Y73: 0.31218552 | Z73: 0.31218552 | AA73: 0.10791544
A74: Retail (General) | B74: 24 | C74: 0.14397421 | D74: 0.062013015 | E74: 0.11983291 | F74: 0.19835938 | G74: 1.0255755 | H74: 1.0617719 | I74: 0.091774725 | J74: 0.46689882 | K74: 0.0578 | L74: 0.080275354 | M74: 0.087887413 | N74: 3.5951299 | O74: 2.0508713 | P74: 18.209022 | Q74: 34.662237 | R74: 8.4286881 | S74: 25.792211 | T74: 0.006904932 | U74: 0.057537257 | V74: 0.021600848 | W74: 0.46411455 | X74: 0.25368085 | Y74: 0.14172819 | Z74: 0.14172819 | AA74: 0.059976343
A75: Retail (Grocery and Food) | B75: 17 | C75: 0.09281 | D75: 0.033325605 | E75: 0.092473762 | F75: 0.21096294 | G75: 0.46632353 | H75: 0.57940731 | I75: 0.070888336 | J75: 0.27128246 | K75: 0.0508 | L75: 0.34321553 | M75: 0.05963487 | N75: 4.8930976 | O75: 0.49497247 | P75: 7.7393984 | Q75: 16.885688 | R75: 3.4976886 | S75: 21.115702 | T75: -0.0019956896 | U75: 0.027438742 | V75: 0.0025903701 | W75: 0.14685771 | X75: 0.21090257 | Y75: 0.23669456 | Z75: 0.23669456 | AA75: 0.024582376
A76: Retail (REITs) | B76: 28 | C76: 0.079100385 | D76: 0.38879346 | E76: 0.049993891 | F76: 0.032032946 | G76: 0.68594271 | H76: 0.94758859 | I76: 0.086830586 | J76: 0.23557206 | K76: 0.0508 | L76: 0.35390073 | M76: 0.069584796 | N76: 0.13573525 | O76: 12.217536 | P76: 17.441938 | Q76: 32.774593 | R76: 2.0154999 | S76: 72.235152 | T76: -0.054707258 | U76: 0.042900179 | V76: -0.2657561 | W76: -0.74880213 | X76: 0.073403158 | Y76: 1.4364007 | Z76: 1.4364007 | AA76: 0.37279033
A77: Retail (Special Lines) | B77: 98 | C77: 0.067852742 | D77: 0.050976112 | E77: 0.17678385 | F77: 0.23366273 | G77: 1.0592548 | H77: 1.2239626 | I77: 0.09879758 | J77: 0.56996081 | K77: 0.0578 | L77: 0.22440272 | M77: 0.086354993 | N77: 3.6771871 | O77: 1.069796 | P77: 9.8958884 | Q77: 19.988364 | R77: 5.8712634 | S77: 24.484944 | T77: 0.049479744 | U77: 0.024350613 | V77: 0.0072602823 | W77: 0.23842468 | X77: 0.10134725 | Y77: 0.86426164 | Z77: 0.86426164 | AA77: 0.053157658
A78: Rubber& Tires | B78: 3 | C78: 0.02755 | D78: 0.04043678 | E78: 0.057556754 | F78: #DIV/0! | G78: 0.1780746 | H78: 0.64534539 | I78: 0.073743455 | J78: 0.72036868 | K78: 0.0641 | L78: 0.79471602 | M78: 0.053344323 | N78: 1.5003253 | O78: 0.61570892 | P78: 5.6778845 | Q78: 14.149107 | R78: 0.52615587 | S78: #DIV/0! | T78: 0.12832594 | U78: 0.060576499 | V78: 0.0064504794 | W78: 0.16171849 | X78: -0.064136878 | Y78: #DIV/0! | Z78: #DIV/0! | AA78: 0.042561847
A79: Semiconductor | B79: 63 | C79: 0.051318864 | D79: 0.29711161 | E79: 0.21144652 | F79: 0.14190702 | G79: 1.4601551 | H79: 1.4858715 | I79: 0.11013824 | J79: 0.56048607 | K79: 0.0578 | L79: 0.03747862 | M79: 0.10763511 | N79: 1.1023164 | O79: 14.645136 | P79: 34.479761 | Q79: 48.853838 | R79: 11.12124 | S79: 54.218451 | T79: 0.20345032 | U79: 0.13251552 | V79: 0.1160024 | W79: 0.59308157 | X79: 0.19084697 | Y79: 0.32634632 | Z79: 0.32634632 | AA79: 0.31440194
A80: Semiconductor Equip | B80: 30 | C80: 0.116725 | D80: 0.24062343 | E80: 0.2419745 | F80: 0.12586026 | G80: 1.4745156 | H80: 1.484976 | I80: 0.11009946 | J80: 0.51093071 | K80: 0.0578 | L80: 0.075578011 | M80: 0.10505467 | N80: 1.6833471 | O80: 5.0691664 | P80: 17.733051 | Q80: 20.92614 | R80: 6.970206 | S80: 71.347685 | T80: 0.32724535 | U80: 0.046504015 | V80: 0.021214202 | W80: 0.046679861 | X80: 0.317845 | Y80: 0.20804683 | Z80: 0.20804683 | AA80: 0.24840614
A81: Shipbuilding & Marine | B81: 8 | C81: -0.04268 | D81: 0.13739294 | E81: 0.13232357 | F81: 0.20600372 | G81: 0.52482381 | H81: 0.57844977 | I81: 0.070846875 | J81: 0.451893 | K81: 0.0578 | L81: 0.16046358 | M81: 0.066434628 | N81: 0.93758671 | O81: 1.7491092 | P81: 7.7139416 | Q81: 11.585715 | R81: 1.6051742 | S81: 12.768568 | T81: 0.10341773 | U81: 0.10180449 | V81: 0.046771735 | W81: 0.44179244 | X81: 0.11718744 | Y81: 0.15050902 | Z81: 0.15050902 | AA81: 0.14979424
A82: Shoe | B82: 12 | C82: 0.0990625 | D82: 0.12820574 | E82: 0.29120898 | F82: 0.16763414 | G82: 1.4086385 | H82: 1.4242079 | I82: 0.1074682 | J82: 0.51752412 | K82: 0.0578 | L82: 0.09294188 | M82: 0.10150894 | N82: 2.535627 | O82: 2.4017042 | P82: 14.770185 | Q82: 18.457142 | R82: 6.7412981 | S82: 17.578092 | T82: 0.19568711 | U82: 0.0079440008 | V82: -0.0079457422 | W82: -0.082301891 | X82: 0.31672211 | Y82: 0.32504532 | Z82: 0.32504532 | AA82: 0.13015594
A83: Software (Entertainment) | B83: 81 | C83: 0.28069176 | D83: 0.32367209 | E83: 0.25294353 | F83: 0.15053174 | G83: 1.1833988 | H83: 1.1827821 | I83: 0.097014465 | J83: 0.66628958 | K83: 0.0641 | L83: 0.024296047 | M83: 0.095825429 | N83: 1.3970197 | O83: 7.3454629 | P83: 18.274026 | Q83: 22.459004 | R83: 7.7104509 | S83: 68.179068 | T83: 0.049741425 | U83: 0.15069196 | V83: 0.1138597 | W83: 0.47974527 | X83: 0.33456424 | Y83: 0.059483802 | Z83: 0.059483802 | AA83: 0.33505218
A84: Software (Internet) | B84: 29 | C84: 0.19720833 | D84: 0.013115108 | E84: 0.029315362 | F84: 0.12622973 | G84: 1.5986239 | H84: 1.6870264 | I84: 0.11884824 | J84: 0.55616698 | K84: 0.0578 | L84: 0.10348217 | M84: 0.11103552 | N84: 1.2317197 | O84: 7.5890876 | P84: 28.080067 | Q84: NA | R84: 8.7194278 | S84: 50.641261 | T84: 0.10195018 | U84: 0.042868643 | V84: 0.024250902 | W84: 3.7643907 | X84: -0.030850956 | Y84: 0.00013770325 | Z84: 0.00013770325 | AA84: 0.042337844
A85: Software (System & Application) | B85: 333 | C85: 0.15553155 | D85: 0.28631658 | E85: 0.26854773 | F85: 0.17372114 | G85: 1.2190339 | H85: 1.2417608 | I85: 0.099568244 | J85: 0.63628486 | K85: 0.0578 | L85: 0.046671098 | M85: 0.096944477 | N85: 1.7141776 | O85: 11.543735 | P85: 27.978212 | Q85: 37.850738 | R85: 10.733766 | S85: 203.77193 | T85: 0.10581056 | U85: 0.11958977 | V85: 0.21011598 | W85: 0.93539436 | X85: 0.27664222 | Y85: 0.23176224 | Z85: 0.23176224 | AA85: 0.30049989
A86: Steel | B86: 27 | C86: 0.060515833 | D86: 0.076058229 | E86: 0.12494672 | F86: 0.18669408 | G86: 0.96393903 | H86: 1.0597792 | I86: 0.09168844 | J86: 0.46790274 | K86: 0.0578 | L86: 0.2056982 | M86: 0.08174531 | N86: 1.8550047 | O86: 0.88738812 | P86: 7.5173169 | Q86: 11.5665 | R86: 1.4229678 | S86: 15.022571 | T86: 0.19146593 | U86: 0.0753058 | V86: 0.049794273 | W86: 0.60845246 | X86: 0.10041297 | Y86: 0.20943524 | Z86: 0.20943524 | AA86: 0.076474907
A87: Telecom (Wireless) | B87: 11 | C87: 0.2806725 | D87: 0.20147396 | E87: 0.083054259 | F87: 0.24089288 | G87: 0.58526739 | H87: 0.77253915 | I87: 0.079250945 | J87: 0.66732691 | K87: 0.0641 | L87: 0.32254088 | M87: 0.069195428 | N87: 0.51675463 | O87: 4.1515031 | P87: 9.843702 | Q87: 21.967972 | R87: 3.5080037 | S87: 13.359763 | T87: 0.090352075 | U87: 0.11373823 | V87: -0.047718938 | W87: 0.068221276 | X87: 0.13417482 | Y87: 0.31533667 | Z87: 0.31533667 | AA87: 0.18900873
A88: Telecom. Equipment | B88: 61 | C88: 0.025522292 | D88: 0.1749072 | E88: 0.21770547 | F88: 0.10244037 | G88: 0.94839632 | H88: 0.99961465 | I88: 0.089083314 | J88: 0.56093443 | K88: 0.0578 | L88: 0.11350801 | M88: 0.083892217 | N88: 2.6691836 | O88: 5.4799001 | P88: 21.766351 | Q88: 29.902931 | R88: 6.9110047 | S88: 46.055972 | T88: 0.24911289 | U88: 0.029582184 | V88: 0.26114498 | W88: 1.5162672 | X88: 0.15034528 | Y88: 0.66912958 | Z88: 0.66912958 | AA88: 0.18414536
A89: Telecom. Services | B89: 32 | C89: 0.105799 | D89: 0.20346195 | E89: 0.11685865 | F89: 0.2830167 | G89: 0.51507264 | H89: 0.88603861 | I89: 0.084165472 | J89: 0.63709118 | K89: 0.0578 | L89: 0.50041698 | M89: 0.063740717 | N89: 0.59226786 | O89: 2.5635059 | P89: 6.6189662 | Q89: 12.281154 | R89: 1.6220826 | S89: 25.51708 | T89: -0.026194258 | U89: 0.14643747 | V89: 0.0016218817 | W89: 0.038956674 | X89: 0.077465138 | Y89: 1.1784208 | Z89: 1.1784208 | AA89: 0.20646024
A90: Tobacco | B90: 12 | C90: -0.0051542857 | D90: 0.41046961 | E90: 0.57899212 | F90: 0.2208949 | G90: 0.82503984 | H90: 0.97996825 | I90: 0.088232625 | J90: 0.68343251 | K90: 0.0641 | L90: 0.21850684 | M90: 0.07945791 | N90: 1.7295164 | O90: 5.537374 | P90: 12.35153 | Q90: 13.422569 | R90: NA | S90: 15.289643 | T90: 0.1522185 | U90: 0.027304165 | V90: -0.0060251026 | W90: -0.013103944 | X90: NA | Y90: 0.74476752 | Z90: 0.74476752 | AA90: 0.41216608
A91: Transportation | B91: 21 | C91: 0.085724286 | D91: 0.068344413 | E91: 0.10895424 | F91: 0.19644394 | G91: 0.83234679 | H91: 1.0268991 | I91: 0.09026473 | J91: 0.5167534 | K91: 0.0578 | L91: 0.27905062 | M91: 0.077173146 | N91: 1.9438034 | O91: 1.5760402 | P91: 11.794226 | Q91: 21.822021 | R91: 4.8854505 | S91: 24.832803 | T91: 0.070722195 | U91: 0.056130369 | V91: 0.034716455 | W91: 1.0095106 | X91: 0.17324664 | Y91: 0.59783163 | Z91: 0.59783163 | AA91: 0.068305927
A92: Transportation (Railroads) | B92: 4 | C92: 0.0223 | D92: 0.3831353 | E92: 0.15062156 | F92: 0.23259322 | G92: 0.82680428 | H92: 0.99185611 | I92: 0.088747369 | J92: 0.26559953 | K92: 0.0508 | L92: 0.22113828 | M92: 0.077547297 | N92: 0.4750981 | O92: 6.2760962 | P92: 12.558834 | Q92: 16.403979 | R92: 5.7917933 | S92: 19.927687 | T92: 0.0101276 | U92: 0.19882191 | V92: 0.094309272 | W92: 0.31893682 | X92: 0.31992256 | Y92: 0.42724562 | Z92: 0.42724562 | AA92: 0.38259597
A93: Trucking | B93: 24 | C93: 0.10226278 | D93: 0.069683457 | E93: 0.092994405 | F93: 0.2409142 | G93: 0.96465363 | H93: 1.1048132 | I93: 0.093638412 | J93: 0.32180094 | K93: 0.0553 | L93: 0.18643278 | M93: 0.083913442 | N93: 1.6281747 | O93: 1.8533739 | P93: 11.329963 | Q93: 25.314405 | R93: 3.2266705 | S93: 335.51513 | T93: 0.070440299 | U93: 0.14730259 | V93: 0.090853694 | W93: 1.642234 | X93: 0.093236257 | Y93: 0.23428414 | Z93: 0.23428414 | AA93: 0.071616273
A94: Utility (General) | B94: 14 | C94: 0.023622143 | D94: 0.23277004 | E94: 0.060541914 | F94: 0.10640099 | G94: 0.25018074 | H94: 0.39343775 | I94: 0.062835854 | J94: 0.18214476 | K94: 0.0508 | L94: 0.43837817 | M94: 0.051992196 | N94: 0.29371423 | O94: 5.2386034 | P94: 13.439817 | Q94: 22.708467 | R94: 1.8234184 | S94: 18.717166 | T94: 0.060863153 | U94: 0.46439281 | V94: 0.30653922 | W94: 1.5320811 | X94: 0.10812006 | Y94: 0.63228137 | Z94: 0.63228137 | AA94: 0.23068944
A95: Utility (Water) | B95: 15 | C95: 0.11646667 | D95: 0.33106424 | E95: 0.069592373 | F95: 0.16358857 | G95: 0.47321202 | H95: 0.6785672 | I95: 0.07518196 | J95: 0.2916778 | K95: 0.0508 | L95: 0.36963857 | M95: 0.061475037 | N95: 0.23750271 | O95: 7.5093193 | P95: 15.027217 | Q95: 22.558596 | R95: 2.0547679 | S95: 23.134377 | T95: 0.10763974 | U95: 0.55872847 | V95: 0.4184203 | W95: 1.5664814 | X95: 0.15933623 | Y95: 0.57826181 | Z95: 0.37933536 | AA95: 0.33063786
A96: Total Market | B96: 6062 | C96: 0.09966282 | D96: 0.12082027 | E96: 0.08728271 | F96: 0.19324456 | G96: 0.81675188 | H96: 1.0027797 | I96: 0.08922036 | J96: 0.52532639 | K96: 0.0578 | L96: 0.28151279 | M96: 0.076307267 | N96: 0.84312697 | O96: 3.6461555 | P96: 18.59758 | Q96: 28.265743 | R96: 4.3086019 | S96: 48.856127 | T96: -0.21701985 | U96: 0.05875143 | V96: 0.04214832 | W96: 0.47727232 | X96: 0.15933623 | Y96: 0.37933536 | Z96: 0.37933536 | AA96: 0.12264078
A97: Total Market (without financials) | B97: 4935 | C97: 0.10246298 | D97: 0.11934235 | E97: 0.15008473 | F97: 0.19335598 | G97: 0.97679306 | H97: 1.0857817 | I97: 0.092814347 | J97: 0.57396285 | K97: 0.0578 | L97: 0.16170905 | M97: 0.084815514 | N97: 1.5606598 | O97: 2.9877223 | P97: 15.831102 | Q97: 24.411761 | R97: 5.0970317 | S97: 53.282763 | T97: 0.082522039 | U97: 0.060781593 | V97: 0.043473903 | W97: 0.50790119 | X97: 0.16407375 | Y97: 0.39682648 | Z97: 0.39682648 | AA97: 0.12132099

Sheet Input Stat Distributioons
C1: Revenue Growth Rate = Last 3 years | F1: Pre-tax Operating Margin | I1: Sales to Invested Capital | L1: Cost of Capital | O1: Beta | P1: Debt to Capital Ratio
A2: Industry Group | B2: count | C2: First Quartlie | D2: Median | E2: Third Quartile | F2: First Quartlie | G2: Median | H2: Third Quartile | I2: First Quartlie | J2: Median | K2: Third Quartile | L2: First Quartlie | M2: Median | N2: Third Quartile | O2: median(Beta) | P2: First Quartlie | Q2: Median | R2: Third Quartile
A3: Advertising | B3: 417 | C3: 0.0156 | D3: 0.0691 | E3: 0.157 | F3: -0.034539474 | G3: 0.036944275 | H3: 0.10511594 | I3: 1.2057087 | J3: 2.9656725 | K3: 6.3820225 | L3: 0.10145761 | M3: 0.10778489 | N3: 0.11005605 | O3: 1.090696 | P3: 0.015324421 | Q3: 0.10502959 | R3: 0.31524975 | S3: 0.091552858 | T3: 0.28106528
A4: Aerospace/Defense | B4: 300 | C4: 0.0766 | D4: 0.148 | E4: 0.25 | F4: -0.04434968 | G4: 0.066805963 | H4: 0.13387424 | I4: 0.6856809 | J4: 1.2621202 | K4: 2.152643 | L4: 0.083708583 | M4: 0.089891933 | N4: 0.092745282 | O4: 0.95106882 | P4: 0.0094887713 | Q4: 0.073536924 | R4: 0.21283784 | S4: 0.097744361 | T4: 0.23568301
A5: Air Transport | B5: 151 | C5: 0.0544 | D5: 0.0971 | E5: 0.144 | F5: 0.025615378 | G5: 0.096853416 | H5: 0.16822917 | I5: 0.66394009 | J5: 1.1074567 | K5: 2.1248306 | L5: 0.079692842 | M5: 0.085864406 | N5: 0.10025694 | O5: 1.2435553 | P5: 0.17503681 | Q5: 0.42710861 | R5: 0.60558129 | S5: 0.43675794 | T5: 0.62652889
A6: Apparel | B6: 1194 | C6: 0.0215 | D6: 0.0698 | E6: 0.135 | F6: -0.017258883 | G6: 0.040765766 | H6: 0.087986213 | I6: 0.65214286 | J6: 1.2593733 | K6: 1.9211674 | L6: 0.084954292 | M6: 0.097790358 | N6: 0.10193757 | O6: 0.69969363 | P6: 0.050793651 | Q6: 0.22608438 | R6: 0.51890941 | S6: 0.23447537 | T6: 0.51264045
A7: Auto & Truck | B7: 162 | C7: 0.00896 | D7: 0.0561 | E7: 0.183 | F7: -0.22720259 | G7: 0.02102154 | H7: 0.084959681 | I7: 0.61188811 | J7: 1.3177572 | K7: 2.9151195 | L7: 0.08977339 | M7: 0.097549307 | N7: 0.11189589 | O7: 1.427983 | P7: 0.018491836 | Q7: 0.16030004 | R7: 0.48195052 | S7: 0.13077098 | T7: 0.37923897
A8: Auto Parts | B8: 780 | C8: 0.0174 | D8: 0.0586 | E8: 0.181 | F8: 0.020782571 | G8: 0.051914414 | H8: 0.091092673 | I8: 1.0430839 | J8: 1.6119829 | K8: 2.3565971 | L8: 0.10007819 | M8: 0.10624054 | N8: 0.11355358 | O8: 1.2539606 | P8: 0.046013009 | Q8: 0.19239874 | R8: 0.44497608 | S8: 0.18155645 | T8: 0.41995532
A9: Bank (Money Center) | B9: 621 | C9: 0.0186 | D9: 0.0586 | E9: 0.116 | F9: 0 | G9: 0 | H9: 0 | I9: 0.14918333 | J9: 0.28042283 | K9: 0.51229236 | L9: 0.065439057 | M9: 0.074171629 | N9: 0.10006376 | O9: 0.74911717 | P9: 0.26067096 | Q9: 0.50760201 | R9: 0.70489066 | S9: 0.52342237 | T9: 0.71974504
A10: Banks (Regional) | B10: 849 | C10: 0.012 | D10: 0.0483 | E10: 0.103 | F10: 0 | G10: 0 | H10: 0.0010508218 | I10: 0.1527152 | J10: 0.29540481 | K10: 0.48489315 | L10: 0.054912025 | M10: 0.056516977 | N10: 0.058320907 | O10: 0.51089794 | P10: 0.12924551 | Q10: 0.36332928 | R10: 0.63993015 | S10: 0.40390391 | T10: 0.64856574
A11: Beverage (Alcoholic) | B11: 216 | C11: 0.0102 | D11: 0.0494 | E11: 0.1 | F11: 0.013551913 | G11: 0.089950593 | H11: 0.17411301 | I11: 0.58605341 | J11: 1.1647116 | K11: 2.1699574 | L11: 0.076395299 | M11: 0.082085432 | N11: 0.095178667 | O11: 0.72927647 | P11: 0.0031380753 | Q11: 0.070536953 | R11: 0.29382716 | S11: 0.062278575 | T11: 0.25914834
A12: Beverage (Soft) | B12: 101 | C12: 0.0326 | D12: 0.0612 | E12: 0.121 | F12: -0.089708738 | G12: 0.078109453 | H12: 0.13760794 | I12: 1.2094047 | J12: 1.8431883 | K12: 2.8984664 | L12: 0.074215642 | M12: 0.079325652 | N12: 0.088363548 | O12: 0.42944427 | P12: 0.0045540471 | Q12: 0.054126831 | R12: 0.25508237 | S12: 0.069020998 | T12: 0.31843428
A13: Broadcasting | B13: 126 | C13: -0.00561 | D13: 0.0165 | E13: 0.0417 | F13: -0.018481267 | G13: 0.052188405 | H13: 0.13422354 | I13: 0.5537899 | J13: 0.89201278 | K13: 1.4887255 | L13: 0.075854316 | M13: 0.081436714 | N13: 0.092939217 | O13: 0.91544094 | P13: 0.028128793 | Q13: 0.23558897 | R13: 0.61463621 | S13: 0.27675556 | T13: 0.58266642
A14: Brokerage & Investment Banking | B14: 606 | C14: 0.0185 | D14: 0.0826 | E14: 0.157 | F14: 0 | G14: 0 | H14: 0 | I14: 0.090564025 | J14: 0.26404494 | K14: 0.95993953 | L14: 0.064468816 | M14: 0.072405161 | N14: 0.074032754 | O14: 0.83999422 | P14: 0.0082644628 | Q14: 0.12352309 | R14: 0.52318264 | S14: 0.14216164 | T14: 0.53527194
... A97: Utility (Water) | B97: 102 | C97: 0.00155 | D97: 0.0688 | E97: 0.131 | F97: 0.072075783 | G97: 0.20313374 | H97: 0.27598566 | I97: 0.21020327 | J97: 0.34106955 | K97: 0.59236205 | L97: 0.058785843 | M97: 0.062298383 | N97: 0.066846835 | O97: 0.42112367 | P97: 0.6038672 | Q97: 0.91490264 | R97: 0.06670579 | S97: 0.3233526 | T97: 0.6080076

Sheet Industry Average Beta (Global)
A1: Industry Name | B1: Number of firms | C1: Annual Average Revenue growth - Last 5 years | D1: Pre-tax Operating Margin (Unadjusted) | E1: After-tax ROC | F1: Average effective tax rate | G1: Unlevered Beta | H1: Equity (Levered) Beta | I1: Cost of equity | J1: Std deviation in stock prices | K1: Pre-tax cost of debt | L1: Market Debt/Capital | M1: Cost of capital | N1: Sales/Capital | O1: EV/Sales | P1: EV/EBITDA | Q1: EV/EBIT | R1: Price/Book | S1: Trailing PE | T1: Non-cash WC as % of Revenues | U1: Cap Ex as % of Revenues | V1: Net Cap Ex as % of Revenues | W1: Reinvestment Rate | X1: ROE | Y1: Dividend Payout Ratio | Z1: Equity Reinvestment Rate | AA1: Pre-tax Operating Margin (Lease & R&D adjusted)
A2: Advertising | B2: 417 | C2: 0.068456444 | D2: 0.079130672 | E2: 0.21482336 | F2: 0.27772031 | G2: 1.1531366 | H2: 1.2544098 | I2: 0.1174268 | J2: 0.4740903 | K2: 0.0682 | L2: 0.21907008 | M2: 0.10287467 | N2: 3.3834631 | O2: 1.645724 | P2: 12.920253 | Q2: 19.470706 | R2: 2.8478508 | S2: 83.111457 | T2: 0.0035044234 | U2: 0.017263749 | V2: 0.00040198831 | W2: 0.19188669 | X2: 0.067759425 | Y2: 0.88570342 | Z2: 0.88570342 | AA2: 0.080901123
A3: Aerospace/Defense | B3: 300 | C3: 0.097381374 | D3: 0.079742623 | E3: 0.13729204 | F3: 0.17428077 | G3: 0.95908677 | H3: 1.0371955 | I3: 0.10502386 | J3: 0.4068127 | K3: 0.0657 | L3: 0.15916292 | M3: 0.096127704 | N3: 2.5396296 | O3: 2.4742341 | P3: 17.817018 | Q3: 27.4934 | R3: 5.4193257 | S3: 97.714565 | T3: 0.36921407 | U3: 0.036123988 | V3: 0.025904809 | W3: 0.98982893 | X3: 0.13402939 | Y3: 0.45591558 | Z3: 0.45591558 | AA3: 0.082616419
A4: Air Transport | B4: 151 | C4: 0.047030938 | D4: 0.07844318 | E4: 0.08850245 | F4: 0.1832785 | G4: 0.85051192 | H4: 1.2946168 | I4: 0.11972262 | J4: 0.34980433 | K4: 0.0657 | L4: 0.4803979 | M4: 0.085810293 | N4: 1.337815 | O4: 1.3140939 | P4: 8.859744 | Q4: 16.544136 | R4: 2.3421281 | S4: 42.002026 | T4: -0.029945451 | U4: 0.096295299 | V4: 0.033190937 | W4: 0.53933794 | X4: 0.20573069 | Y4: 0.29684996 | Z4: 0.29684996 | AA4: 0.07803033
A5: Apparel | B5: 1194 | C5: 0.032728794 | D5: 0.14208716 | E5: 0.18859814 | F5: 0.25196081 | G5: 0.69442861 | H5: 0.75053974 | I5: 0.088655819 | J5: 0.38575066 | K5: 0.0657 | L5: 0.16416614 | M5: 0.082167093 | N5: 1.5685524 | O5: 2.3000825 | P5: 12.737552 | Q5: 15.694507 | R5: 3.1878093 | S5: 50.668188 | T5: 0.23010529 | U5: 0.048569456 | V5: 0.036380363 | W5: 0.47113929 | X5: 0.14562583 | Y5: 0.52340317 | Z5: 0.52340317 | AA5: 0.14362963
A6: Auto & Truck | B6: 162 | C6: 0.12695689 | D6: 0.067066397 | E6: 0.071428459 | F6: 0.23279849 | G6: 1.2450164 | H6: 1.5289122 | I6: 0.13310089 | J6: 0.4791066 | K6: 0.0682 | L6: 0.33160162 | M6: 0.10587609 | N6: 1.3255157 | O6: 1.3688005 | P6: 12.125556 | Q6: 19.801842 | R6: 1.9254464 | S6: 280.7109 | T6: 0.048572617 | U6: 0.066225062 | V6: 0.042017509 | W6: 0.77049467 | X6: 0.11597866 | Y6: 0.30537678 | Z6: 0.30537678 | AA6: 0.070078491
A7: Auto Parts | B7: 780 | C7: 0.075551745 | D7: 0.052685484 | E7: 0.079377704 | F7: 0.22585506 | G7: 1.1857072 | H7: 1.2988008 | I7: 0.11996153 | J7: 0.36388827 | K7: 0.0657 | L7: 0.26425915 | M7: 0.10124377 | N7: 2.0899722 | O7: 0.73745546 | P7: 7.2426585 | Q7: 13.350116 | R7: 1.2997942 | S7: 44.145381 | T7: 0.11844075 | U7: 0.051831987 | V7: 0.032074039 | W7: 0.90977623 | X7: 0.072108599 | Y7: 0.42003285 | Z7: 0.42003285 | AA7: 0.056199116
A8: Bank (Money Center) | B8: 621 | C8: 0.13966549 | D8: NA | E8: NA | F8: 0.19221418 | G8: 0.38784573 | H8: 0.79703325 | I8: 0.091310598 | J8: 0.23784038 | K8: 0.0612 | L8: 0.72605945 | M8: 0.058242048 | N8: 0 | O8: NA | P8: NA | Q8: NA | R8: 0.90353181 | S8: 15.369409 | T8: NA | U8: NA | V8: NA | W8: NA | X8: 0.11993771 | Y8: 0.38292304 | Z8: 0.38292304 | AA8: NA
A9: Banks (Regional) | B9: 849 | C9: 0.070516584 | D9: NA | E9: NA | F9: 0.19066731 | G9: 0.32581147 | H9: 0.55704109 | I9: 0.077607046 | J9: 0.27469873 | K9: 0.0612 | L9: 0.69353807 | M9: 0.055523625 | N9: 0 | O9: NA | P9: NA | Q9: NA | R9: 0.7802286 | S9: 16.319062 | T9: NA | U9: NA | V9: NA | W9: NA | X9: 0.07595581 | Y9: 0.39896722 | Z9: 0.39896722 | AA9: NA
A10: Beverage (Alcoholic) | B10: 216 | C10: 0.08466419 | D10: 0.22475441 | E10: 0.15898286 | F10: 0.24907092 | G10: 0.78231423 | H10: 0.86351324 | I10: 0.095106606 | J10: 0.32159699 | K10: 0.0657 | L10: 0.19010887 | M10: 0.086366133 | N10: 0.84834844 | O10: 2.9382466 | P10: 10.864404 | Q10: 12.94736 | R10: 2.3889454 | S10: 37.119178 | T10: 0.1003332 | U10: 0.049327755 | V10: 0.014771796 | W10: 0.14851682 | X10: 0.12953691 | Y10: 0.58559872 | Z10: 0.58559872 | AA10: 0.22401121
A11: Beverage (Soft) | B11: 101 | C11: 0.072841746 | D11: 0.17273826 | E11: 0.26466406 | F11: 0.21237669 | G11: 0.5241587 | H11: 0.57262637 | I11: 0.078496966 | J11: 0.34852094 | K11: 0.0657 | L11: 0.15617531 | M11: 0.073910642 | N11: 1.7731796 | O11: 3.3731471 | P11: 15.971324 | Q11: 19.414654 | R11: 6.0639454 | S11: 27.394976 | T11: -0.066279154 | U11: 0.055461522 | V11: 0.034472421 | W11: 0.32446841 | X11: 0.26342971 | Y11: 0.64471334 | Z11: 0.64471334 | AA11: 0.17363889
A12: Broadcasting | B12: 126 | C12: 0.015663524 | D12: 0.10026649 | E12: 0.091187664 | F12: 0.24870391 | G12: 0.69938066 | H12: 1.0043908 | I12: 0.10315072 | J12: 0.39297439 | K12: 0.0657 | L12: 0.45516248 | M12: 0.078562722 | N12: 1.0683894 | O12: 1.1959706 | P12: 7.4336341 | Q12: 11.248086 | R12: 0.86208535 | S12: 81.554915 | T12: 0.14311965 | U12: 0.033601496 | V12: -0.0097096432 | W12: 1.4386473 | X12: -0.01794367 | Y12: 0.0060205969 | Z12: 0.0060205969 | AA12: 0.10006439
A13: Brokerage & Investment Banking | B13: 606 | C13: 0.19713918 | D13: NA | E13: NA | F13: 0.19425314 | G13: 0.40657975 | H13: 0.9085138 | I13: 0.097676138 | J13: 0.38888892 | K13: 0.0657 | L13: 0.68400208 | M13: 0.064470793 | N13: 0 | O13: NA | P13: NA | Q13: NA | R13: 1.4657789 | S13: 101.58408 | T13: NA | U13: NA | V13: NA | W13: NA | X13: 0.088577419 | Y13: 0.52114264 | Z13: 0.52114264 | AA13: NA
A14: Building Materials | B14: 462 | C14: 0.047801337 | D14: 0.1055074 | E14: 0.15629327 | F14: 0.22959365 | G14: 0.93500071 | H14: 1.0264653 | I14: 0.10441117 | J14: 0.31754054 | K14: 0.0657 | L14: 0.17989725 | M14: 0.094466321 | N14: 1.9021251 | O14: 1.7897276 | P14: 11.90787 | Q14: 16.651119 | R14: 2.6995663 | S14: 30.11018 | T14: 0.16970842 | U14: 0.04376842 | V14: 0.066589852 | W14: 0.79082587 | X14: 0.13491465 | Y14: 0.35065128 | Z14: 0.35065128 | AA14: 0.10782325
A15: Business & Consumer Services | B15: 974 | C15: 0.077076274 | D15: 0.097820013 | E15: 0.21417691 | F15: 0.23134745 | G15: 0.94649819 | H15: 1.0155397 | I15: 0.10378732 | J15: 0.38820797 | K15: 0.0657 | L15: 0.1471868 | M15: 0.095742549 | N15: 2.7985866 | O15: 2.2341585 | P15: 15.97957 | Q15: 22.033241 | R15: 4.7263068 | S15: 50.160271 | T15: 0.11117211 | U15: 0.02553366 | V15: 0.0056238531 | W15: 0.15404641 | X15: 0.15996585 | Y15: 0.46928574 | Z15: 0.46928574 | AA15: 0.099408533
A16: Cable TV | B16: 45 | C16: 0.04126878 | D16: 0.17152961 | E16: 0.12395247 | F16: 0.25041302 | G16: 0.59241488 | H16: 1.0687516 | I16: 0.10682572 | J16: 0.38950232 | K16: 0.0657 | L16: 0.53617647 | M16: 0.075890877 | N16: 0.82540081 | O16: 2.3017812 | P16: 7.2771082 | Q16: 13.502589 | R16: 1.4440953 | S16: 63.461615 | T16: 0.023338171 | U16: 0.1284074 | V16: -0.0038141169 | W16: 0.046504521 | X16: 0.11186833 | Y16: 0.38660463 | Z16: 0.38660463 | AA16: 0.16884225
A17: Chemical (Basic) | B17: 897 | C17: 0.078558569 | D17: 0.043643418 | E17: 0.042117702 | F17: 0.19032897 | G17: 0.90590364 | H17: 1.149282 | I17: 0.111424 | J17: 0.34088887 | K17: 0.0657 | L17: 0.35539198 | M17: 0.089285378 | N17: 1.155938 | O17: 1.1972259 | P17: 10.877089 | Q17: 25.707502 | R17: 1.2126188 | S17: 58.86035 | T17: 0.12904778 | U17: 0.091259645 | V17: 0.057368302 | W17: 0.97814311 | X17: 0.030176306 | Y17: 1.6512525 | Z17: 1.6512525 | AA17: 0.044803982
A18: Chemical (Diversified) | B18: 64 | C18: 0.065249655 | D18: 0.054331135 | E18: 0.047486815 | F18: 0.31321077 | G18: 0.84112979 | H18: 1.1400491 | I18: 0.1108968 | J18: 0.28122767 | K18: 0.0612 | L18: 0.39462038 | M18: 0.085194608 | N18: 1.1517165 | O18: 1.0086359 | P18: 8.4191756 | Q18: 17.463822 | R18: 1.110921 | S18: 29.174003 | T18: 0.19455145 | U18: 0.081398847 | V18: 0.037391689 | W18: 0.87609432 | X18: 0.016669654 | Y18: 2.91801 | Z18: 2.91801 | AA18: 0.055717655
A19: Chemical (Specialty) | B19: 951 | C19: 0.084908076 | D19: 0.10567136 | E19: 0.096274498 | F19: 0.23022632 | G19: 0.94900606 | H19: 1.048814 | I19: 0.10568728 | J19: 0.37283899 | K19: 0.0657 | L19: 0.19388774 | M19: 0.094721606 | N19: 1.1280818 | O19: 2.2179807 | P19: 12.545314 | Q19: 20.102125 | R19: 2.1338927 | S19: 42.713962 | T19: 0.18536199 | U19: 0.09045718 | V19: 0.049438736 | W19: 0.62846707 | X19: 0.074547691 | Y19: 0.67257542 | Z19: 0.67257542 | AA19: 0.10690823
A20: Coal & Related Energy | B20: 216 | C20: 0.074630826 | D20: 0.2074933 | E20: 0.24085864 | F20: 0.2102708 | G20: 1.2437418 | H20: 1.1962107 | I20: 0.11410363 | J20: 0.55612308 | K20: 0.0682 | L20: 0.1604976 | M20: 0.10397564 | N20: 1.3211597 | O20: 1.6107027 | P20: 5.3519535 | Q20: 7.3831426 | R20: 1.5023584 | S20: 38.397651 | T20: -0.027227901 | U20: 0.11453327 | V20: 0.06904728 | W20: 0.63777689 | X20: 0.17139697 | Y20: 0.79855033 | Z20: 0.79855033 | AA20: 0.20788174
A21: Computer Services | B21: 1182 | C21: 0.091584691 | D21: 0.071765132 | E21: 0.20377161 | F21: 0.22494048 | G21: 1.0477595 | H21: 1.09258 | I21: 0.10818632 | J21: 0.39454245 | K21: 0.0657 | L21: 0.12910176 | M21: 0.1005621 | N21: 3.8438543 | O21: 1.5137032 | P21: 15.245954 | Q21: 20.351275 | R21: 4.0209697 | S21: 59.679309 | T21: 0.15935118 | U21: 0.01557147 | V21: 0.01825144 | W21: 0.32694833 | X21: 0.14443881 | Y21: 0.5565591 | Z21: 0.5565591 | AA21: 0.073272657
A22: Computers/Peripherals | B22: 342 | C22: 0.034963609 | D22: 0.13062874 | E22: 0.20415937 | F22: 0.19680017 | G22: 1.2452856 | H22: 1.2618565 | I22: 0.117852 | J22: 0.41480392 | K22: 0.0657 | L22: 0.061860212 | M22: 0.11360087 | N22: 2.4658781 | O22: 3.3510269 | P22: 19.044383 | Q22: 25.458165 | R22: 7.5761694 | S22: 92.110977 | T22: 0.029771803 | U22: 0.048325901 | V22: 0.036192197 | W22: 0.34307128 | X22: 0.26403231 | Y22: 0.2542751 | Z22: 0.2542751 | AA22: 0.13536126
A23: Construction Supplies | B23: 804 | C23: 0.093048898 | D23: 0.094591148 | E23: 0.097290499 | F23: 0.23089861 | G23: 0.8467977 | H23: 0.97817929 | I23: 0.10165404 | J23: 0.35215653 | K23: 0.0657 | L23: 0.27237045 | M23: 0.087348167 | N23: 1.2994151 | O23: 1.4443805 | P23: 10.268126 | Q23: 14.965943 | R23: 1.6552859 | S23: 69.547936 | T23: 0.16694498 | U23: 0.052150183 | V23: 0.031958498 | W23: 0.54186017 | X23: 0.10186002 | Y23: 0.446869 | Z23: 0.446869 | AA23: 0.096370212
A24: Diversified | B24: 335 | C24: 0.1245467 | D24: 0.19126688 | E24: 0.13052165 | F24: 0.16667693 | G24: 0.69550763 | H24: 0.88856195 | I24: 0.096536887 | J24: 0.29019575 | K24: 0.0612 | L24: 0.33459935 | M24: 0.079548767 | N24: 0.80990478 | O24: 1.9598135 | P24: 8.3981307 | Q24: 10.126119 | R24: 1.1389673 | S24: 23.624757 | T24: -0.10274985 | U24: 0.050695894 | V24: 0.027932501 | W24: 0.22130687 | X24: 0.15189768 | Y24: 0.15552381 | Z24: 0.15552381 | AA24: 0.19127387
A25: Drugs (Biotechnology) | B25: 1223 | C25: 0.25387421 | D25: 0.0017550043 | E25: 0.019137906 | F25: 0.1725664 | G25: 1.2281686 | H25: 1.29189 | I25: 0.11956692 | J25: 0.70050115 | K25: 0.0745 | L25: 0.1316878 | M25: 0.11115789 | N25: 0.8098586 | O25: 6.7442011 | P25: 15.972191 | Q25: NA | R25: 4.6947249 | S25: 91.229241 | T25: 0.21363003 | U25: 0.045585384 | V25: 0.18843639 | W25: NA | X25: -0.082210733 | Y25: 0.0064958694 | Z25: 0.0064958694 | AA25: 0.046415057
A26: Drugs (Pharmaceutical) | B26: 1271 | C26: 0.12712799 | D26: 0.20418324 | E26: 0.13663933 | F26: 0.16064148 | G26: 0.97444555 | H26: 1.04599 | I26: 0.10552603 | J26: 0.47680688 | K26: 0.0682 | L26: 0.14274968 | M26: 0.097742452 | N26: 1.0855797 | O26: 3.9470093 | P26: 13.408666 | Q26: 18.824918 | R26: 3.7441872 | S26: 73.374286 | T26: 0.16774712 | U26: 0.051463017 | V26: 0.098143128 | W26: 0.64377067 | X26: 0.12357116 | Y26: 0.72629036 | Z26: 0.72629036 | AA26: 0.21726947
A27: Education | B27: 272 | C27: 0.070044431 | D27: 0.13433608 | E27: 0.11595776 | F27: 0.20811151 | G27: 0.78378021 | H27: 0.86268907 | I27: 0.095059546 | J27: 0.42984199 | K27: 0.0657 | L27: 0.22558029 | M27: 0.084698849 | N27: 1.1132733 | O27: 2.31461 | P27: 11.187385 | Q27: 16.921324 | R27: 2.0558121 | S27: 50.526279 | T27: 0.051706754 | U27: 0.055874489 | V27: 0.023931515 | W27: 0.39579365 | X27: 0.067839231 | Y27: 0.6360184 | Z27: 0.6360184 | AA27: 0.13151151
A28: Electrical Equipment | B28: 1101 | C28: 0.10367486 | D28: 0.072910054 | E28: 0.10591672 | F28: 0.18997957 | G28: 1.1801425 | H28: 1.2156684 | I28: 0.11521467 | J28: 0.43176609 | K28: 0.0657 | L28: 0.14665709 | M28: 0.10552295 | N28: 1.8766458 | O28: 2.1500588 | P28: 17.143812 | Q28: 27.802777 | R28: 2.9876406 | S28: 47.215519 | T28: 0.23318263 | U28: 0.07118995 | V28: 0.066381329 | W28: 1.3156207 | X28: 0.091174666 | Y28: 0.55243609 | Z28: 0.55243609 | AA28: 0.07570009
A29: Electronics (Consumer & Office) | B29: 125 | C29: 0.021197961 | D29: 0.058005556 | E29: 0.10563965 | F29: 0.21689689 | G29: 1.1198909 | H29: 1.2099502 | I29: 0.11488816 | J29: 0.45184781 | K29: 0.0682 | L29: 0.21344317 | M29: 0.10125166 | N29: 2.0670829 | O29: 0.95581523 | P29: 10.518161 | Q29: 16.117105 | R29: 1.7815825 | S29: 33.498846 | T29: 0.049128229 | U29: 0.044635348 | V29: 0.050417669 | W29: 1.0045942 | X29: 0.093154717 | Y29: 0.26621712 | Z29: 0.26621712 | AA29: 0.073430943
A30: Electronics (General) | B30: 1480 | C30: 0.05836875 | D30: 0.058477566 | E30: 0.077569989 | F30: 0.16900845 | G30: 1.3619378 | H30: 1.3767896 | I30: 0.12441468 | J30: 0.41931738 | K30: 0.0657 | L30: 0.14890115 | M30: 0.11320478 | N30: 1.7214522 | O30: 1.6413704 | P30: 13.898834 | Q30: 26.487675 | R30: 2.30998 | S30: 70.860834 | T30: 0.19103083 | U30: 0.05911668 | V30: 0.035242926 | W30: 0.804804 | X30: 0.0795421 | Y30: 0.52682904 | Z30: 0.52682904 | AA30: 0.061680091
A31: Engineering/Construction | B31: 1327 | C31: 0.067785063 | D31: 0.048119138 | E31: 0.077848896 | F31: 0.22533743 | G31: 0.66313405 | H31: 0.92879865 | I31: 0.098834403 | J31: 0.37039888 | K31: 0.0657 | L31: 0.48473411 | M31: 0.074741206 | N31: 2.1204934 | O31: 0.69293735 | P31: 9.9450246 | Q31: 13.874886 | R31: 1.0793295 | S31: 40.073374 | T31: 0.15915697 | U31: 0.10185507 | V31: 0.092472439 | W31: 1.6076086 | X31: 0.094666687 | Y31: 0.68362282 | Z31: 0.68362282 | AA31: 0.048665931
A32: Entertainment | B32: 748 | C32: 0.090673049 | D32: 0.092377329 | E32: 0.096520741 | F32: 0.21491863 | G32: 0.9946761 | H32: 1.0554393 | I32: 0.10606558 | J32: 0.47466302 | K32: 0.0682 | L32: 0.15039781 | M32: 0.097783833 | N32: 1.3248975 | O32: 3.3973576 | P32: 10.018114 | Q32: 35.037372 | R32: 3.148312 | S32: 75.605023 | T32: 0.025583647 | U32: 0.14379702 | V32: 0.077895712 | W32: 28.107358 | X32: 0.015830257 | Y32: 1.5537994 | Z32: 1.5537994 | AA32: 0.093564576
A33: Environmental & Waste Services | B33: 391 | C33: 0.086715972 | D33: 0.11387736 | E33: 0.11120965 | F33: 0.21895077 | G33: 0.85595082 | H33: 1.0297058 | I33: 0.1045962 | J33: 0.42938192 | K33: 0.0657 | L33: 0.25587569 | M33: 0.090403867 | N33: 1.1393893 | O33: 2.7574507 | P33: 13.975562 | Q33: 23.293638 | R33: 3.0119189 | S33: 44.100858 | T33: 0.16827459 | U33: 0.086631588 | V33: 0.059779432 | W33: 1.0005491 | X33: 0.099550321 | Y33: 0.48887102 | Z33: 0.48887102 | AA33: 0.11487977
A34: Farming/Agriculture | B34: 429 | C34: 0.10853714 | D34: 0.067597823 | E34: 0.075136857 | F34: 0.20940565 | G34: 0.55752414 | H34: 0.77354538 | I34: 0.089969441 | J34: 0.37236302 | K34: 0.0657 | L34: 0.39044782 | M34: 0.07402395 | N34: 1.3429172 | O34: 1.1025697 | P34: 11.01046 | Q34: 15.699243 | R34: 1.6010275 | S34: 207.49712 | T34: 0.17353879 | U34: 0.044746905 | V34: 0.029266163 | W34: 0.43177504 | X34: 0.12141798 | Y34: 0.37246248 | Z34: 0.37246248 | AA34: 0.068982077
A35: Financial Svcs. (Non-bank & Insurance) | B35: 1117 | C35: 0.15429169 | D35: NA | E35: NA | F35: 0.17474488 | G35: 0.27307489 | H35: 0.82085648 | I35: 0.092670905 | J35: 0.40822235 | K35: 0.0657 | L35: 0.7474051 | M35: 0.060128554 | N35: 0 | O35: NA | P35: 46.493361 | Q35: 59.411574 | R35: 2.3699459 | S35: 73.381928 | T35: NA | U35: NA | V35: NA | W35: NA | X35: 0.20077722 | Y35: 0.20913029 | Z35: 0.20913029 | AA35: NA
A36: Food Processing | B36: 1424 | C36: 0.088634766 | D36: 0.084467386 | E36: 0.12288224 | F36: 0.22148943 | G36: 0.57391526 | H36: 0.68123561 | I36: 0.084698553 | J36: 0.32702488 | K36: 0.0657 | L36: 0.2655151 | M36: 0.075254687 | N36: 1.7566913 | O36: 1.3014172 | P36: 10.759608 | Q36: 15.155317 | R36: 2.0450973 | S36: 38.646736 | T36: 0.10267806 | U36: 0.043420696 | V36: 0.025182533 | W36: 0.38792611 | X36: 0.11468592 | Y36: 0.60222322 | Z36: 0.60222322 | AA36: 0.085037585
A37: Food Wholesalers | B37: 188 | C37: 0.10498807 | D37: 0.025910813 | E37: 0.11568187 | F37: 0.22186413 | G37: 0.44056582 | H37: 0.59854812 | I37: 0.079977097 | J37: 0.36762295 | K37: 0.0657 | L37: 0.36926625 | M37: 0.068586475 | N37: 5.3925818 | O37: 0.41608581 | P37: 10.393488 | Q37: 15.929687 | R37: 2.0529541 | S37: 45.134851 | T37: 0.065476896 | U37: 0.011412606 | V37: 0.0096968629 | W37: 0.92897573 | X37: 0.11576016 | Y37: 0.4098871 | Z37: 0.4098871 | AA37: 0.025783349
A38: Furn/Home Furnishings | B38: 380 | C38: 0.050241893 | D38: 0.073618827 | E38: 0.13806763 | F38: 0.17581133 | G38: 0.95133463 | H38: 0.93610405 | I38: 0.099251541 | J38: 0.35335197 | K38: 0.0657 | L38: 0.1986498 | M38: 0.089294999 | N38: 2.5392051 | O38: 1.0822095 | P38: 10.231659 | Q38: 14.106461 | R38: 2.0734337 | S38: 35.63092 | T38: 0.031899069 | U38: 0.032181186 | V38: 0.015116134 | W38: -0.22974119 | X38: 0.13459587 | Y38: 0.6174692 | Z38: 0.6174692 | AA38: 0.076391372
A39: Green & Renewable Energy | B39: 260 | C39: 0.12277535 | D39: 0.30365435 | E39: 0.062926486 | F39: 0.20300952 | G39: 0.59631189 | H39: 0.88597908 | I39: 0.096389406 | J39: 0.38164888 | K39: 0.0657 | L39: 0.42171118 | M39: 0.07645978 | N39: 0.23558645 | O39: 6.9891317 | P39: 13.69759 | Q39: 22.890412 | R39: 1.7709188 | S39: 41.036666 | T39: 0.096460085 | U39: 0.5113711 | V39: 0.27548674 | W39: 1.2755394 | X39: 0.076889108 | Y39: 0.89466576 | Z39: 0.89466576 | AA39: 0.302787
A40: Healthcare Products | B40: 850 | C40: 0.13721645 | D40: 0.13832356 | E40: 0.1218233 | F40: 0.17241351 | G40: 1.0816981 | H40: 1.1457756 | I40: 0.11122379 | J40: 0.4908498 | K40: 0.0682 | L40: 0.12459018 | M40: 0.10372049 | N40: 1.1765514 | O40: 4.3888031 | P40: 19.377323 | Q40: 30.316856 | R40: 3.5219708 | S40: 67.939547 | T40: 0.27893793 | U40: 0.05438362 | V40: 0.041649919 | W40: 0.5380482 | X40: 0.078106321 | Y40: 0.51061568 | Z40: 0.51061568 | AA40: 0.14275881
A41: Healthcare Support Services | B41: 480 | C41: 0.13499156 | D41: 0.035089065 | E41: 0.23334053 | F41: 0.23951022 | G41: 0.73175951 | H41: 0.86832079 | I41: 0.095381117 | J41: 0.41139754 | K41: 0.0657 | L41: 0.27971874 | M41: 0.082443942 | N41: 8.1724893 | O41: 0.54856014 | P41: 10.837306 | Q41: 15.603649 | R41: 2.3248577 | S41: 73.034518 | T41: -0.034464194 | U41: 0.0077418391 | V41: 0.0071607832 | W41: 0.45876009 | X41: 0.094227885 | Y41: 0.46555884 | Z41: 0.46555884 | AA41: 0.034641491
A42: Heathcare Information and Technology | B42: 435 | C42: 0.13021968 | D42: 0.12799841 | E42: 0.11111501 | F42: 0.17487821 | G42: 1.1322537 | H42: 1.2059921 | I42: 0.11466215 | J42: 0.52671259 | K42: 0.0682 | L42: 0.12344133 | M42: 0.10680361 | N42: 1.1152274 | O42: 5.117858 | P42: 21.558804 | Q42: 38.098256 | R42: 3.6674534 | S42: 146.24483 | T42: 0.24428343 | U42: 0.066635167 | V42: 0.064468139 | W42: 0.58530094 | X42: 0.043618945 | Y42: 0.33030864 | Z42: 0.33030864 | AA42: 0.12991519
A43: Homebuilding | B43: 165 | C43: 0.059902348 | D43: 0.12393976 | E43: 0.13610316 | F43: 0.23822705 | G43: 0.94957587 | H43: 1.0677356 | I43: 0.10676771 | J43: 0.33421357 | K43: 0.0657 | L43: 0.2580428 | M43: 0.091894829 | N43: 1.4026521 | O43: 1.1458029 | P43: 8.3146553 | Q43: 9.4632268 | R43: 1.4237005 | S43: 17.251373 | T43: 0.66268539 | U43: 0.0057896922 | V43: 0.0054960747 | W43: 0.48593343 | X43: 0.15264333 | Y43: 0.17225114 | Z43: 0.17225114 | AA43: 0.11997239
A44: Hospitals/Healthcare Facilities | B44: 245 | C44: 0.10104325 | D44: 0.11302582 | E44: 0.12874281 | F44: 0.19476987 | G44: 0.58809202 | H44: 0.77367833 | I44: 0.089977033 | J44: 0.34422329 | K44: 0.0657 | L44: 0.33381945 | M44: 0.076341652 | N44: 1.4074175 | O44: 1.9890357 | P44: 11.947381 | Q44: 17.878504 | R44: 3.227282 | S44: 51.420465 | T44: 0.053432249 | U44: 0.067695067 | V44: 0.03631982 | W44: 0.52320318 | X44: 0.25378012 | Y44: 0.33409825 | Z44: 0.33409825 | AA44: 0.11056841
A45: Hotel/Gaming | B45: 660 | C45: 0.075201727 | D45: 0.15571478 | E45: 0.10909506 | F45: 0.17470172 | G45: 0.74231545 | H45: 0.91305268 | I45: 0.097935308 | J45: 0.37039744 | K45: 0.0657 | L45: 0.29801698 | M45: 0.083390635 | N45: 0.92715963 | O45: 3.3799126 | P45: 14.079987 | Q45: 23.51851 | R45: 4.516437 | S45: 53.997069 | T45: -0.016755297 | U45: 0.067163902 | V45: 0.011232514 | W45: 0.14794105 | X45: 0.14828396 | Y45: 0.30999424 | Z45: 0.30999424 | AA45: 0.14153799
A46: Household Products | B46: 554 | C46: 0.065729732 | D46: 0.16021742 | E46: 0.22277651 | F46: 0.24047783 | G46: 0.82758452 | H46: 0.87995435 | I46: 0.096045393 | J46: 0.3928461 | K46: 0.0657 | L46: 0.12374496 | M46: 0.090239907 | N46: 1.7614342 | O46: 3.0331969 | P46: 15.311206 | Q46: 18.692511 | R46: 4.6956405 | S46: 67.363779 | T46: 0.058834031 | U46: 0.034708927 | V46: 0.024621545 | W46: 0.23145142 | X46: 0.17827339 | Y46: 0.70123489 | Z46: 0.70123489 | AA46: 0.16119327
A47: Information Services | B47: 85 | C47: 0.066317368 | D47: 0.11044125 | E47: 0.21256133 | F47: 0.23667824 | G47: 0.94618581 | H47: 1.124561 | I47: 0.11001244 | J47: 0.41228864 | K47: 0.0657 | L47: 0.25438748 | M47: 0.094524823 | N47: 2.59689 | O47: 1.9465266 | P47: 11.286514 | Q47: 16.835615 | R47: 3.1330702 | S47: 47.86378 | T47: 0.16890947 | U47: 0.02027883 | V47: 0.045093737 | W47: 0.60152156 | X47: 0.13730677 | Y47: 0.37477605 | Z47: 0.37477605 | AA47: 0.11434607
... A50: Insurance (Prop/Cas.) | B50: 240 | C50: 0.11804827 | D50: 0.14728007 | E50: 0.204968 | F50: 0.17571332 | G50: 0.47753753 | H50: 0.49854866 | I50: 0.074267129 | J50: 0.29601677 | K50: 0.0612 | L50: 0.14412768 | M50: 0.070159235 | N50: 1.6841376 | O50: 1.2631239 | P50: 7.966623 | Q50: 8.5317885 | R50: 1.7020451 | S50: 17.683477 | T50: -0.27537504 | U50: 0.0069888741 | V50: 0.0022022869 | W50: 0.017433284 | X50: 0.19981322 | Y50: 0.22294197 | Z50: 0.22294197 | AA50: 0.14756513
A51: Investments & Asset Management | B51: 1291 | C51: 0.1475218 | D51: 0.18799811 | E51: 0.062863428 | F51: 0.16836138 | G51: 0.57516032 | H51: 0.76702681 | I51: 0.089597231 | J51: 0.37580312 | K51: 0.0657 | L51: 0.38145631 | M51: 0.074160926 | N51: 0.36621453 | O51: 5.1390496 | P51: 19.776536 | Q51: 21.922169 | R51: 1.6370771 | S51: 46.242032 | T51: NA | U51: 0.040419358 | V51: 0.04743448 | W51: 0.38395889 | X51: 0.10266771 | Y51: 0.53433367 | Z51: 0.53433367 | AA51: 0.18660043
A52: Machinery | B52: 1548 | C52: 0.065576248 | D52: 0.10246595 | E52: 0.12879276 | F52: 0.21773332 | G52: 1.1230407 | H52: 1.1576883 | I52: 0.111904 | J52: 0.37357026 | K52: 0.0657 | L52: 0.13500058 | M52: 0.10342954 | N52: 1.6428307 | O52: 2.0885541 | P52: 13.952773 | Q52: 19.456207 | R52: 2.7643976 | S52: 79.078822 | T52: 0.28590348 | U52: 0.041186579 | V52: 0.039328099 | W52: 0.65716453 | X52: 0.11487606 | Y52: 0.44634026 | Z52: 0.44634026 | AA52: 0.10466244
A53: Metals & Mining | B53: 1832 | C53: 0.22555768 | D53: 0.10940902 | E53: 0.15028462 | F53: 0.30618329 | G53: 1.0067153 | H53: 1.1212472 | I53: 0.10982322 | J53: 0.69554926 | K53: 0.0745 | L53: 0.2339174 | M53: 0.09716545 | N53: 1.4513326 | O53: 1.2222895 | P53: 7.0211688 | Q53: 10.577327 | R53: 1.665867 | S53: 64.704008 | T53: 0.1247659 | U53: 0.083569178 | V53: 0.0478099 | W53: 0.71295511 | X53: 0.086061058 | Y53: 0.79645908 | Z53: 0.79645908 | AA53: 0.11009707
A54: Office Equipment & Services | B54: 140 | C54: 0.050200417 | D54: 0.073582063 | E54: 0.12805012 | F54: 0.23349151 | G54: 0.72673249 | H54: 0.76010841 | I54: 0.08920219 | J54: 0.35550866 | K54: 0.0657 | L54: 0.2192346 | M54: 0.08041708 | N54: 2.1812278 | O54: 1.0044525 | P54: 8.827085 | Q54: 13.16904 | R54: 1.8026559 | S54: 133.87204 | T54: 0.13156635 | U54: 0.026356483 | V54: 0.007258332 | W54: 0.043640671 | X54: 0.081991966 | Y54: 0.60150665 | Z54: 0.60150665 | AA54: 0.075575133
A55: Oil/Gas (Integrated) | B55: 36 | C55: 0.072163143 | D55: 0.1491379 | E55: 0.16942432 | F55: 0.4240946 | G55: 0.8705119 | H55: 0.93167771 | I55: 0.098998797 | J55: 0.30370602 | K55: 0.0657 | L55: 0.16717889 | M55: 0.090661864 | N55: 1.534047 | O55: 1.2320301 | P55: 5.7550249 | Q55: 8.2293208 | R55: 1.7561518 | S55: 11.847866 | T55: 0.023309152 | U55: 0.082820856 | V55: 0.0156814 | W55: 0.09817507 | X55: 0.14992924 | Y55: 0.78217317 | Z55: 0.78217317 | AA55: 0.1498611
A56: Oil/Gas (Production and Exploration) | B56: 548 | C56: 0.15812939 | D56: 0.31594019 | E56: 0.18249956 | F56: 0.32747213 | G56: 0.89387196 | H56: 1.0156806 | I56: 0.10379536 | J56: 0.50379768 | K56: 0.0682 | L56: 0.22437289 | M56: 0.091949504 | N56: 0.64005923 | O56: 2.5494331 | P56: 4.5585159 | Q56: 7.8694358 | R56: 1.4319196 | S56: 17.96234 | T56: 0.0059598585 | U56: 0.31442503 | V56: 0.14432289 | W56: 0.59162934 | X56: 0.15066651 | Y56: 0.44928169 | Z56: 0.44928169 | AA56: 0.31855474
A57: Oil/Gas Distribution | B57: 179 | C57: 0.090194104 | D57: 0.17409117 | E57: 0.10213475 | F57: 0.16519017 | G57: 0.4713783 | H57: 0.67213343 | I57: 0.084178819 | J57: 0.31500689 | K57: 0.0657 | L57: 0.38697011 | M57: 0.070616152 | N57: 0.66470143 | O57: 2.9100056 | P57: 11.347358 | Q57: 16.226493 | R57: 2.0385178 | S57: 24.232799 | T57: 0.065329282 | U57: 0.14358434 | V57: 0.12400935 | W57: 0.83980368 | X57: 0.16128449 | Y57: 0.69747699 | Z57: 0.69747699 | AA57: 0.17536333
A58: Oilfield Svcs/Equip. | B58: 437 | C58: 0.074979648 | D58: 0.048700399 | E58: 0.10190718 | F58: 0.2304143 | G58: 0.76914615 | H58: 0.95299984 | I58: 0.10021629 | J58: 0.40800245 | K58: 0.0657 | L58: 0.3223038 | M58: 0.083751134 | N58: 2.4092616 | O58: 0.60960486 | P58: 7.5802355 | Q58: 12.034567 | R58: 1.3015925 | S58: 38.633843 | T58: 0.062711257 | U58: 0.041870932 | V58: 0.022181706 | W58: 0.43719647 | X58: 0.096284313 | Y58: 0.51220459 | Z58: 0.51220459 | AA58: 0.049703678
A59: Packaging & Container | B59: 438 | C59: 0.054073194 | D59: 0.082364518 | E59: 0.10687019 | F59: 0.22615724 | G59: 0.61110626 | H59: 0.77880183 | I59: 0.090269585 | J59: 0.33083795 | K59: 0.0657 | L59: 0.32394016 | M59: 0.07694297 | N59: 1.561316 | O59: 1.4527002 | P59: 10.066297 | Q59: 17.20055 | R59: 1.9039653 | S59: 368.70255 | T59: 0.1544468 | U59: 0.063285564 | V59: 0.029401525 | W59: 0.39229167 | X59: 0.11623959 | Y59: 0.50699857 | Z59: 0.50699857 | AA59: 0.083691567
A60: Paper/Forest Products | B60: 269 | C60: 0.031712136 | D60: 0.069877995 | E60: 0.052728667 | F60: 0.20538045 | G60: 0.58691702 | H60: 0.86640849 | I60: 0.095271925 | J60: 0.34316383 | K60: 0.0657 | L60: 0.451023 | M60: 0.074461063 | N60: 0.87332834 | O60: 1.2574427 | P60: 9.3905073 | Q60: 17.422384 | R60: 0.839134 | S60: 564.66421 | T60: 0.23127249 | U60: 0.10016345 | V60: 0.064560554 | W60: 1.1950005 | X60: 0.038734812 | Y60: 0.89287246 | Z60: 0.89287246 | AA60: 0.070743214
A61: Power | B61: 492 | C61: 0.094705962 | D61: 0.14046123 | E61: 0.070509061 | F61: 0.22193021 | G61: 0.42664852 | H61: 0.70294825 | I61: 0.085938345 | J61: 0.28515599 | K61: 0.0612 | L61: 0.49461606 | M61: 0.066068142 | N61: 0.60835934 | O61: 2.2428031 | P61: 9.521225 | Q61: 15.894373 | R61: 1.3092157 | S61: 23.937128 | T61: 0.048894778 | U61: 0.18962667 | V61: 0.11282125 | W61: 1.0749431 | X61: 0.10420386 | Y61: 0.59452605 | Z61: 0.59452605 | AA61: 0.14044341
A62: Precious Metals | B62: 823 | C62: 0.23166027 | D62: 0.12678782 | E62: 0.10269894 | F62: 0.27555218 | G62: 1.1122273 | H62: 1.1733809 | I62: 0.11280005 | J62: 0.70789524 | K62: 0.0745 | L62: 0.15751587 | M62: 0.10380763 | N62: 0.85278951 | O62: 2.3138333 | P62: 8.1912444 | Q62: 16.96133 | R62: 1.6595541 | S62: 43.668298 | T62: 0.10452005 | U62: 0.18342541 | V62: 0.086916996 | W62: 1.1399814 | X62: 0.033011304 | Y62: 1.5292433 | Z62: 1.5292433 | AA62: 0.12719776
A63: Publishing & Newspapers | B63: 321 | C63: 0.012444811 | D63: 0.075547165 | E63: 0.1034345 | F63: 0.18182837 | G63: 0.8404532 | H63: 0.83383464 | I63: 0.093411958 | J63: 0.37553461 | K63: 0.0657 | L63: 0.17225527 | M63: 0.085784236 | N63: 1.6459547 | O63: 1.3284966 | P63: 10.162095 | Q63: 16.334104 | R63: 1.6114673 | S63: 40.614205 | T63: 0.084151006 | U63: 0.036172415 | V63: 0.0026847917 | W63: 0.062371266 | X63: 0.088102396 | Y63: 0.6645051 | Z63: 0.6645051 | AA63: 0.076601905
... A97: Total Market (without financials) | B97: 42750 | C97: 0.086785967 | D97: 0.09777263 | E97: 0.10997032 | F97: 0.22547871 | G97: 0.9151552 | H97: 1.048002 | I97: 0.10564091 | J97: 0.41664367 | K97: 0.0657 | L97: 0.22771762 | M97: 0.092772488 | N97: 1.3815053 | O97: 1.8953803 | P97: 12.152628 | Q97: 18.667602 | R97: 2.5328728 | S97: 77.658971 | T97: 0.12219536 | U97: 0.064765086 | V97: 0.040760209 | W97: 0.71234199 | X97: 0.1112438 | Y97: 0.5354053 | Z97: 0.5354053 | AA97: 0.10142295

Sheet Trailing 12 month
B1: Last 10K | C1: First X months: Last year | D1: First X months: Current year | E1: Trailing 12 month
A2: Revenues | B2: 15794.34 | C2: 7608.13 | D2: 9444.11 | E2: =B2-C2+D2
A3: Technology & Content | B3: 1221.81 | C3: 581.41 | D3: 756 | E3: =B3-C3+D3
A4: Operating income or EBIT | B4: 1605.23 | C4: 908.79 | D4: 1165.5 | E4: =B4-C4+D4
A5: Interest expenses | B5: 420.49 | C5: 182.82 | D5: 287.56 | E5: =B5-C5+D5
A6: Book value of equity | B6: 5238.77 | D6: 6105.55
A7: Book value of debt | B7: 10360 | D7: 12594.14
A8: Do you have operating lease commitments?
A9: Cash and cross holdings | B9: 3794.48 | D9: 5004.25
A10: Non-operating assets | B10: 0 | D10: 0
A11: Minority interests | B11: 0 | D11: 0
A12: Number of shares outstanding =
A13: Current stock price =
A14: Effective tax rate = | B14: =15885/61372 | C14: =6965/27030 | D14: =3941/23906
A15: Marginal tax rate =
A16: Lease commitments
A17: Year 1 | B17: 172.47 | D17: NA
A18: Year 2 | B18: 139.4 | C18: Copy into operating lease worksheet | D18: NA
A19: Year 3 | B19: 145.18 | D19: NA
A20: Year 4 | B20: 156.53 | D20: NA
A21: Year 5 | B21: 151.2 | D21: NA
A22: Beyond year 5 | B22: 943.63 | D22: NA
A25: Current year's lease expense | B25: 107
D29: 75872
D30: 2404
D31: 24171
D32: 276
A36: G&A | B36: 630.29 | C36: 286.14 | D36: 426.61 | E36: =B36-C36+D36
A37: Marketing Costs | B37: 2369.47 | C37: 1128.78 | D37: 1219.73 | E37: =B37-C37+D37
A38: Content Costs | B38: 9967.54 | C38: 4703.01 | D38: 5876.21 | E38: =B38-C38+D38
A40: Content Costs (Cash Flows) | B40: 13043 | C40: 6020.47 | D40: 6322.85 | E40: =B40-C40+D40

Sheet Answer keys
A1: Yes/No | B1: Book or Market Value | C1: ERP choices | D1: Cost of debt | E1: Synthetic rating | F1: Beta | G1: Rating is | H1: Region | I1: Cost of Capital Approach | J1: Reinvestment lag
A2: Yes | B2: B | C2: Will input | D2: Direct input | E2: 1 | F2: Direct input | G2: Aaa/AAA | H2: US | I2: I will input | J2: 0 | K2: First Decile
A3: No | B3: V | C3: Country of incorporation | D3: Synthetic rating | E3: 2 | F3: Single Business(US) | G3: Aa2/AA | H3: Emerging Markets | I3: Detailed | J3: 1 | K3: First Quartile
C4: Operating countries | D4: Actual rating | F4: Single Business(Global) | G4: A1/A+ | H4: Europe | I4: Industry Average | J4: 2 | K4: Median
C5: Operating regions | F5: Multibusiness(US) | G5: A2/A | H5: Japan | I5: Distribution | J5: 3 | K5: Third Quartile
F6: Multibusiness(Global) | G6: A3/A- | H6: Global | K6: Ninth Decile
G7: Baa2/BBB
G8: Ba1/BB+
G9: Ba2/BB
G10: B1/B+
G11: B2/B
G12: B3/B-
G13: C2/C
G14: Ca2/CC
G15: Caa/CCC
G16: D2/D
